Workbook
Name \C: #REF!
Name \C: #REF!
Name \C: #REF!
Name \C: #REF!
Name \C: #REF!
Name \C: #REF!
Name \C: #REF!
Name \C: #REF!
Name \C: #REF!
Name \C: #REF!
Name \C: #REF!
Name \C: #REF!
Name \C: #REF!
Name \C: #REF!
Name \C: #REF!
Name \C: #REF!
Name \C: #REF!
Name \C: #REF!
Name \C: #REF!
Name \C: #REF!
Name \C: #REF!
Name \C: #REF!
Name \C: #REF!
Name \C: #REF!
Name \C: #REF!
Name \C: #REF!
Name \C: #REF!
Name \C: #REF!
Name \C: #REF!
Name \C: #REF!
Name \C: #REF!
Name \C: #REF!
Name \C: #REF!
Name \C: #REF!
Name \C: #REF!
Name \C: #REF!
Name \C: #REF!
Name \C: #REF!
Name \C: #REF!
Name \C: #REF!
Name \C: #REF!
Name \C: #REF!
Name \C: #REF!
Name \D: #REF!
Name \D: #REF!
Name \D: #REF!
Name \D: #REF!
Name \D: #REF!
Name \D: #REF!
Name \D: #REF!
Name \D: #REF!
Name \D: #REF!
Name \D: #REF!
Name \D: #REF!
Name \D: #REF!
Name \D: #REF!
Name \D: #REF!
Name \D: #REF!
Name \D: #REF!
Name \D: #REF!

Sheet Content
C1: Українською | D1: English | E1: 1 | G1: Українською
C2: English | D2: Українською | G2: English
B3: =IF($E$1=1,C3,D3) -> Суми значень можуть не співпадати через заокруглення | C3: Суми значень можуть не співпадати через заокруглення | D3: Numbers may not add up due to rounding
B4: =IF($E$1=1,C4,D4) -> Якщо не позначено інше – пунктирна лінія в графіках означає попередній прогноз | C4: Якщо не позначено інше – пунктирна лінія в графіках означає попередній прогноз | D4: Dotted line in charts refers to previous forecast unless otherwise stated
A6: 0 | B6: =IF($E$1=1,C6,D6) -> Головне | C6: Головне | D6: Summary
A7: 0.1 | B7: ='0.1'!L1 -> Зміна ІСЦ (станом на кінець періоду, % р/р) та інфляційні цілі
A8: 0.2 | B8: ='0.2'!G1 -> Облікова ставка НБУ, середня, %
A10: 1 | B10: =IF($E$1=1,C10,D10) -> Інфляційний розвиток | C10: Інфляційний розвиток | D10: Inflation Developments
A11: 1.1 | B11: ='1.1'!K1 -> Споживча інфляція та оцінки основного інфляційного тренду*, % р/р
A12: 1.2 | B12: ='1.2'!J1 -> Окремі компоненти ІСЦ, % р/р
A13: 1.3 | B13: ='1.3'!M1 -> Внески в зміну цін на продукти харчування*, в. п.
A14: 1.4 | B14: ='1.4'!K1 -> Зміна цін на окремі групи харчових продуктів, % р/р
A15: 1.5 | B15: ='1.5'!J1 -> Роздрібні та гуртові* ціни на пальне в останні місяці, грн/л
A16: 1.6 | B16: ='1.6'!J1 -> Внески в зміну адміністративно регульованих цін, в. п.
A17: 1.7 | B17: ='1.7'!I1 -> Окремі компоненти адміністративної інфляції, % р/р
A18: 1.8 | B18: ='1.8'!I1 -> Інфляційні очікування на наступні 12 місяців та інфляція в річному вимірі, %
A19: 1.9 | B19: ='1.9'!H1 -> Індекс цін виробників (ІЦВ) та його компоненти, % р/р
A20: 1.10 | B20: ='1.10'!G1 -> Ціни на е/е для непобутових споживачів, грн/МВт•год
A21: 1.11 | B21: ='1.11'!H1 -> Компоненти БІСЦ, % р/р
A22: 1.12 | B22: ='1.12'!I1 -> Ануалізовані* зміни основних складових БІСЦ, %
A23: 1.13 | B23: ='1.13'!H1 -> Річна зміна середньої зарплати, %*
A24: 1.14 | B24: ='1.14'!I1 -> Зміна цін на окремі групи послуг, % р/р
A25: 1.15 | B25: ='1.15'!E1 -> Теплова карта БІСЦ*, %
A26: 1.16 | B26: ='1.16'!E1 -> Ануалізовані* зміни ІСЦ та БІСЦ, %
A27: 1.17 | B27: ='1.17'!H1 -> Базовий ІСЦ на кінець періоду, %
A28: 1.18 | B28: ='1.18'!F1 -> Компоненти продовольчої інфляції, зміна на кінець періоду, % р/р
A29: 1.19 | B29: ='1.19'!H1 -> Ціни на сирі продовольчі товари на кінець періоду, %
A30: 1.20 | B30: ='1.20'!G1 -> Окремі компоненти продовольчої інфляції та врожай, зміна на кінець періоду, % р/р
A31: 1.21 | B31: ='1.21'!G1 -> Адміністративно регульовані ціни на кінець періоду, %
A32: 1.22 | B32: ='1.22'!G1 -> Ціни на пальне на кінець періоду, %
A33: 1.23 | B33: ='1.23'!M1 -> ІСЦ на кінець періоду, %
A34: 1.24 | B34: ='1.24'!I1 -> Внески компонентів у річну зміну ІСЦ (в. п.)
A36: 2 | B36: =IF($E$1=1,C36,D36) -> Економічний розвиток | C36: Економічний розвиток | D36: Economic Developments
A37: 2.1 | B37: ='2.1'!H1 -> Індекс промислової продукції за видами економічної діяльності*, % р/р
A38: 2.2 | B38: ='2.2'!K1 -> Індекс ділових очікувань за видами діяльності, %
A39: 2.3 | B39: ='2.3'!F1 -> Індекс вантажо- та пасажирообігу*, % р/р
A40: 2.4 | B40: ='2.4'!H1 -> Індекс будівельної продукції*, % р/р
A41: 2.5 | B41: ='2.5'!F1 -> Нестача працівників як проблема бізнесу, % відповідей
A42: 2.6 | B42: ='2.6'!K1 -> Брак кваліфікованих працівників як чинник, що обмежує спроможності збільшувати виробництво, % відповідей
A43: 2.7 | B43: ='2.7'!H1 -> Сальдо СЗДУ за різними вимірами* та реальний ВВП
A44: 2.8 | B44: ='2.8'!W1 -> Видатки зведеного бюджету, млрд грн (економічна класифікація)
A45: 2.9 | B45: ='2.9'!G1 -> Реальна річна зміна зарплат окремих ВЕД, % р/р*
A46: 2.1 | B46: ='2.10'!F1 -> Індекси обороту роздрібної та оптової торгівлі*, % р/р
A47: 2.11 | B47: ='2.11'!F1 -> Дефіцит зведеного бюджету без грантів у доходах, % ВВП
A48: 2.12 | B48: ='2.12'!B1 -> Реальна зарплата, рівень (логарифми)
A49: 2.13 | B49: ='2.13'!H1 -> Внески в річну зміну фізичних обсягів експорту окремих товарів, в. п.
A50: 2.14 | B50: ='2.14'!K1 -> Внески в річну зміну імпорту товарів, в. п.
A51: 2.15 | B51: ='2.15'!F1 -> Дефіцит е/е, %
A52: 2.16 | B52: ='2.16'!G1 -> Урожай зернових та олійних, млн т
A53: 2.17 | B53: ='2.17'!F1 -> Реальний ВВП, % р/р
A54: 2.18 | B54: ='2.18'!F1 -> Розрив ВВП, % потенційного ВВП
B56: =IF($E$1=1,C56,D56) -> Вставка 1. Економічна війна: як змінюються цілі російських атак і як адаптується українська економіка | C56: Вставка 1. Економічна війна: як змінюються цілі російських атак і як адаптується українська економіка | D56: Box 1. Economic war: how the targets of russian attacks change and how the Ukrainian economy adapts
A57: B.1.1 | B57: ='В.1.1'!F1 -> Імпорт нафтопродуктів і ціни на пальне в Україні, індекс 01.2021 = 100
A58: B.1.2 | B58: ='В.1.2'!G1 -> Експорт вантажів через українські порти, млн т
A59: B.1.3 | B59: ='В.1.3'!F1 -> Атаки рф на об'єкти енергетики та динаміка виробництва, передачі та розподілу е/е
A60: B.1.4 | B60: ='В.1.4'!F1 -> Атаки рф на об'єкти газовидобутку та динаміка виробництва газу й нафти
A61: B.1.5 | B61: ='В.1.5'!I1 -> Частка нових пошкоджень об'єктів виробництва, логістики та бізнесу внаслідок обстрілів рф, %
A62: B.1.6 | B62: ='В.1.6'!I1 -> Кількість нових пошкоджень об'єктів бізнесу внаслідок обстрілів рф
A63: B.1.7 | B63: ='В.1.7'!G1 -> Кількість нових пошкоджень об'єктів логістики й транспортної інфраструктури внаслідок обстрілів рф
A64: B.1.8 | B64: ='В.1.8'!F1 -> Експорт с/г вантажів чорноморськими портами та альтернативними маршрутами, млн т
B66: =IF($E$1=1,C66,D66) -> Вставка 2. Бюджетна декларація на 2027-2029 роки | C66: Вставка 2. Бюджетна декларація на 2027-2029 роки | D66: Box 2. Budget Declaration for 2027-2029
A67: B.2.T.1 | B67: ='B.2.T.1'!C1 -> Таблиця 1. Порівняння сценаріїв, закладених у Бюджетну декларацію, і прогнозу НБУ
A68: B.2.T.2 | B68: ='B.2.T.2'!C1 -> Таблиця 2. Параметри державного бюджету за Сценарієм 1 відповідно до Бюджетної декларації, млрд грн
A70: 3 | B70: =IF($E$1=1,C70,D70) -> Монетарні умови та фінансові ринки | C70: Монетарні умови та фінансові ринки | D70: Monetary Conditions and Financial Markets
A71: 3.1 | B71: ='3.1'!H1 -> Ставки за строковими гривневими депозитами та середньомісячна облікова ставка, %
A72: 3.2 | B72: ='3.2'!H1 -> Середньозважені ставки за гривневими депозитами ФО на строк від трьох місяців (за групами банків), %
A73: 3.3 | B73: ='3.3'!H1 -> Середньомісячні* залишки гривневих депозитів ФО, млрд грн, та частка строкових коштів у портфелі, %
A74: 3.4 | B74: ='3.4'!F1 -> Зміна залишків гривневих ОВДП у портфелі ФО та строкових депозитів ФО, млрд грн
A75: 3.5 | B75: ='3.5'!H1 -> Середньозважені процентні ставки за новими* гривневими кредитами НФК (за розміром підприємств), %
A76: 3.6 | B76: ='3.6'!F1 -> Чисті гривневі кредити, 12.2018 = 100
A77: 3.7 | B77: ='3.7'!H1 -> Курси гривні до долара та євро до долара
A78: 3.8 | B78: ='3.8'!G1 -> Внески в зміну індексу РЕОК, % р/р
A79: 3.9 | B79: ='3.9'!K1 -> Основні компоненти валютних надходжень у країну, млрд дол.
A80: 3.1 | B80: ='3.10'!K1 -> Основні компоненти відпливу валюти, млрд дол.
A81: 3.11 | B81: ='3.11'!G1 -> Чиста купівля клієнтами банків та сальдо продажу іноземної валюти НБУ, млрд дол.
A82: 3.12 | B82: ='3.12'!H1 -> Курсові очікування на наступні 12 місяців, грн/дол.
A83: 3.13 | B83: ='3.13'!L1 -> Широкий базовий баланс, млрд дол.
A84: 3.14 | B84: ='3.14'!F1 -> Валові міжнародні резерви
A85: 3.15 | B85: ='3.15'!O2 -> Фінансування* дефіциту державного бюджету (без урахування грантів у доходах), млрд грн
A86: 3.16 | B86: ='3.16'!H1 -> Первинне розміщення* та погашення гривневих ОВДП, млрд грн
A87: 3.17 | B87: ='3.17'!H1 -> Широкий дефіцит СЗДУ й державний та гарантований державою борг, % ВВП
A88: 3.18 | B88: ='3.18'!I1 -> Облікова ставка, у середньому за квартал %
B90: =IF($E$1=1,C90,D90) -> Вставка 3. Як змінилася комунікація НБУ під час повномасштабної війни: погляд ШІ | C90: Вставка 3. Як змінилася комунікація НБУ під час повномасштабної війни: погляд ШІ | D90: Box 3. How the NBU's communication changed during a full-scale war: an AI perspective
A91: B.3.1 | B91: ='В.3.1'!J1 -> Частка політичної комунікації у звітах за різні періоди
A92: В.3.2 | B92: ='В.3.2'!M1 -> Структура основних цілей та додаткових завдань політичної комунікації за різних періодів
A93: В.3.3 | B93: ='В.3.3'!M1 -> Структура обґрунтувань політичної та структура неполітичної комунікації звітів за різних періодів
A95: 4 | B95: =IF($E$1=1,C95,D95) -> Зовнішні припущення | C95: Зовнішні припущення | D95: External Assumptions
A96: 4.1 | B96: ='4.1'!H1 -> Світові ціни на нафту марки Brent (дол./бар.) та природний газ на нідерландському ринку, TTF (дол./тис.м³)
A97: 4.2 | B97: ='4.2'!G1 -> Видобуток сирої нафти, млн бар./день
A98: 4.3 | B98: ='4.3'!S1 -> Імпорт природного газу до ЄС за джерелом походження, млрд м³
A99: 4.4 | B99: ='4.4'!G1 -> Рівень заповнення газових сховищ у ЄС у відповідному році, %
A100: 4.5 | B100: ='4.5'!I1 -> Світові ціни на окремі зернові та соняшникову олію, дол./т
A101: 4.6 | B101: ='4.6'!H1 -> Світові ціни на сталь та залізну руду, дол./т
A102: 4.7 | B102: ='4.7'!F1 -> Індекс невизначеності глобальної економічної політики (GEPU) та Індекс геополітичних ризиків (GPR)
A103: 4.8 | B103: ='4.8'!J1 -> Реальний ВВП окремих країн та середньозважений показник економічного зростання в країнах – ОТП України (UAwGDP), % р/р
A104: 4.9 | B104: ='4.9'!L1 -> Споживча інфляція окремих країн на кінець періоду та середньозважена інфляція в країнах – ОТП України (UAwCPI), % р/р
A105: 4.1 | B105: ='4.10'!E1 -> Очікувані ринком (за OIS) ключові ставки* на дати відповідних засідань, %

Sheet 0.1
A1: << | C1: =IF(Content!$E$1=1,C2,C3) -> ІСЦ | D1: =IF(Content!$E$1=1,D2,D3) -> Попередній прогноз | E1: =IF(Content!$E$1=1,E2,E3) -> Цільовий діапазон | I1: =IF(Content!$E$1=1,I2,I3) -> Ціль | L1: =IF(Content!$E$1=1,L2,L3) -> Зміна ІСЦ (станом на кінець періоду, % р/р) та інфляційні цілі | V1: =IF(Content!$E$1=1,V2,V3) -> Прогноз | W1: =IF(Content!$E$1=1,W2,W3) -> Горизонт монетарної політики
C2: ІСЦ | D2: Попередній прогноз | E2: Цільовий діапазон | I2: Ціль | L2: Зміна ІСЦ (станом на кінець періоду, % р/р) та інфляційні цілі | V2: Прогноз | W2: Горизонт монетарної політики
C3: CPI | D3: Previous forecast | E3: Tolerance bands | I3: Target | L3: CPI growth (eop, % yoy) and inflation targets | V3: Forecast | W3: Monetary policy horizon
A4: I.17 | B4: I.17 | C4: 15.1 | E4: 9 | F4: 15 | G4: 6 | I4: 12
B5: II.17 | C5: 15.6 | E5: 9 | F5: 15 | G5: 6 | I5: 12
B6: III.17 | C6: 16.4 | E6: 7 | F6: 13 | G6: 6 | I6: 10
B7: IV.17 | C7: 13.7 | E7: 6 | F7: 10 | G7: 4 | I7: 8
A8: I.18 | B8: I.18 | C8: 13.2 | E8: 5.5 | F8: 9.5 | G8: 4 | I8: 7.5
B9: II.18 | C9: 9.9 | E9: 5 | F9: 9 | G9: 4 | I9: 7
B10: III.18 | C10: 8.9 | E10: 4.5 | F10: 8.5 | G10: 4 | I10: 6.5
B11: IV.18 | C11: 9.8 | E11: 4 | F11: 8 | G11: 4 | I11: 6
A12: I.19 | B12: I.19 | C12: 8.6 | E12: 3.75 | F12: 7.75 | G12: 4 | I12: 5.75
B13: II.19 | C13: 9 | E13: 3.5 | F13: 7.5 | G13: 4 | I13: 5.5
B14: III.19 | C14: 7.5 | E14: 3.25 | F14: 7.25 | G14: 4 | I14: 5.25
B15: IV.19 | C15: 4.1 | E15: 4 | F15: 6 | G15: 2 | I15: 5
A16: I.20 | B16: I.20 | C16: 2.3 | E16: 4 | F16: 6 | G16: 2 | I16: 5 | L16: =IF(Content!$E$1=1,L20,L19) -> Джерело: ДССУ, розрахунки НБУ.
B17: II.20 | C17: 2.4 | E17: 4 | F17: 6 | G17: 2 | I17: 5
B18: III.20 | C18: 2.3 | E18: 4 | F18: 6 | G18: 2 | I18: 5
B19: IV.20 | C19: 5 | E19: 4 | F19: 6 | G19: 2 | I19: 5 | L19: Source: SSSU, NBU staff estimates.
A20: I.21 | B20: I.21 | C20: 8.5 | E20: 4 | F20: 6 | G20: 2 | I20: 5 | L20: Джерело: ДССУ, розрахунки НБУ.
B21: II.21 | C21: 9.5 | E21: 4 | F21: 6 | G21: 2 | I21: 5
B22: III.21 | C22: 11 | E22: 4 | F22: 6 | G22: 2 | I22: 5
B23: IV.21 | C23: 10 | E23: 4 | F23: 6 | G23: 2 | I23: 5
A24: I.22 | B24: I.22 | C24: 13.7 | E24: 4 | F24: 6 | G24: 2 | I24: 5
B25: II.22 | C25: 21.5 | E25: 4 | F25: 6 | G25: 2 | I25: 5
B26: III.22 | C26: 24.6 | E26: 4 | F26: 6 | G26: 2 | I26: 5
B27: IV.22 | C27: 26.6 | E27: 4 | F27: 6 | G27: 2 | I27: 5
A28: I.23 | B28: I.23 | C28: 21.3 | E28: 4 | F28: 6 | G28: 2 | I28: 5
B29: II.23 | C29: 12.8 | E29: 4 | F29: 6 | G29: 2 | I29: 5
B30: III.23 | C30: 7.1 | E30: 4 | F30: 6 | G30: 2 | I30: 5
B31: IV.23 | C31: 5.1 | E31: 4 | F31: 6 | G31: 2 | I31: 5
A32: I.24 | B32: I.24 | C32: 3.2 | E32: 4 | F32: 6 | G32: 2 | I32: 5
B33: II.24 | C33: 4.8 | E33: 4 | F33: 6 | G33: 2 | I33: 5
B34: III.24 | C34: 8.6 | E34: 4 | F34: 6 | G34: 2 | I34: 5
B35: IV.24 | C35: 12 | E35: 5 | F35: 6 | I35: 5
A36: I.25 | B36: I.25 | C36: 14.6 | I36: 5
B37: II.25 | C37: 14.3 | I37: 5
B38: III.25 | C38: 11.9 | I38: 5
B39: IV.25 | C39: 8 | I39: 5
A40: I.26 | B40: I.26 | C40: 7.9 | D40: 7.9 | I40: 5
B41: II.26 | C41: 7.2 | D41: 7.3 | I41: 5
B42: III.26 | C42: 8.4 | D42: 8.3 | I42: 5
B43: IV.26 | C43: 10 | D43: 9.4 | I43: 5
A44: I.27 | B44: I.27 | C44: 9.1 | D44: 8.2 | I44: 5
B45: II.27 | C45: 8.7 | D45: 7.5 | I45: 5
B46: III.27 | C46: 7.8 | D46: 6.9 | I46: 5
B47: IV.27 | C47: 6.9 | D47: 6.5 | I47: 5
A48: I.28 | B48: I.28 | C48: 6.1 | D48: 6.1 | I48: 5
B49: II.28 | C49: 5.6 | D49: 5.7 | I49: 5
B50: III.28 | C50: 5.2 | D50: 5.3 | I50: 5
A51: IV.28 | B51: IV.28 | C51: 5 | D51: 5 | I51: 5
A56: II.25
A62: IV.25

Sheet 0.2
A1: << | B1: =IF(Content!$E$1=1,B2,B3) -> Облікова ставка, % | C1: =IF(Content!$E$1=1,C2,C3) -> Попередній прогноз | G1: =IF(Content!$E$1=1,G2,G3) -> Облікова ставка НБУ, середня, %
B2: Облікова ставка, % | C2: Попередній прогноз | G2: Облікова ставка НБУ, середня, %
B3: Key policy rate, % | C3: Previous forecast | G3: NBU`s key policy rate, average, %
A4: I.19 | B4: 18 | C4: 18
B5: 17.6 | C5: 17.6
B6: 17 | C6: 17
B7: 15.3 | C7: 15.3
A8: I.20 | B8: 11.6 | C8: 11.6
B9: 8.1 | C9: 8.1
B10: 6 | C10: 6
B11: 6 | C11: 6
A12: I.21 | B12: 6.1 | C12: 6.1
B13: 7.3 | C13: 7.3
B14: 8 | C14: 8
B15: 8.6 | C15: 8.6
A16: I.22 | B16: 9.8 | C16: 9.8
B17: 14.7 | C17: 14.7
B18: 25 | C18: 25
B19: 25 | C19: 25 | G19: =IF(Content!$E$1=1,G20,G21) -> Джерело: розрахунки НБУ.
A20: I.23 | B20: 25 | C20: 25 | G20: Джерело: розрахунки НБУ.
B21: 25 | C21: 25 | G21: Source: NBU staff estimates.
B22: 22.5 | C22: 22.5
B23: 16.9
A24: I.24 | B24: 14.9
B25: 13.7
B26: 13
B27: 13.1
A28: I.25 | B28: 14.5
B29: 15.5
B30: 15.5
B31: 15.5
A32: I.26 | B32: 15.2
B33: 15 | C33: 15
B34: 15.4 | C34: 15
B35: 16 | C35: 15
A36: I.27 | B36: 16 | C36: 15
B37: 15.3 | C37: 14.3
B38: 14.6 | C38: 13.6
B39: 14 | C39: 13
A40: I.28 | B40: 13.2 | C40: 12.3
B41: 12.4 | C41: 11.7
B42: 11.7 | C42: 11.2
A43: IV.28 | B43: 11.2 | C43: 10.7

Sheet 1.1
A1: << | B1: =IF(Content!$E$1=1,B2,B3) -> ІСЦ | C1: =IF(Content!$E$1=1,C2,C3) -> Базовий ІСЦ | D1: =IF(Content!$E$1=1,D2,D3) -> Нижня межа діапазону | E1: =IF(Content!$E$1=1,E2,E3) -> Показники базової інфляції | F1: =IF(Content!$E$1=1,F2,F3) -> Ціль з інфляції | G1: =IF(Content!$E$1=1,G2,G3) -> Цільовий діапазон | H1: =IF(Content!$E$1=1,H2,H3) -> Верхня лінія цільового діапазону | K1: =IF(Content!$E$1=1,K2,K3) -> Споживча інфляція та оцінки основного інфляційного тренду*, % р/р
B2: ІСЦ | C2: Базовий ІСЦ | D2: Нижня межа діапазону | E2: Показники базової інфляції | F2: Ціль з інфляції | G2: Цільовий діапазон | H2: Верхня лінія цільового діапазону | K2: Споживча інфляція та оцінки основного інфляційного тренду*, % р/р
B3: CPI | C3: Core CPI | D3: Lower bound | E3: Core inflation measures | F3: Inflation target | G3: Target range | H3: Upper target bound | K3: Consumer inflation and estimates of the underlying inflation trends*, % yoy
A4: 45292 | B4: 4.7 | C4: 4.6 | D4: 3.7 | E4: 4.3 | F4: 5 | G4: 4 | H4: 6 | I4: 01.24
A5: 45323 | B5: 4.3 | C5: 4.5 | D5: 3.5 | E5: 4.3 | F5: 5 | G5: 4 | H5: 6
A6: 45352 | B6: 3.2 | C6: 4.2 | D6: 3.1 | E6: 4.4 | F6: 5 | G6: 4 | H6: 6
A7: 45383 | B7: 3.2 | C7: 4.4 | D7: 3.1 | E7: 4.2 | F7: 5 | G7: 4 | H7: 6
A8: 45413 | B8: 3.3 | C8: 4.4 | D8: 3.4 | E8: 4 | F8: 5 | G8: 4 | H8: 6
A9: 45444 | B9: 4.8 | C9: 5 | D9: 3.6 | E9: 4 | F9: 5 | G9: 4 | H9: 6
A10: 45474 | B10: 5.4 | C10: 5.7 | D10: 2.9 | E10: 4.9 | F10: 5 | G10: 4 | H10: 6 | I10: 07.24
A11: 45505 | B11: 7.5 | C11: 6.5 | D11: 4.7 | E11: 3.6 | F11: 5 | G11: 4 | H11: 6
A12: 45536 | B12: 8.6 | C12: 7.3 | D12: 5.3 | E12: 3.8 | F12: 5
A13: 45566 | B13: 9.7 | C13: 8.3 | D13: 5.9 | E13: 4 | F13: 5
A14: 45597 | B14: 11.2 | C14: 9.3 | D14: 6.7 | E14: 4.1 | F14: 5
A15: 45627 | B15: 12 | C15: 10.7 | D15: 7.7 | E15: 3.9 | F15: 5
A16: 45658 | B16: 12.9 | C16: 11.7 | D16: 8.6 | E16: 3.8 | F16: 5 | I16: 01.25
A17: 45689 | B17: 13.4 | C17: 12 | D17: 9.1 | E17: 3.7 | F17: 5
A18: 45717 | B18: 14.6 | C18: 12.4 | D18: 9.6 | E18: 3.8 | F18: 5
A19: 45748 | B19: 15.1 | C19: 12.1 | D19: 9.4 | E19: 4.2 | F19: 5 | K19: =IF(Content!$E$1=1,K32,K34) -> * Детальніше – в Інфляційному звіті за січень 2017 року (стор. 20, 21). Цільовий діапазон діяв до серпня 2024 року включно.
A20: 45778 | B20: 15.9 | C20: 12.3 | D20: 9.6 | E20: 4.6 | F20: 5 | K20: =IF(Content!$E$1=1,K33,K35) -> Джерело: ДССУ, розрахунки НБУ.
A21: 45809 | B21: 14.3 | C21: 12.1 | D21: 9.6 | E21: 4.7 | F21: 5
A22: 45839 | B22: 14.1 | C22: 11.7 | D22: 9.5 | E22: 4.8 | F22: 5 | I22: 07.25
A23: 45870 | B23: 13.2 | C23: 11.4 | D23: 9.1 | E23: 4.9 | F23: 5
A24: 45901 | B24: 11.9 | C24: 11 | D24: 8.6 | E24: 4.8 | F24: 5
A25: 45931 | B25: 10.9 | C25: 10.2 | D25: 7.8 | E25: 5.1 | F25: 5
A26: 45962 | B26: 9.3 | C26: 9.3 | D26: 6.8 | E26: 5.2 | F26: 5
A27: 45992 | B27: 8 | C27: 8 | D27: 5.9 | E27: 5 | F27: 5
A28: 46023 | B28: 7.4 | C28: 7 | D28: 5.8 | E28: 4.3 | F28: 5 | I28: 46023
A29: 46054 | B29: 7.6 | C29: 7 | D29: 6.2 | E29: 3.7 | F29: 5
A30: 46082 | B30: 7.9 | C30: 7.1 | D30: 6.3 | E30: 3.7 | F30: 5
A31: 46113 | B31: 8.6 | C31: 7.6 | D31: 7.1 | E31: 3.4 | F31: 5
A32: 46143 | B32: 8.2 | C32: 7.9 | D32: 7.4 | E32: 3.1 | F32: 5 | K32: * Детальніше – в Інфляційному звіті за січень 2017 року (стор. 20, 21). Цільовий діапазон діяв до серпня 2024 року включно.
A33: 46174 | B33: 7.2 | C33: 8.1 | D33: 7.3 | E33: 2.9 | F33: 5 | I33: 46174 | K33: Джерело: ДССУ, розрахунки НБУ.
K34: * Read more in the January 2017 Inflation Report (pages 20, 21). The target range remained in effect until August 2024 inclusive.
K35: Source: SSSU, NBU staff estimates.

Sheet 1.2
A1: << | B1: =IF(Content!$E$1=1,B2,B3) -> Оброблені продукти | C1: =IF(Content!$E$1=1,C2,C3) -> Сирі продукти | D1: =IF(Content!$E$1=1,D2,D3) -> Адміністративно регульовані ціни | E1: =IF(Content!$E$1=1,E2,E3) -> Непродовольчі товари | F1: =IF(Content!$E$1=1,F2,F3) -> Послуги | G1: =IF(Content!$E$1=1,G2,G3) -> Ціни на паливо | J1: =IF(Content!$E$1=1,J2,J3) -> Окремі компоненти ІСЦ, % р/р
B2: Оброблені продукти | C2: Сирі продукти | D2: Адміністративно регульовані ціни | E2: Непродовольчі товари | F2: Послуги | G2: Ціни на паливо | J2: Окремі компоненти ІСЦ, % р/р
B3: Processed foods | C3: Raw foods | D3: Administered prices | E3: Nonfood products | F3: Services | G3: Fuel prices | J3: Selected CPI components, % yoy
A4: 45292 | B4: 5.5 | C4: 2.1 | D4: 10.4 | E4: -0.2 | F4: 10.1 | G4: -0.1 | H4: 01.24
A5: 45323 | B5: 5.6 | C5: -0.3 | D5: 10.1 | E5: -0.5 | F5: 9.8 | G5: 5
A6: 45352 | B6: 5.3 | C6: -4.9 | D6: 9.9 | E6: -0.9 | F6: 9.7 | G6: 11.2
A7: 45383 | B7: 5.5 | C7: -6.5 | D7: 9.5 | E7: -0.6 | F7: 9.7 | G7: 18.1
A8: 45413 | B8: 5.3 | C8: -6.6 | D8: 9.4 | E8: -0.3 | F8: 9.7 | G8: 22.5
A9: 45444 | B9: 5.9 | C9: -6.5 | D9: 13.3 | E9: 0.4 | F9: 9.9 | G9: 25.5
A10: 45474 | B10: 6.5 | C10: -4.8 | D10: 13.4 | E10: 1.2 | F10: 10.3 | G10: 17.6 | H10: 07.24
A11: 45505 | B11: 7.4 | C11: 3.7 | D11: 13.7 | E11: 1.9 | F11: 10.5 | G11: 10.1
A12: 45536 | B12: 8.9 | C12: 7.1 | D12: 14 | E12: 2.2 | F12: 10.9 | G12: 6
A13: 45566 | B13: 10.7 | C13: 10.5 | D13: 14.5 | E13: 2.9 | F13: 11 | G13: 3.2
A14: 45597 | B14: 12.5 | C14: 15.7 | D14: 15.1 | E14: 3.6 | F14: 11.2 | G14: 0.6
A15: 45627 | B15: 14.7 | C15: 13.2 | D15: 16.3 | E15: 4.1 | F15: 12.5 | G15: 4.8
A16: 45658 | B16: 15.9 | C16: 11.8 | D16: 17.5 | E16: 4.3 | F16: 14.2 | G16: 12.1 | H16: 01.25
A17: 45689 | B17: 16.7 | C17: 13 | D17: 18.1 | E17: 4.4 | F17: 14.3 | G17: 13.9
A18: 45717 | B18: 17.3 | C18: 17 | D18: 19 | E18: 4.7 | F18: 14.6 | G18: 9.9
A19: 45748 | B19: 17.3 | C19: 22.2 | D19: 19.5 | E19: 3.8 | F19: 14.6 | G19: 3.7 | J19: =IF(Content!$E$1=1,J21,J23) -> Джерело: ДССУ, розрахунки НБУ.
A20: 45778 | B20: 18 | C20: 26.4 | D20: 19.8 | E20: 3.8 | F20: 14.6 | G20: 1.2
A21: 45809 | B21: 18.2 | C21: 28.7 | D21: 10.9 | E21: 3.6 | F21: 14.4 | G21: 3.1 | J21: Джерело: ДССУ, розрахунки НБУ.
A22: 45839 | B22: 18 | C22: 28 | D22: 11 | E22: 3.2 | F22: 14 | G22: 6.7 | H22: 07.25
A23: 45870 | B23: 17.7 | C23: 23.9 | D23: 10.8 | E23: 2.8 | F23: 14.1 | G23: 6 | J23: Source: SSSU, NBU staff estimates.
A24: 45901 | B24: 16.8 | C24: 18.1 | D24: 10.7 | E24: 2.3 | F24: 14.1 | G24: 4.7
A25: 45931 | B25: 15.6 | C25: 15.2 | D25: 10.6 | E25: 1.6 | F25: 13.8 | G25: 3.9
A26: 45962 | B26: 13.9 | C26: 9.6 | D26: 10.4 | E26: 0.8 | F26: 13.4 | G26: 5.3
A27: 45992 | B27: 12.1 | C27: 7.4 | D27: 9.7 | E27: 0 | F27: 12.3 | G27: 6.4
A28: 46023 | B28: 10.8 | C28: 8.2 | D28: 9.1 | E28: -0.4 | F28: 11.2 | G28: 5.7 | H28: 46023
A29: 46054 | B29: 9.9 | C29: 9.6 | D29: 8.8 | E29: -0.4 | F29: 12.3 | G29: 8
A30: 46082 | B30: 10 | C30: 8.4 | D30: 8.6 | E30: -0.5 | F30: 12.8 | G30: 23.4
A31: 46113 | B31: 10.2 | C31: 8.3 | D31: 9.4 | E31: 0.3 | F31: 13.3 | G31: 36.1
A32: 46143 | B32: 10.4 | C32: 4.6 | D32: 10.2 | E32: 0.3 | F32: 13.6 | G32: 38.7
A33: 46174 | B33: 10.4 | C33: -0.2 | D33: 10.7 | E33: 0.5 | F33: 13.7 | G33: 33.4 | H33: 46174

Sheet 1.3
A1: << | B1: =IF(Content!$E$1=1,B2,B3) -> Продукти харчування, % р/р | C1: =IF(Content!$E$1=1,C2,C3) -> Хліб, крупи, макарони | D1: =IF(Content!$E$1=1,D2,D3) -> Молочні продукти | E1: =IF(Content!$E$1=1,E2,E3) -> Яйця | F1: =IF(Content!$E$1=1,F2,F3) -> М'ясо та м’ясопродукти | G1: =IF(Content!$E$1=1,G2,G3) -> Риба та рибопродукти | H1: =IF(Content!$E$1=1,H2,H3) -> Овочі | I1: =IF(Content!$E$1=1,I2,I3) -> Фрукти | J1: =IF(Content!$E$1=1,J2,J3) -> Інше | M1: =IF(Content!$E$1=1,M2,M3) -> Внески в зміну цін на продукти харчування*, в. п.
B2: Продукти харчування, % р/р | C2: Хліб, крупи, макарони | D2: Молочні продукти | E2: Яйця | F2: М'ясо та м’ясопродукти | G2: Риба та рибопродукти | H2: Овочі | I2: Фрукти | J2: Інше | M2: Внески в зміну цін на продукти харчування*, в. п.
B3: Foods, % yoy | C3: Bread, cereals, pasta | D3: Dairy products | E3: Eggs | F3: Meat and meat products | G3: Fish and fish products | H3: Vegetables | I3: Fruits | J3: Other | M3: Contributions to the annual change in food prices*, pp
A4: 45292 | B4: 3.7 | C4: -0.7 | D4: 1.1 | E4: -0.5 | F4: 2 | G4: 0.3 | H4: 1.1 | I4: 0.1 | J4: 0.3 | K4: 45292
A5: 45323 | B5: 2.6 | C5: -0.5 | D5: 1.1 | E5: -0.5 | F5: 1.5 | G5: 0.2 | H5: 0.5 | I5: 0 | J5: 0.1
A6: 45352 | B6: 0.2 | C6: -0.1 | D6: 0.1 | E6: -0.1 | F6: 0.2 | G6: 0 | H6: 0 | I6: 0 | J6: 0
A7: 45383 | B7: -0.5 | C7: 0.2 | D7: -0.5 | E7: 0.4 | F7: -0.3 | G7: -0.1 | H7: 0 | I7: -0.1 | J7: 0
A8: 45413 | B8: -0.5 | C8: 0.1 | D8: -0.3 | E8: 0.2 | F8: -0.2 | G8: -0.1 | H8: -0.1 | I8: -0.1 | J8: 0
A9: 45444 | B9: -0.1 | C9: 0 | D9: -0.1 | E9: 0 | F9: 0 | G9: 0 | H9: 0 | I9: 0 | J9: 0
A10: 45474 | B10: 1.2 | C10: 0.2 | D10: 0.8 | E10: -0.3 | F10: -0.1 | G10: 0.2 | H10: -0.4 | I10: 0.4 | J10: 0.4 | K10: 45474
A11: 45505 | B11: 6 | C11: 0.6 | D11: 1.6 | E11: -0.5 | F11: -0.2 | G11: 0.4 | H11: 2.6 | I11: 0.5 | J11: 0.9
A12: 45536 | B12: 8.5 | C12: 0.9 | D12: 2 | E12: -0.5 | F12: -0.1 | G12: 0.5 | H12: 3.6 | I12: 0.9 | J12: 1.2
A13: 45566 | B13: 10.8 | C13: 1.1 | D13: 2.4 | E13: -0.4 | F13: 0.1 | G13: 0.6 | H13: 4.1 | I13: 1.4 | J13: 1.5
A14: 45597 | B14: 14.3 | C14: 1.4 | D14: 2.9 | E14: 0.9 | F14: 0.5 | G14: 0.7 | H14: 4.3 | I14: 1.5 | J14: 2.1
A15: 45627 | B15: 14.1 | C15: 1.8 | D15: 3.3 | E15: 0.4 | F15: 0.8 | G15: 0.8 | H15: 3.2 | I15: 1 | J15: 2.8
A16: 45658 | B16: 14.3 | C16: 2 | D16: 3.5 | E16: -0.1 | F16: 1.4 | G16: 0.8 | H16: 2.6 | I16: 0.8 | J16: 3.3 | K16: 45658
A17: 45689 | B17: 15.2 | C17: 2.1 | D17: 3.5 | E17: 0 | F17: 1.7 | G17: 0.8 | H17: 2.4 | I17: 0.9 | J17: 3.6 | M17: =IF(Content!$E$1=1,M21,M22) -> * Містять як сирі, так і оброблені продукти харчування.
A18: 45717 | B18: 17.4 | C18: 2.2 | D18: 3.5 | E18: 1 | F18: 2 | G18: 0.8 | H18: 2.7 | I18: 1.1 | J18: 3.9 | M18: =IF(Content!$E$1=1,M19,M20) -> Джерело: ДССУ, розрахунки НБУ.
A19: 45748 | B19: 19.8 | C19: 2.3 | D19: 3.4 | E19: 1.4 | F19: 2.9 | G19: 0.8 | H19: 3.1 | I19: 1.7 | J19: 4.1 | M19: Джерело: ДССУ, розрахунки НБУ.
A20: 45778 | B20: 22.1 | C20: 2.4 | D20: 3.4 | E20: 1.5 | F20: 4.2 | G20: 0.8 | H20: 3.1 | I20: 2.4 | J20: 4.3 | M20: Source: SSSU, NBU staff estimates.
A21: 45809 | B21: 23.2 | C21: 2.3 | D21: 3.4 | E21: 1.2 | F21: 5.2 | G21: 0.8 | H21: 2.2 | I21: 3.7 | J21: 4.3 | M21: * Містять як сирі, так і оброблені продукти харчування.
A22: 45839 | B22: 22.6 | C22: 2.1 | D22: 3.4 | E22: 1.6 | F22: 5.4 | G22: 0.8 | H22: 1.6 | I22: 3.7 | J22: 4 | K22: 45839 | M22: * Includes both raw and processed foods.
A23: 45870 | B23: 20.5 | C23: 1.9 | D23: 3.4 | E23: 1.5 | F23: 5.6 | G23: 0.9 | H23: -0.1 | I23: 3.3 | J23: 3.9
A24: 45901 | B24: 17.4 | C24: 1.8 | D24: 3.1 | E24: 1.1 | F24: 5.6 | G24: 1 | H24: -1.3 | I24: 2.1 | J24: 3.9
A25: 45931 | B25: 15.6 | C25: 1.8 | D25: 2.7 | E25: 1 | F25: 5.7 | G25: 1 | H25: -1.9 | I25: 1.5 | J25: 3.9
A26: 45962 | B26: 12.1 | C26: 1.6 | D26: 2 | E26: 0.1 | F26: 5.2 | G26: 1 | H26: -2.6 | I26: 1.3 | J26: 3.5
A27: 45992 | B27: 10.2 | C27: 1.4 | D27: 1.4 | E27: 0.3 | F27: 4.8 | G27: 1 | H27: -2.9 | I27: 1 | J27: 3.2
A28: 46023 | B28: 9.7 | C28: 1.3 | D28: 1 | E28: 0.6 | F28: 4 | G28: 1 | H28: -2 | I28: 1.1 | J28: 2.8 | K28: 46023
A29: 46054 | B29: 9.9 | C29: 1.3 | D29: 0.7 | E29: 0.6 | F29: 3.5 | G29: 1 | H29: -0.9 | I29: 1.3 | J29: 2.4
A30: 46082 | B30: 9.5 | C30: 1.4 | D30: 0.6 | E30: 0.4 | F30: 3.2 | G30: 1.1 | H30: -0.8 | I30: 1.1 | J30: 2.4
A31: 46113 | B31: 9.6 | C31: 2 | D31: 0.6 | E31: 0.4 | F31: 2.8 | G31: 1.1 | H31: -0.4 | I31: 0.7 | J31: 2.3
A32: 46143 | B32: 7.9 | C32: 2.2 | D32: 0.5 | E32: 0.2 | F32: 1.6 | G32: 1.1 | H32: -0.3 | I32: 0.4 | J32: 2.2
A33: 46174 | B33: 5.6 | C33: 2 | D33: 0.5 | E33: -0.3 | F33: 0.9 | G33: 1 | H33: 0 | I33: -0.4 | J33: 2 | K33: 46174

Sheet 1.4
A1: << | B1: =IF(Content!$E$1=1,B2,B3) -> Крупи | C1: =IF(Content!$E$1=1,C2,C3) -> М’ясо та м’ясопродукти | D1: =IF(Content!$E$1=1,D2,D3) -> Риба та рибопродукти | E1: =IF(Content!$E$1=1,E2,E3) -> Молочні продукти | F1: =IF(Content!$E$1=1,F2,F3) -> Овочі | G1: =IF(Content!$E$1=1,G2,G3) -> Фрукти | H1: =IF(Content!$E$1=1,H2,H3) -> Цукор | K1: =IF(Content!$E$1=1,K2,K3) -> Зміна цін на окремі групи харчових продуктів, % р/р
B2: Крупи | C2: М’ясо та м’ясопродукти | D2: Риба та рибопродукти | E2: Молочні продукти | F2: Овочі | G2: Фрукти | H2: Цукор | K2: Зміна цін на окремі групи харчових продуктів, % р/р
B3: Cereals | C3: Meat and meat products | D3: Fish and fish products | E3: Dairy products | F3: Vegetables | G3: Fruits | H3: Sugar | K3: Changes in prices for selected food product groups, % yoy
A4: 45292 | B4: -40.5 | C4: 10.2 | D4: 5.3 | E4: 9.1 | F4: 13.1 | G4: 2.3 | H4: -8.2 | J4: 01.24
A5: 45323 | B5: -39.8 | C5: 9.1 | D5: 4.7 | E5: 10.2 | F5: 3.7 | G5: 1.3 | H5: -10.4
A6: 45352 | B6: -38.7 | C6: 7.7 | D6: 4.5 | E6: 9.8 | F6: -12.2 | G6: 4.9 | H6: -13.1
A7: 45383 | B7: -38.5 | C7: 4.2 | D7: 5.1 | E7: 10.3 | F7: -13.9 | G7: 7 | H7: -14.9
A8: 45413 | B8: -35.4 | C8: 2.9 | D8: 5.4 | E8: 9.9 | F8: -17.4 | G8: 8.7 | H8: -14.1
A9: 45444 | B9: -30.2 | C9: 0.4 | D9: 6.4 | E9: 10.2 | F9: -17.9 | G9: 11 | H9: -11.3
A10: 45474 | B10: -24 | C10: -0.7 | D10: 5.9 | E10: 10.3 | F10: -19.3 | G10: 14.1 | H10: -1.8 | J10: 07.24
A11: 45505 | B11: -21.3 | C11: -0.7 | D11: 6.7 | E11: 11.8 | F11: 36 | G11: 10.3 | H11: -1.6
A12: 45536 | B12: -16.1 | C12: -0.3 | D12: 8 | E12: 13.9 | F12: 56.4 | G12: 16 | H12: -4.6
A13: 45566 | B13: -6.5 | C13: 0.3 | D13: 9.3 | E13: 16.9 | F13: 62.1 | G13: 23.9 | H13: -6.6
A14: 45597 | B14: 4.6 | C14: 1.9 | D14: 11.1 | E14: 19.4 | F14: 62.9 | G14: 24.7 | H14: -3.6
A15: 45627 | B15: 13.6 | C15: 3.1 | D15: 12.1 | E15: 21.8 | F15: 48.3 | G15: 16.4 | H15: 0
A16: 45658 | B16: 16.7 | C16: 5.3 | D16: 11.6 | E16: 22.2 | F16: 33.9 | G16: 12.5 | H16: 2.3 | J16: 01.25
A17: 45689 | B17: 20.2 | C17: 6.8 | D17: 12.4 | E17: 22.3 | F17: 29.4 | G17: 14.1 | H17: 4.2
A18: 45717 | B18: 23.1 | C18: 8.5 | D18: 12.6 | E18: 22.2 | F18: 32.3 | G18: 16.9 | H18: 7.2
A19: 45748 | B19: 26.9 | C19: 12.6 | D19: 12.8 | E19: 21.7 | F19: 35.8 | G19: 25.3 | H19: 12.3
A20: 45778 | B20: 26.2 | C20: 18.2 | D20: 13.3 | E20: 21.7 | F20: 35.7 | G20: 33.5 | H20: 12.3 | K20: =IF(Content!$E$1=1,K21,K22) -> Джерело: ДССУ, розрахунки НБУ.
A21: 45809 | B21: 22 | C21: 22.9 | D21: 13.3 | E21: 21.7 | F21: 24.2 | G21: 51.7 | H21: 9 | K21: Джерело: ДССУ, розрахунки НБУ.
A22: 45839 | B22: 17.9 | C22: 24.2 | D22: 13.7 | E22: 21.6 | F22: 17.5 | G22: 52.1 | H22: -5.4 | J22: 07.25 | K22: Source: SSSU, NBU staff estimates.
A23: 45870 | B23: 17.3 | C23: 25.2 | D23: 14.5 | E23: 21 | F23: -2.5 | G23: 47.5 | H23: -8.5
A24: 45901 | B24: 17.7 | C24: 24.8 | D24: 15.6 | E24: 18.9 | F24: -16 | G24: 30.4 | H24: -8.2
A25: 45931 | B25: 21.9 | C25: 25.2 | D25: 16.2 | E25: 15.8 | F25: -21.5 | G25: 22.1 | H25: -6.6
A26: 45962 | B26: 19.9 | C26: 23.1 | D26: 16.7 | E26: 12.1 | F26: -27.8 | G26: 20.2 | H26: -7.6
A27: 45992 | B27: 19.6 | C27: 21 | D27: 16.5 | E27: 7.9 | F27: -29.8 | G27: 15.2 | H27: -9.7
A28: 46023 | B28: 23.2 | C28: 18.5 | D28: 17.4 | E28: 6.3 | F28: -23.7 | G28: 16.9 | H28: -10.3 | J28: 46023
A29: 46054 | B29: 27.7 | C29: 16.4 | D29: 17.9 | E29: 4.5 | F29: -14.6 | G29: 21.9 | H29: -10.8
A30: 46082 | B30: 34.8 | C30: 15.3 | D30: 19.3 | E30: 4.3 | F30: -15.1 | G30: 17.1 | H30: -12
A31: 46113 | B31: 63.7 | C31: 13.2 | D31: 20.5 | E31: 4 | F31: -14.3 | G31: 10.4 | H31: -10.8
A32: 46143 | B32: 77 | C32: 7.9 | D32: 21 | E32: 4.1 | F32: -16.8 | G32: 4.3 | H32: -10.3
A33: 46174 | B33: 72.9 | C33: 4.4 | D33: 21.4 | E33: 4.1 | F33: -12.8 | G33: -9.3 | H33: -11.3 | J33: 46174

Sheet 1.5
A1: << | B1: =IF(Content!$E$1=1,B2,B3) -> Роздріб на АЗС, грн/л | E1: =IF(Content!$E$1=1,E2,E3) -> Гуртові ціни, грн/л | J1: =IF(Content!$E$1=1,J2,J3) -> Роздрібні та гуртові* ціни на пальне в останні місяці, грн/л
B2: Роздріб на АЗС, грн/л | E2: Гуртові ціни, грн/л | J2: Роздрібні та гуртові* ціни на пальне в останні місяці, грн/л
B3: Retail price at gas stations, UAH/L | E3: Wholesale prices, UAH/L | J3: Retail and wholesale* fuel prices in recent months, UAH/L
B4: =IF(Content!$E$1=1,B5,B6) -> A-95 | C4: =IF(Content!$E$1=1,C5,C6) -> ДП | D4: =IF(Content!$E$1=1,D5,D6) -> Газ | E4: =IF(Content!$E$1=1,E5,E6) -> A-95 | F4: =IF(Content!$E$1=1,F5,F6) -> ДП | G4: =IF(Content!$E$1=1,G5,G6) -> Газ
B5: A-95 | C5: ДП | D5: Газ | E5: A-95 | F5: ДП | G5: Газ
B6: A-95 | C6: Diesel | D6: LPG | E6: A-95 | F6: Diesel | G6: LPG
A7: 46055 | B7: 60.65 | C7: 60.26 | D7: 38.34 | E7: 56.83 | F7: 53.03 | G7: 32.59
A8: 46056 | B8: 60.66 | C8: 60.25 | D8: 38.34 | E8: 55.48 | F8: 52.9 | G8: 32.61
A9: 46057 | B9: 60.72 | C9: 60.3 | D9: 38.34 | E9: 54.73 | F9: 52.76 | G9: 32.62
A10: 46058 | B10: 60.72 | C10: 60.35 | D10: 38.36 | E10: 54.04 | F10: 52.64 | G10: 32.48
A11: 46059 | B11: 60.8 | C11: 60.42 | D11: 38.35 | E11: 54.47 | F11: 52.55 | G11: 32.38
A12: 46062 | B12: 60.87 | C12: 60.5 | D12: 38.43 | E12: 54.47 | F12: 52.22 | G12: 32.25
A13: 46063 | B13: 60.91 | C13: 60.56 | D13: 38.44 | E13: 54.35 | F13: 52.26 | G13: 32.17
A14: 46064 | B14: 60.91 | C14: 60.57 | D14: 38.46 | E14: 54.24 | F14: 52.26 | G14: 32.25
A15: 46065 | B15: 60.93 | C15: 60.59 | D15: 38.47 | E15: 54.51 | F15: 52.37 | G15: 32.21
A16: 46066 | B16: 60.96 | C16: 60.62 | D16: 38.5 | E16: 53.26 | F16: 51.97 | G16: 32.55
A17: 46069 | B17: 60.96 | C17: 60.64 | D17: 38.51 | E17: 52.51 | F17: 51.9 | G17: 32.43
A18: 46070 | B18: 60.95 | C18: 60.63 | D18: 38.5 | E18: 52.42 | F18: 52 | G18: 32.42
A19: 46071 | B19: 60.94 | C19: 60.61 | D19: 38.5 | E19: 52 | F19: 51.95 | G19: 32.38 | J19: =IF(Content!$E$1=1,J22,J23) -> * Роздрібні – суцільні лінії, гуртові – пунктир.
A20: 46072 | B20: 60.94 | C20: 60.61 | D20: 38.51 | E20: 52.3 | F20: 52.72 | G20: 32.33 | J20: =IF(Content!$E$1=1,J24,J25) -> Джерело: Консалтингова група “А-95”.
A21: 46073 | B21: 60.93 | C21: 60.6 | D21: 38.51 | E21: 52.5 | F21: 53.32 | G21: 32.42
A22: 46076 | B22: 61.46 | C22: 61.15 | D22: 38.52 | E22: 52.5 | F22: 53.08 | G22: 32.54 | J22: * Роздрібні – суцільні лінії, гуртові – пунктир.
A23: 46077 | B23: 61.55 | C23: 61.24 | D23: 38.52 | E23: 52.46 | F23: 54.12 | G23: 32.59 | J23: * Retail – solid lines; wholesale – dotted lines.
A24: 46078 | B24: 61.78 | C24: 61.48 | D24: 38.52 | E24: 52.42 | F24: 54.3 | G24: 32.55 | J24: Джерело: Консалтингова група “А-95”.
A25: 46079 | B25: 61.83 | C25: 61.55 | D25: 38.51 | E25: 52.31 | F25: 54.36 | G25: 32.55 | J25: Source: A-95 Consulting Group.
A26: 46080 | B26: 61.84 | C26: 61.6 | D26: 38.5 | E26: 52.76 | F26: 54.65 | G26: 32.64
A27: 46083 | B27: 63.13 | C27: 62.96 | D27: 38.47 | E27: 54.77 | F27: 61.23 | G27: 32.74
A28: 46084 | B28: 65.07 | C28: 65.02 | D28: 39.05 | E28: 60.05 | F28: 67.34 | G28: 33.8
A29: 46085 | B29: 67.2 | C29: 67.4 | D29: 39.97 | E29: 61.36 | F29: 70.82 | G29: 34.66
A30: 46086 | B30: 68.28 | C30: 68.96 | D30: 40.23 | E30: 62.83 | F30: 71.75 | G30: 35.5
A31: 46087 | B31: 68.37 | C31: 69.1 | D31: 40.33 | E31: 61.53 | F31: 71.93 | G31: 35.57
A32: 46090 | B32: 68.97 | C32: 71.59 | D32: 40.66 | E32: 65.33 | F32: 82.77 | G32: 36.22
A33: 46091 | B33: 69.1 | C33: 72.92 | D33: 40.72 | E33: 62.66 | F33: 77.82 | G33: 39.41
A34: 46092 | B34: 69.09 | C34: 73.52 | D34: 41.36 | E34: 63.6 | F34: 74.29 | G34: 39.43
A35: 46093 | B35: 69.14 | C35: 74.37 | D35: 41.97 | E35: 62.9 | F35: 74.9 | G35: 40.93
A36: 46094 | B36: 69.14 | C36: 74.91 | D36: 42.5 | E36: 63.35 | F36: 76.78 | G36: 40.98
A37: 46097 | B37: 69.31 | C37: 76.76 | D37: 43.14 | E37: 64.57 | F37: 78 | G37: 41.52
... A136: 46234 | B136: 81.19 | C136: 91.99 | D136: 43.52 | E136: 80 | F136: 97.65 | G136: 39.23

Sheet 1.6
A1: << | B1: =IF(Content!$E$1=1,B2,B3) -> Адміністративно регульовані ціни, % р/р | C1: =IF(Content!$E$1=1,C2,C3) -> Алкогольні напої | D1: =IF(Content!$E$1=1,D2,D3) -> Тютюнові вироби | E1: =IF(Content!$E$1=1,E2,E3) -> Послуги ЖКГ | F1: =IF(Content!$E$1=1,F2,F3) -> Транспорт | G1: =IF(Content!$E$1=1,G2,G3) -> Іншe | J1: =IF(Content!$E$1=1,J2,J3) -> Внески в зміну адміністративно регульованих цін, в. п.
B2: Адміністративно регульовані ціни, % р/р | C2: Алкогольні напої | D2: Тютюнові вироби | E2: Послуги ЖКГ | F2: Транспорт | G2: Іншe | J2: Внески в зміну адміністративно регульованих цін, в. п.
B3: Administered prices, % yoy | C3: Alcoholic beverages | D3: Tobacco products | E3: Utilities | F3: Transport | G3: Other | J3: Contributions to the annual change in administered prices, pp
A4: 45292 | B4: 10.4 | C4: 0.7 | D4: 3.1 | E4: 4.8 | F4: 0.3 | G4: 1.4 | H4: 01.24
A5: 45323 | B5: 10.1 | C5: 0.5 | D5: 3.1 | E5: 4.9 | F5: 0.3 | G5: 1.4
A6: 45352 | B6: 9.9 | C6: 0.2 | D6: 3 | E6: 5 | F6: 0.3 | G6: 1.4
A7: 45383 | B7: 9.5 | C7: 0.1 | D7: 2.9 | E7: 5.1 | F7: 0.3 | G7: 1.1
A8: 45413 | B8: 9.4 | C8: -0.2 | D8: 2.8 | E8: 5.2 | F8: 0.3 | G8: 1.3
A9: 45444 | B9: 13.3 | C9: -0.2 | D9: 3.5 | E9: 7.9 | F9: 0.5 | G9: 1.6
A10: 45474 | B10: 13.4 | C10: -0.1 | D10: 3.4 | E10: 7.9 | F10: 0.5 | G10: 1.7 | H10: 07.24
A11: 45505 | B11: 13.7 | C11: -0.1 | D11: 3.2 | E11: 8 | F11: 0.6 | G11: 2
A12: 45536 | B12: 14 | C12: -0.1 | D12: 3.4 | E12: 8 | F12: 0.5 | G12: 2.1
A13: 45566 | B13: 14.5 | C13: 0.1 | D13: 3.8 | E13: 8.1 | F13: 0.6 | G13: 2
A14: 45597 | B14: 15.1 | C14: 0.2 | D14: 4 | E14: 8.2 | F14: 0.6 | G14: 2.1
A15: 45627 | B15: 16.3 | C15: 0.6 | D15: 4.3 | E15: 8.3 | F15: 0.7 | G15: 2.4
A16: 45658 | B16: 17.5 | C16: 0.7 | D16: 4.6 | E16: 8.3 | F16: 0.8 | G16: 3.1 | H16: 01.25
A17: 45689 | B17: 18.1 | C17: 0.8 | D17: 4.8 | E17: 8.3 | F17: 0.9 | G17: 3.3
A18: 45717 | B18: 19 | C18: 1.1 | D18: 5.1 | E18: 8.5 | F18: 1 | G18: 3.2
A19: 45748 | B19: 19.5 | C19: 1.1 | D19: 5.4 | E19: 8.7 | F19: 1 | G19: 3.2
A20: 45778 | B20: 19.8 | C20: 1.3 | D20: 5.6 | E20: 8.7 | F20: 1 | G20: 3.2 | J20: =IF(Content!$E$1=1,J21,J22) -> Джерело: ДССУ, розрахунки НБУ.
A21: 45809 | B21: 10.9 | C21: 1.1 | D21: 5.4 | E21: 0.4 | F21: 1 | G21: 3.1 | J21: Джерело: ДССУ, розрахунки НБУ.
A22: 45839 | B22: 11 | C22: 1.1 | D22: 5.8 | E22: 0.4 | F22: 0.9 | G22: 2.8 | H22: 07.25 | J22: Source: SSSU, NBU staff estimates.
A23: 45870 | B23: 10.8 | C23: 1 | D23: 6 | E23: 0.4 | F23: 0.9 | G23: 2.5
A24: 45901 | B24: 10.7 | C24: 1.1 | D24: 5.8 | E24: 0.4 | F24: 0.9 | G24: 2.5
A25: 45931 | B25: 10.6 | C25: 1 | D25: 5.8 | E25: 0.4 | F25: 1 | G25: 2.4
A26: 45962 | B26: 10.4 | C26: 1 | D26: 5.8 | E26: 0.4 | F26: 1 | G26: 2.2
A27: 45992 | B27: 9.7 | C27: 0.8 | D27: 5.7 | E27: 0.4 | F27: 0.8 | G27: 2
A28: 46023 | B28: 9.1 | C28: 0.7 | D28: 5.6 | E28: 0.3 | F28: 0.7 | G28: 1.7 | H28: 46023
A29: 46054 | B29: 8.8 | C29: 0.8 | D29: 5.6 | E29: 0.4 | F29: 0.7 | G29: 1.3
A30: 46082 | B30: 8.6 | C30: 0.7 | D30: 5.4 | E30: 0.1 | F30: 1 | G30: 1.3
A31: 46113 | B31: 9.4 | C31: 0.8 | D31: 5.5 | E31: 0.2 | F31: 1.6 | G31: 1.4
A32: 46143 | B32: 10.2 | C32: 1 | D32: 5.6 | E32: 0.2 | F32: 1.9 | G32: 1.5
A33: 46174 | B33: 10.7 | C33: 1.1 | D33: 5.7 | E33: 0.5 | F33: 1.9 | G33: 1.6 | H33: 46174

Sheet 1.7
A1: << | B1: =IF(Content!$E$1=1,B2,B3) -> Алкогольні напої | C1: =IF(Content!$E$1=1,C2,C3) -> Тютюнові вироби | D1: =IF(Content!$E$1=1,D2,D3) -> Послуги ЖКГ | E1: =IF(Content!$E$1=1,E2,E3) -> Транспорт | F1: =IF(Content!$E$1=1,F2,F3) -> Фармацевтична продукція | I1: =IF(Content!$E$1=1,I2,I3) -> Окремі компоненти адміністративної інфляції, % р/р
B2: Алкогольні напої | C2: Тютюнові вироби | D2: Послуги ЖКГ | E2: Транспорт | F2: Фармацевтична продукція | I2: Окремі компоненти адміністративної інфляції, % р/р
B3: Alcoholic beverages | C3: Tobacco products | D3: Utilities | E3: Transport | F3: Pharmaceutical products | I3: Selected components of administered inflation, % yoy
A4: 45292 | B4: 3.4 | C4: 16.1 | D4: 16.1 | E4: 3.7 | F4: 12.1 | H4: 01.24
A5: 45323 | B5: 2.5 | C5: 16.1 | D5: 16 | E5: 3.6 | F5: 12.3
A6: 45352 | B6: 1 | C6: 16.4 | D6: 16 | E6: 3.6 | F6: 13
A7: 45383 | B7: 0.1 | C7: 16.4 | D7: 16 | E7: 4.2 | F7: 14.2
A8: 45413 | B8: -1.2 | C8: 16.5 | D8: 16 | E8: 4.4 | F8: 16
A9: 45444 | B9: -0.9 | C9: 16.8 | D9: 22.8 | E9: 5.6 | F9: 16.7
A10: 45474 | B10: -0.8 | C10: 16.5 | D10: 22.8 | E10: 6.5 | F10: 14.8 | H10: 07.24
A11: 45505 | B11: -0.5 | C11: 16.1 | D11: 22.8 | E11: 7 | F11: 15.7
A12: 45536 | B12: -0.4 | C12: 17.4 | D12: 22.8 | E12: 6.9 | F12: 15.4
A13: 45566 | B13: 0.5 | C13: 19.4 | D13: 22.9 | E13: 6.9 | F13: 15.5
A14: 45597 | B14: 1.1 | C14: 20.8 | D14: 22.9 | E14: 7.4 | F14: 15.6
A15: 45627 | B15: 3.2 | C15: 22.9 | D15: 22.9 | E15: 8.5 | F15: 17.5
A16: 45658 | B16: 3.8 | C16: 24.3 | D16: 23 | E16: 10.1 | F16: 17.9 | H16: 01.25
A17: 45689 | B17: 4.3 | C17: 25.1 | D17: 23 | E17: 11.4 | F17: 19.2
A18: 45717 | B18: 6.1 | C18: 26.4 | D18: 23.9 | E18: 12.7 | F18: 20.7
A19: 45748 | B19: 6.2 | C19: 27.6 | D19: 23.9 | E19: 13.1 | F19: 18.8
A20: 45778 | B20: 6.9 | C20: 28.3 | D20: 23.8 | E20: 13.2 | F20: 17.4 | I20: =IF(Content!$E$1=1,I21,I22) -> Джерело: ДССУ, розрахунки НБУ.
A21: 45809 | B21: 6.6 | C21: 28.4 | D21: 1.1 | E21: 13.2 | F21: 16.8 | I21: Джерело: ДССУ, розрахунки НБУ.
A22: 45839 | B22: 6.7 | C22: 30.1 | D22: 1.1 | E22: 12.5 | F22: 15.9 | H22: 07.25 | I22: Source: SSSU, NBU staff estimates.
A23: 45870 | B23: 5.6 | C23: 30.9 | D23: 1.1 | E23: 11.9 | F23: 14.6
A24: 45901 | B24: 6.6 | C24: 29.3 | D24: 1.1 | E24: 12.1 | F24: 14.7
A25: 45931 | B25: 6.4 | C25: 28.8 | D25: 1.1 | E25: 12.6 | F25: 13.6
A26: 45962 | B26: 6.1 | C26: 28.7 | D26: 1 | E26: 12.2 | F26: 12.2
A27: 45992 | B27: 4.7 | C27: 27.7 | D27: 1 | E27: 10.6 | F27: 10
A28: 46023 | B28: 4.4 | C28: 26.8 | D28: 0.9 | E28: 9.3 | F28: 7.4 | H28: 46023
A29: 46054 | B29: 4.6 | C29: 26.3 | D29: 1 | E29: 8.9 | F29: 1.1
A30: 46082 | B30: 4.2 | C30: 25 | D30: 0.3 | E30: 13.4 | F30: -2.7
A31: 46113 | B31: 4.5 | C31: 24.5 | D31: 0.4 | E31: 21.4 | F31: -3.5
A32: 46143 | B32: 5.5 | C32: 24.6 | D32: 0.4 | E32: 25.2 | F32: -4.5
A33: 46174 | B33: 6.1 | C33: 24.6 | D33: 1.1 | E33: 25.5 | F33: -5.4 | H33: 46174

Sheet 1.8
A1: << | B1: =IF(Content!$E$1=1,B2,B3) -> Банки | C1: =IF(Content!$E$1=1,C2,C3) -> Підприємства | D1: =IF(Content!$E$1=1,D2,D3) -> Домогосподарства | E1: =IF(Content!$E$1=1,E2,E3) -> Фінансові аналітики | F1: =IF(Content!$E$1=1,F2,F3) -> ІСЦ | I1: =IF(Content!$E$1=1,I2,I3) -> Інфляційні очікування на наступні 12 місяців та інфляція в річному вимірі, %
B2: Банки | C2: Підприємства | D2: Домогосподарства | E2: Фінансові аналітики | F2: ІСЦ | I2: Інфляційні очікування на наступні 12 місяців та інфляція в річному вимірі, %
B3: Banks | C3: Corporates | D3: Households | E3: Financial analysts | F3: CPI | I3: 12-month-ahead inflation expectations and inflation in annual terms, %
A4: 45292 | B4: 10.4 | C4: #N/A | D4: 8.7 | E4: 8.2 | F4: 4.7 | G4: 01.24
A5: 45323 | B5: #N/A | C5: 11 | D5: 9.3 | E5: #N/A | F5: 4.3
A6: 45352 | B6: #N/A | C6: #N/A | D6: 8.7 | E6: 8.1 | F6: 3.2
A7: 45383 | B7: 9.3 | C7: #N/A | D7: 6.5 | E7: 7.4 | F7: 3.2
A8: 45413 | B8: #N/A | C8: 9 | D8: 6.5 | E8: #N/A | F8: 3.3
A9: 45444 | B9: #N/A | C9: #N/A | D9: 7.9 | E9: 7.1 | F9: 4.8
A10: 45474 | B10: 8.7 | C10: #N/A | D10: 7.6 | E10: 7.2 | F10: 5.4 | G10: 07.24
A11: 45505 | B11: #N/A | C11: 9.7 | D11: 7.1 | E11: #N/A | F11: 7.5
A12: 45536 | B12: #N/A | C12: #N/A | D12: 7.2 | E12: 7.4 | F12: 8.6
A13: 45566 | B13: 9.2 | C13: #N/A | D13: 8.1 | E13: 7.6 | F13: 9.7
A14: 45597 | B14: #N/A | C14: 10.3 | D14: 7.8 | E14: #N/A | F14: 11.2
A15: 45627 | B15: #N/A | C15: #N/A | D15: 11.3 | E15: 7.2 | F15: 12
A16: 45658 | B16: 9 | C16: #N/A | D16: 11 | E16: 7.8 | F16: 12.9 | G16: 01.25
A17: 45689 | B17: #N/A | C17: 11.5 | D17: 9.9 | E17: 7.8 | F17: 13.4
A18: 45717 | B18: #N/A | C18: #N/A | D18: 9.2 | E18: #N/A | F18: 14.6
A19: 45748 | B19: 9.8 | C19: #N/A | D19: 10.1 | E19: 7.7 | F19: 15.1 | I19: =IF(Content!$E$1=1,I20,I21) -> Джерело: НБУ, Info Sapiens, ДССУ.
A20: 45778 | B20: #N/A | C20: 10.9 | D20: 10.2 | E20: 7.9 | F20: 15.9 | I20: Джерело: НБУ, Info Sapiens, ДССУ.
A21: 45809 | B21: #N/A | C21: #N/A | D21: 10.8 | E21: #N/A | F21: 14.3 | I21: Source: NBU, Info Sapiens, SSSU.
A22: 45839 | B22: 11.6 | C22: #N/A | D22: 10.7 | E22: 7.5 | F22: 14.1 | G22: 07.25
A23: 45870 | B23: #N/A | C23: 11.4 | D23: 10.1 | E23: #N/A | F23: 13.2
A24: 45901 | B24: #N/A | C24: #N/A | D24: 10.8 | E24: 7.2 | F24: 11.9
A25: 45931 | B25: 10 | C25: #N/A | D25: 10.3 | E25: 7.4 | F25: 10.9
A26: 45962 | B26: #N/A | C26: 11.1 | D26: 10.4 | E26: #N/A | F26: 9.3
A27: 45992 | B27: #N/A | C27: #N/A | D27: 10.5 | E27: 7.5 | F27: 8
A28: 46023 | B28: 9.4 | C28: #N/A | D28: 10.9 | E28: 7.5 | F28: 7.4 | G28: 46023
A29: 46054 | B29: #N/A | C29: 11.1 | D29: 13.5 | E29: #N/A | F29: 7.6
A30: 46082 | B30: #N/A | C30: #N/A | D30: 14.4 | E30: 7.7 | F30: 7.9
A31: 46113 | B31: 9.3 | C31: #N/A | D31: 10.9 | E31: 7.6 | F31: 8.6
A32: 46143 | B32: #N/A | C32: 11.6 | D32: 13.7 | E32: #N/A | F32: 8.2
A33: 46174 | B33: #N/A | C33: #N/A | D33: 12.7 | E33: 7.5 | F33: 7.2
A34: 46204 | B34: 8.7 | C34: #N/A | D34: 10 | E34: 7.9 | F34: #N/A | G34: 46204

Sheet 1.9
A1: << | B1: =IF(Content!$E$1=1,B2,B3) -> ІЦВ | C1: =IF(Content!$E$1=1,C2,C3) -> Переробна промисловість | D1: =IF(Content!$E$1=1,D2,D3) -> Добувна промисловість | E1: =IF(Content!$E$1=1,E2,E3) -> Е/е, газ, пара та конд. повітря (п. ш.) | H1: =IF(Content!$E$1=1,H2,H3) -> Індекс цін виробників (ІЦВ) та його компоненти, % р/р
B2: ІЦВ | C2: Переробна промисловість | D2: Добувна промисловість | E2: Е/е, газ, пара та конд. повітря (п. ш.) | H2: Індекс цін виробників (ІЦВ) та його компоненти, % р/р
B3: PPI | C3: Processing industry | D3: Mining industry | E3: Electricity, gas, steam and air cond. supply (RHS) | H3: Producer Price Index (PPI) and its components, % yoy
A4: 45292 | B4: 10.3 | C4: 8.7 | D4: 11.4 | E4: 10.4 | F4: 01.24
A5: 45323 | B5: 7.7 | C5: 8.8 | D5: 3.5 | E5: 7.4
A6: 45352 | B6: -0.2 | C6: 8.1 | D6: -0.3 | E6: -7.8
A7: 45383 | B7: 4.9 | C7: 6.4 | D7: 2.8 | E7: 3.7
A8: 45413 | B8: 14.8 | C8: 6.3 | D8: 9.5 | E8: 23.7
A9: 45444 | B9: 26.7 | C9: 7.2 | D9: 10.8 | E9: 48.1
A10: 45474 | B10: 33.3 | C10: 9.6 | D10: 10.1 | E10: 60.6 | F10: 07.24
A11: 45505 | B11: 31.2 | C11: 9.2 | D11: 7.4 | E11: 56.2
A12: 45536 | B12: 27.1 | C12: 10 | D12: 0.4 | E12: 47.1
A13: 45566 | B13: 24.5 | C13: 11.4 | D13: -0.4 | E13: 39
A14: 45597 | B14: 24.1 | C14: 13.2 | D14: 2.5 | E14: 34.6
A15: 45627 | B15: 27.6 | C15: 14 | D15: 5.8 | E15: 41.4
A16: 45658 | B16: 32.5 | C16: 13.7 | D16: 7.1 | E16: 53 | F16: 01.25
A17: 45689 | B17: 37 | C17: 13 | D17: 7.7 | E17: 65.1
A18: 45717 | B18: 51.9 | C18: 13.2 | D18: 9.8 | E18: 106.4
A19: 45748 | B19: 41.6 | C19: 14.2 | D19: 5.8 | E19: 76.4 | H19: =IF(Content!$E$1=1,H20,H21) -> Джерело: ДССУ.
A20: 45778 | B20: 28.9 | C20: 13.9 | D20: 3 | E20: 45.7 | H20: Джерело: ДССУ.
A21: 45809 | B21: 13.1 | C21: 13.1 | D21: 0.7 | E21: 13.4 | H21: Source: SSSU.
A22: 45839 | B22: 4.7 | C22: 11.5 | D22: 4.4 | E22: -3 | F22: 07.25
A23: 45870 | B23: 7.3 | C23: 11.4 | D23: 5.2 | E23: 2.5
A24: 45901 | B24: 1.3 | C24: 11.1 | D24: 7 | E24: -10.1
A25: 45931 | B25: 5.5 | C25: 10.4 | D25: 4.5 | E25: -0.7
A26: 45962 | B26: 9.9 | C26: 9.2 | D26: 0.9 | E26: 10.7
A27: 45992 | B27: 8.2 | C27: 8.8 | D27: -0.3 | E27: 7.8
A28: 46023 | B28: 11.2 | C28: 8.9 | D28: -1.3 | E28: 15.4 | F28: 01.26
A29: 46054 | B29: 34.5 | C29: 10 | D29: -1.4 | E29: 73.4
A30: 46082 | B30: 36.6 | C30: 11.4 | D30: 3.7 | E30: 75.8
A31: 46113 | B31: 40.2 | C31: 12 | D31: 10.3 | E31: 81.7
A32: 46143 | B32: 45.2 | C32: 13.4 | D32: 10.1 | E32: 94.3
A33: 46174 | B33: 39.1 | C33: 13.8 | D33: 9.9 | E33: 73 | F33: 06.26

Sheet 1.10
A1: << | B1: =IF(Content!$E$1=1,B2,B3) -> Ринок "доба наперед" | C1: =IF(Content!$E$1=1,C2,C3) -> Внутрішньодобовий ринок | D1: =IF(Content!$E$1=1,D2,D3) -> Ринок довгострокових договорів* | G1: =IF(Content!$E$1=1,G2,G3) -> Ціни на е/е для непобутових споживачів, грн/МВт•год
B2: Ринок "доба наперед" | C2: Внутрішньодобовий ринок | D2: Ринок довгострокових договорів* | G2: Ціни на е/е для непобутових споживачів, грн/МВт•год
B3: Day-ahead market | C3: Intraday market | D3: Long-term contracts market* | G3: Electricity prices for non-household consumers, UAH/MWh
A4: 45292 | B4: 3370.3 | C4: 3507.51 | D4: 3752.3 | E4: 01.24
A5: 45323 | B5: 3100.54 | C5: 3285.42 | D5: 3107.6
A6: 45352 | B6: 2908.09 | C6: 3063.26 | D6: 2409
A7: 45383 | B7: 3115.54 | C7: 3406.63 | D7: 2665.2
A8: 45413 | B8: 3941.16 | C8: 4975.95 | D8: 3304.8
A9: 45444 | B9: 4981.94 | C9: 5609.46 | D9: 5484.3
A10: 45474 | B10: 5567.2 | C10: 5725.42 | D10: 5353.1 | E10: 07.24
A11: 45505 | B11: 5497.53 | C11: 5971.35 | D11: 5049.9
A12: 45536 | B12: 5410.71 | C12: 6109.8 | D12: 5022.9
A13: 45566 | B13: 5249.44 | C13: 5568.77 | D13: 5144.7
A14: 45597 | B14: 5276.88 | C14: 5584.1 | D14: 5071.1
A15: 45627 | B15: 5778.6 | C15: 6057.22 | D15: 5057.8
A16: 45658 | B16: 5548.03 | C16: 5839.35 | D16: 5327.4 | E16: 01.25
A17: 45689 | B17: 5872.87 | C17: 6531.23 | D17: 5413.8
A18: 45717 | B18: 5150.66 | C18: 4745.95 | D18: 5611.1 | G18: =IF(Content!$E$1=1,G21,G22) -> * З травня 2026 року дані за середньодекадними значеннями.
A19: 45748 | B19: 4258.63 | C19: 4287.3 | D19: 4782.5 | G19: =IF(Content!$E$1=1,G24,G25) -> Джерело: Українська енергетична біржа, Оператор ринку.
A20: 45778 | B20: 4421.95 | C20: 4216.48 | D20: 3886.9
A21: 45809 | B21: 4664.67 | C21: 4167.84 | D21: 4449.4 | G21: * З травня 2026 року дані за середньодекадними значеннями.
A22: 45839 | B22: 5184.24 | C22: 4943.77 | D22: 4686.2 | E22: 07.25 | G22: * From May 2026 onward, monthly values are based on three 10-day averages
A23: 45870 | B23: 5188.78 | C23: 4913.41 | D23: 5416.4
A24: 45901 | B24: 4196.92 | C24: 4451.85 | D24: 4972.9 | G24: Джерело: Українська енергетична біржа, Оператор ринку.
A25: 45931 | B25: 5986.52 | C25: 6688.41 | D25: 4168.9 | G25: Source: Ukrainian Energy Exchange, Market operator.
A26: 45962 | B26: 6387.89 | C26: 6658.85 | D26: 5209
A27: 45992 | B27: 6648.95 | C27: 6893.16 | D27: 5564.5
A28: 46023 | B28: 8253.26 | C28: 8692.26 | D28: 6102.2 | E28: 01.26
A29: 46054 | B29: 9785.72 | C29: 10282.29 | D29: 9182.4
A30: 46082 | B30: 7075.53 | C30: 6684.63 | D30: 7211.3
A31: 46113 | B31: 5391.3 | C31: 5007.83 | D31: 6006.7
A32: 46143 | B32: 5068.72 | C32: 4946.7 | D32: 5397.77
A33: 46174 | B33: 5599.18 | C33: 5106.08 | D33: 5152.43
A34: 46204 | B34: 4443.89 | C34: 4311.33 | D34: 5330.4 | E34: 07.26

Sheet 1.11
A1: << | B1: =IF(Content!$E$1=1,B2,B3) -> Оброблені продукти | C1: =IF(Content!$E$1=1,C2,C3) -> Послуги | D1: =IF(Content!$E$1=1,D2,D3) -> Одяг і взуття | E1: =IF(Content!$E$1=1,E2,E3) -> Інші непродовольчі товари | H1: =IF(Content!$E$1=1,H2,H3) -> Компоненти БІСЦ, % р/р
B2: Оброблені продукти | C2: Послуги | D2: Одяг і взуття | E2: Інші непродовольчі товари | H2: Компоненти БІСЦ, % р/р
B3: Processed foods | C3: Services | D3: Clothing & Footwear | E3: Other nonfoods | H3: Components of the core CPI, % yoy
A4: 45292 | B4: 5.5 | C4: 10.1 | D4: -6.7 | E4: 1 | F4: 01.24
A5: 45323 | B5: 5.6 | C5: 9.8 | D5: -7 | E5: 0.6
A6: 45352 | B6: 5.3 | C6: 9.7 | D6: -6.7 | E6: 0.4
A7: 45383 | B7: 5.5 | C7: 9.7 | D7: -6.2 | E7: 0.8
A8: 45413 | B8: 5.3 | C8: 9.7 | D8: -6.1 | E8: 1
A9: 45444 | B9: 5.9 | C9: 9.9 | D9: -5.6 | E9: 1.6
A10: 45474 | B10: 6.5 | C10: 10.3 | D10: -4.5 | E10: 2.2 | F10: 07.24
A11: 45505 | B11: 7.4 | C11: 10.5 | D11: -5.1 | E11: 3.1
A12: 45536 | B12: 8.9 | C12: 10.9 | D12: -5.1 | E12: 3.8
A13: 45566 | B13: 10.7 | C13: 11 | D13: -4.6 | E13: 4.6
A14: 45597 | B14: 12.5 | C14: 11.2 | D14: -3.9 | E14: 5.1
A15: 45627 | B15: 14.7 | C15: 12.5 | D15: -4.3 | E15: 5.6
A16: 45658 | B16: 15.9 | C16: 14.2 | D16: -4.3 | E16: 5.9 | F16: 01.25
A17: 45689 | B17: 16.7 | C17: 14.3 | D17: -4 | E17: 5.9
A18: 45717 | B18: 17.3 | C18: 14.6 | D18: -3.6 | E18: 6.3
A19: 45748 | B19: 17.3 | C19: 14.6 | D19: -4.4 | E19: 5.3 | H19: =IF(Content!$E$1=1,H20,H21) -> Джерело: ДССУ, розрахунки НБУ.
A20: 45778 | B20: 18 | C20: 14.6 | D20: -4.8 | E20: 5.4 | H20: Джерело: ДССУ, розрахунки НБУ.
A21: 45809 | B21: 18.2 | C21: 14.4 | D21: -4.5 | E21: 5 | H21: Source: SSSU, NBU staff estimates.
A22: 45839 | B22: 18 | C22: 14 | D22: -5.4 | E22: 4.8 | F22: 07.25
A23: 45870 | B23: 17.7 | C23: 14.1 | D23: -5.7 | E23: 4.2
A24: 45901 | B24: 16.8 | C24: 14.1 | D24: -5.3 | E24: 3.7
A25: 45931 | B25: 15.6 | C25: 13.8 | D25: -6 | E25: 3
A26: 45962 | B26: 13.9 | C26: 13.4 | D26: -6.1 | E26: 2
A27: 45992 | B27: 12.1 | C27: 12.3 | D27: -6.1 | E27: 1
A28: 46023 | B28: 10.8 | C28: 11.2 | D28: -5.4 | E28: 0.5 | F28: 46023
A29: 46054 | B29: 9.9 | C29: 12.3 | D29: -5 | E29: 0.5
A30: 46082 | B30: 10 | C30: 12.8 | D30: -6.1 | E30: 0.5
A31: 46113 | B31: 10.2 | C31: 13.3 | D31: -5.4 | E31: 1.3
A32: 46143 | B32: 10.4 | C32: 13.6 | D32: -5.3 | E32: 1.3
A33: 46174 | B33: 10.4 | C33: 13.7 | D33: -5.4 | E33: 1.6 | F33: 46174

Sheet 1.12
A1: << | B1: =IF(Content!$E$1=1,B2,B3) -> Оброблені продукти | C1: =IF(Content!$E$1=1,C2,C3) -> Послуги | D1: =IF(Content!$E$1=1,D2,D3) -> Одяг і взуття | E1: =IF(Content!$E$1=1,E2,E3) -> Інші непродовольчі товари | I1: =IF(Content!$E$1=1,I2,I3) -> Ануалізовані* зміни основних складових БІСЦ, %
B2: Оброблені продукти | C2: Послуги | D2: Одяг і взуття | E2: Інші непродовольчі товари | I2: Ануалізовані* зміни основних складових БІСЦ, %
B3: Processed foods | C3: Services | D3: Clothing & Footwear | E3: Other nonfoods | I3: Annualized* changes in the main components of the core CPI, %
A4: 45292 | B4: 5.7 | C4: 6.6 | D4: -4.7 | E4: 4.6 | F4: 01.24
A5: 45323 | B5: 9.1 | C5: 7.9 | D5: -5.4 | E5: 2.7
A6: 45352 | B6: 4.9 | C6: 11.3 | D6: -0.8 | E6: 1.4
A7: 45383 | B7: 8.8 | C7: 12.4 | D7: -2.2 | E7: 7.3
A8: 45413 | B8: 4.9 | C8: 12.9 | D8: -3.8 | E8: 3.5
A9: 45444 | B9: 14 | C9: 13.5 | D9: -5.8 | E9: 5.8
A10: 45474 | B10: 13.9 | C10: 13.9 | D10: 4.6 | E10: 4.9 | F10: 07.24 | S10: =IF(Content!$E$1=1,S11,S12) -> Значні перегляди тарифів мобільними операторами
A11: 45505 | B11: 17.9 | C11: 12 | D11: -7.5 | E11: 6.6 | S11: Значні перегляди тарифів мобільними операторами
A12: 45536 | B12: 21.9 | C12: 13.6 | D12: -8.3 | E12: 6.3 | S12: Significant revisions of tariffs by mobile operators
A13: 45566 | B13: 23 | C13: 12.3 | D13: -1.7 | E13: 8.3
A14: 45597 | B14: 26.3 | C14: 10.8 | D14: -3 | E14: 7.8
A15: 45627 | B15: 27.2 | C15: 23.9 | D15: -9.5 | E15: 9
A16: 45658 | B16: 19.9 | C16: 28.1 | D16: -4.3 | E16: 5.9 | F16: 01.25
A17: 45689 | B17: 18.4 | C17: 8.4 | D17: -3 | E17: 3.5
A18: 45717 | B18: 13 | C18: 14.7 | D18: 3.3 | E18: 5.3 | I18: =IF(Content!$E$1=1,I22,I23) -> * Приведена до річного виміру місячна зміна, сезонно скоригована.
A19: 45748 | B19: 10.7 | C19: 12.5 | D19: -11.9 | E19: -2.7 | I19: =IF(Content!$E$1=1,I20,I21) -> Джерело: ДССУ, розрахунки НБУ.
A20: 45778 | B20: 14 | C20: 12.3 | D20: -7.2 | E20: 4.3 | I20: Джерело: ДССУ, розрахунки НБУ.
A21: 45809 | B21: 14.5 | C21: 11.5 | D21: -3.1 | E21: 1.6 | I21: Source: SSSU, NBU staff estimates.
A22: 45839 | B22: 11.4 | C22: 9.6 | D22: -6.9 | E22: 2.1 | F22: 07.25 | I22: * Приведена до річного виміру місячна зміна, сезонно скоригована.
A23: 45870 | B23: 14 | C23: 13.5 | D23: -10.5 | E23: 0.6 | I23: * Annualized monthly change, seasonally adjusted.
A24: 45901 | B24: 10.8 | C24: 12.5 | D24: -2.9 | E24: 0.2
A25: 45931 | B25: 8.8 | C25: 9 | D25: -9.3 | E25: -0.8
A26: 45962 | B26: 5.6 | C26: 6.9 | D26: -4.7 | E26: -3.2
A27: 45992 | B27: 4.4 | C27: 10.1 | D27: -8.9 | E27: -3.7
A28: 46023 | B28: 4.5 | C28: 14 | D28: 4.1 | E28: -0.8 | F28: 46023
A29: 46054 | B29: 7.2 | C29: 21.7 | D29: 0.5 | E29: 3.2
A30: 46082 | B30: 14.1 | C30: 20.6 | D30: -10.2 | E30: 4.3
A31: 46113 | B31: 14.3 | C31: 19.1 | D31: -5.4 | E31: 8.8
A32: 46143 | B32: 17.1 | C32: 16.2 | D32: -5 | E32: 3.8
A33: 46174 | B33: 15.1 | C33: 12.8 | D33: -5.2 | E33: 5.8 | F33: 46174

Sheet 1.13
A1: << | B1: =IF(Content!$E$1=1,B2,B3) -> Номінальна | C1: =IF(Content!$E$1=1,C2,C3) -> Номінальна (оцінка) | D1: =IF(Content!$E$1=1,D2,D3) -> Реальна | E1: =IF(Content!$E$1=1,E2,E3) -> Реальна (оцінка) | H1: =IF(Content!$E$1=1,H2,H3) -> Річна зміна середньої зарплати, %*
B2: Номінальна | C2: Номінальна (оцінка) | D2: Реальна | E2: Реальна (оцінка) | H2: Річна зміна середньої зарплати, %*
B3: Nominal | C3: Nominal (estimate) | D3: Real | E3: Real (estimate) | H3: Annual change in average wage, %*
A4: 44592 | B4: 18.2 | D4: 7.4
A5: 44620 | C5: 18.1 | E5: 6.7
A6: 44651 | C6: 6.4 | E6: -6.4
A7: 44681 | C7: -7.3 | E7: -20.4
A8: 44712 | C8: -3 | E8: -17.8
A9: 44742 | C9: 8.5 | E9: -10.7 | O9: -50
A10: 44773 | C10: 3.5 | E10: -15.3 | O10: 30
A11: 44804 | C11: -0.6 | E11: -19.7
A12: 44834 | C12: 6.1 | E12: -14.9
A13: 44865 | C13: 8 | E13: -14.7
A14: 44895 | C14: 6.6 | E14: -15.7
A15: 44926 | C15: 9 | E15: -13.9
A16: 44957 | C16: 1.1 | E16: -19.7
A17: 44985 | C17: 3.2 | E17: -17.4
A18: 45016 | C18: 12.4 | E18: -7.4 | H18: =IF(Content!$E$1=1,H22,H23) -> * Для місяців, щодо яких немає даних ДССУ, наведено оцінку НБУ.
A19: 45046 | C19: 25 | E19: 6 | H19: =IF(Content!$E$1=1,H20,H21) -> Джерело: ДССУ, НБУ.
A20: 45077 | C20: 25.3 | E20: 8.7 | H20: Джерело: ДССУ, НБУ.
A21: 45107 | C21: 25.1 | E21: 10.9 | H21: Source: SSSU, NBU.
A22: 45138 | C22: 21.3 | E22: 9 | H22: * Для місяців, щодо яких немає даних ДССУ, наведено оцінку НБУ.
A23: 45169 | C23: 23.8 | E23: 14 | H23: * For months for which there is no data from the SSSU, the NBU’s estimate is provided.
A24: 45199 | C24: 23.1 | E24: 14.9
A25: 45230 | C25: 18 | E25: 12
A26: 45260 | C26: 18.3 | E26: 12.5
A27: 45291 | C27: 14.5 | E27: 8.9
A28: 45322 | B28: 24.2 | C28: 24.2 | D28: 18.7 | E28: 18.7
A29: 45351 | B29: 22.7 | D29: 17.6
A30: 45382 | B30: 21.2 | C30: 21.2 | D30: 17.4 | E30: 17.4
A31: 45412 | C31: 32 | E31: 27.9
A32: 45443 | C32: 26.6 | E32: 22.6
A33: 45473 | C33: 10.9 | E33: 5.8
A34: 45504 | C34: 21.2 | E34: 15
A35: 45535 | C35: 24.4 | E35: 15.7
A36: 45565 | C36: 22.2 | E36: 12.5
A37: 45596 | C37: 26.2 | E37: 15
A38: 45626 | C38: 27.6 | E38: 14.8
A39: 45657 | C39: 24.9 | E39: 11.5
A40: 45688 | B40: 25.5 | C40: 25.5 | D40: 11.2 | E40: 11.2
A41: 45716 | B41: 23.3 | D41: 8.7
A42: 45747 | B42: 25.5 | D42: 9.5
A43: 45777 | B43: 21.5 | D43: 5.5
A44: 45808 | B44: 21.6 | D44: 4.9
A45: 45838 | B45: 21.3 | D45: 6.2
A46: 45869 | B46: 21.4 | D46: 6.4
A47: 45900 | B47: 21.1 | D47: 6.9
A48: 45930 | B48: 17.2 | D48: 4.7
A49: 45961 | B49: 19.2 | D49: 7.4
A50: 45991 | B50: 18.2 | D50: 8.1
A51: 46022 | B51: 13.7 | D51: 5.3
A52: 46053 | B52: 21.7 | D52: 13.3
... A57: 46203 | B57: 25.4 | D57: 17

Sheet 1.14
A1: << | B1: =IF(Content!$E$1=1,B2,B3) -> Перукарні та манікюр | C1: =IF(Content!$E$1=1,C2,C3) -> Готелі та пансіонати | D1: =IF(Content!$E$1=1,D2,D3) -> Оренда житла | E1: =IF(Content!$E$1=1,E2,E3) -> Послуги з утримання та ремонту житла | F1: =IF(Content!$E$1=1,F2,F3) -> Мобільний зв'язок та інтернет | I1: =IF(Content!$E$1=1,I2,I3) -> Зміна цін на окремі групи послуг, % р/р
B2: Перукарні та манікюр | C2: Готелі та пансіонати | D2: Оренда житла | E2: Послуги з утримання та ремонту житла | F2: Мобільний зв'язок та інтернет | I2: Зміна цін на окремі групи послуг, % р/р
B3: Hair salons and manicure | C3: Hotels and holiday resorts | D3: Housing rentals | E3: Dwelling maintenance and repair services | F3: Mobile communications and the internet | I3: Changes in prices for selected service groups, % yoy
A4: 45292 | B4: 14.9 | C4: 9.8 | D4: 9 | E4: 10.1 | F4: 4.5 | H4: 01.24
A5: 45323 | B5: 15 | C5: 11.1 | D5: 9.5 | E5: 10.1 | F5: 3.9
A6: 45352 | B6: 15.6 | C6: 10.5 | D6: 9.5 | E6: 10.1 | F6: 3.3
A7: 45383 | B7: 16.4 | C7: 9.4 | D7: 9.4 | E7: 11.2 | F7: 3.1
A8: 45413 | B8: 15.1 | C8: 10 | D8: 9.6 | E8: 11.6 | F8: 3.1
A9: 45444 | B9: 14.5 | C9: 9.6 | D9: 9.1 | E9: 11.3 | F9: 3.6
A10: 45474 | B10: 14.7 | C10: 11.1 | D10: 9.1 | E10: 11.3 | F10: 5.5 | H10: 07.24
A11: 45505 | B11: 15.6 | C11: 12 | D11: 7.9 | E11: 11.6 | F11: 6.1
A12: 45536 | B12: 15.7 | C12: 12 | D12: 8.6 | E12: 11.9 | F12: 6.5
A13: 45566 | B13: 16.3 | C13: 11.9 | D13: 8.1 | E13: 12.6 | F13: 6.8
A14: 45597 | B14: 16.5 | C14: 11.4 | D14: 8 | E14: 12 | F14: 7
A15: 45627 | B15: 17.7 | C15: 11.7 | D15: 7.8 | E15: 11.7 | F15: 12.6
A16: 45658 | B16: 17.5 | C16: 12.4 | D16: 7.4 | E16: 11.8 | F16: 24.8 | H16: 01.25
A17: 45689 | B17: 17.2 | C17: 11.1 | D17: 7.6 | E17: 11.6 | F17: 25.2
A18: 45717 | B18: 16.5 | C18: 11.5 | D18: 7.6 | E18: 11.9 | F18: 24.3
A19: 45748 | B19: 15.7 | C19: 12 | D19: 7.5 | E19: 11.2 | F19: 24.3 | I19: =IF(Content!$E$1=1,I20,I21) -> Джерело: ДССУ, розрахунки НБУ.
A20: 45778 | B20: 15.8 | C20: 12.2 | D20: 7.3 | E20: 10.9 | F20: 24.3 | I20: Джерело: ДССУ, розрахунки НБУ.
A21: 45809 | B21: 16.2 | C21: 13.3 | D21: 7.3 | E21: 10.7 | F21: 22.5 | I21: Source: SSSU, NBU staff estimates.
A22: 45839 | B22: 16.2 | C22: 14.6 | D22: 7.2 | E22: 11.3 | F22: 19.9 | H22: 07.25
A23: 45870 | B23: 15.3 | C23: 13.4 | D23: 7.3 | E23: 11.1 | F23: 22.8
A24: 45901 | B24: 16 | C24: 12.1 | D24: 6.6 | E24: 10.9 | F24: 22.7
A25: 45931 | B25: 15.6 | C25: 10.5 | D25: 6.8 | E25: 9 | F25: 22.4
A26: 45962 | B26: 15.5 | C26: 10.7 | D26: 6.4 | E26: 8.7 | F26: 22.2
A27: 45992 | B27: 14.9 | C27: 11.3 | D27: 6.6 | E27: 8.8 | F27: 16
A28: 46023 | B28: 14.2 | C28: 10.1 | D28: 6.6 | E28: 8.6 | F28: 9.8 | G28: 46023 | H28: 46023
A29: 46054 | B29: 14.7 | C29: 11.8 | D29: 6.6 | E29: 8.4 | F29: 16.3
A30: 46082 | B30: 16.2 | C30: 11.7 | D30: 7.1 | E30: 8.2 | F30: 19.5
A31: 46113 | B31: 17.3 | C31: 13.2 | D31: 7.7 | E31: 9.2 | F31: 19.5
A32: 46143 | B32: 17.6 | C32: 13.5 | D32: 8.9 | E32: 9.2 | F32: 19.5
A33: 46174 | B33: 18.4 | C33: 13.7 | D33: 10.2 | E33: 12.2 | F33: 19.4 | G33: 46174 | H33: 46174

Sheet 1.15
A1: << | E1: =IF(Content!$E$1=1,E2,E3) -> Теплова карта БІСЦ*, %
E2: Теплова карта БІСЦ*, %
E3: Core CPI heatmap*, %
A4: 44197 | B4: 100 | D4: 01.21
A5: 44228 | B5: 100
A6: 44256 | B6: 100
A7: 44287 | B7: 100
A8: 44317 | B8: 100
A9: 44348 | B9: 100
A10: 44378 | B10: 100
A11: 44409 | B11: 100
A12: 44440 | B12: 100
A13: 44470 | B13: 100
A14: 44501 | B14: 100
A15: 44531 | B15: 100
A16: 44562 | B16: 100 | D16: 01.22 | E16: =IF(Content!$E$1=1,E17,E18) -> Стандартизовані оцінки (z-scores)
A17: 44593 | B17: 100 | E17: Стандартизовані оцінки (z-scores)
A18: 44621 | B18: 100 | E18: Standardized scores (z-scores)
A19: 44652 | B19: 100 | J19: -3 | K19: 3
A20: 44682 | B20: 100
A21: 44713 | B21: 100 | E21: =IF(Content!$E$1=1,E28,E29) -> * Кольори надають інформацію про те, чи перебуває інфляція окремого компонента вище середнього (червоний) за відповідний період або нижче (синій); насиченість кольорів позначає ступінь такої події, виміряну в стандартних відхиленнях; розмір клітинок позначає розподіл значень між індикаторами.
A22: 44743 | B22: 100
A23: 44774 | B23: 100
A24: 44805 | B24: 100 | E24: =IF(Content!$E$1=1,E26,E27) -> Джерело: ДССУ, розрахунки НБУ.
A25: 44835 | B25: 100
A26: 44866 | B26: 100 | E26: Джерело: ДССУ, розрахунки НБУ.
A27: 44896 | B27: 100 | E27: Source: SSSU, NBU staff estimates.
A28: 44927 | B28: 100 | D28: 01.23 | E28: * Кольори надають інформацію про те, чи перебуває інфляція окремого компонента вище середнього (червоний) за відповідний період або нижче (синій); насиченість кольорів позначає ступінь такої події, виміряну в стандартних відхиленнях; розмір клітинок позначає розподіл значень між індикаторами.
A29: 44958 | B29: 100 | E29: * The colors on the heatmap provide information on whether the inflation of a particular component is above the average (red) for the respective period or below it (blue); the saturation of the colors indicates the degree of such an event measured in standard deviations, and the size of the cells indicates the distribution of values between the indicators.
A30: 44986 | B30: 100
A31: 45017 | B31: 100
A32: 45047 | B32: 100
A33: 45078 | B33: 100
A34: 45108 | B34: 100
A35: 45139 | B35: 100
A36: 45170 | B36: 100
A37: 45200 | B37: 100
A38: 45231 | B38: 100
A39: 45261 | B39: 100
A40: 45292 | B40: 100 | D40: 01.24
A41: 45323 | B41: 100
A42: 45352 | B42: 100
A43: 45383 | B43: 100
A44: 45413 | B44: 100
A45: 45444 | B45: 100
A46: 45474 | B46: 100
A47: 45505 | B47: 100
A48: 45536 | B48: 100
A49: 45566 | B49: 100
A50: 45597 | B50: 100
A51: 45627 | B51: 100
A52: 45658 | B52: 100 | D52: 01.25
A53: 45689 | B53: 100
A54: 45717 | B54: 100
A55: 45748 | B55: 100
A56: 45778 | B56: 100
A57: 45809 | B57: 100
A58: 45839 | B58: 100
A59: 45870 | B59: 100
A60: 45901 | B60: 100
A61: 45931 | B61: 100
A62: 45962 | B62: 100
A63: 45992 | B63: 100
A64: 46023 | B64: 100
... A68: 46143 | B68: 100
A69: 46174 | B69: 100 | D69: 06.26

Sheet 1.16
A1: << | B1: =IF(Content!$E$1=1,B2,B3) -> ІСЦ | C1: =IF(Content!$E$1=1,C2,C3) -> Базовий ІСЦ | E1: =IF(Content!$E$1=1,E2,E3) -> Ануалізовані* зміни ІСЦ та БІСЦ, %
B2: ІСЦ | C2: Базовий ІСЦ | E2: Ануалізовані* зміни ІСЦ та БІСЦ, %
B3: CPI | C3: Core CPI | E3: Annualised* changes in the CPI and Core CPI, %
A4: 45292 | B4: 4.4 | C4: 6.7 | D4: 01.24
A5: 45323 | B5: 4.1 | C5: 5.6
A6: 45352 | B6: 0.1 | C6: 4.6
A7: 45383 | B7: 3.5 | C7: 8.8
A8: 45413 | B8: 3 | C8: 6.2
A9: 45444 | B9: 22.6 | C9: 10.4
A10: 45474 | B10: 13 | C10: 13 | D10: 07.24
A11: 45505 | B11: 20.3 | C11: 11.8
A12: 45536 | B12: 18.4 | C12: 12.6
A13: 45566 | B13: 16.8 | C13: 14.3
A14: 45597 | B14: 21.7 | C14: 15.1
A15: 45627 | B15: 16.7 | C15: 18.4
A16: 45658 | B16: 14.6 | C16: 18.1 | D16: 01.25
A17: 45689 | B17: 11.7 | C17: 8.7
A18: 45717 | B18: 13.4 | C18: 10.6
A19: 45748 | B19: 10.6 | C19: 6.4 | E19: =IF(Content!$E$1=1,E22,E23) -> * Приведена до річного виміру місячна зміна, сезонно скоригована.
A20: 45778 | B20: 13.6 | C20: 9.5 | E20: =IF(Content!$E$1=1,E25,E26) -> Джерело: ДССУ, розрахунки НБУ.
A21: 45809 | B21: 4.3 | C21: 8.5
A22: 45839 | B22: 10.9 | C22: 7.1 | D22: 07.25 | E22: * Приведена до річного виміру місячна зміна, сезонно скоригована.
A23: 45870 | B23: 8.2 | C23: 8.5 | E23: * Annualized monthly change, seasonally adjusted.
A24: 45901 | B24: 2.9 | C24: 7
A25: 45931 | B25: 4.7 | C25: 4.8 | E25: Джерело: ДССУ, розрахунки НБУ.
A26: 45962 | B26: 0.8 | C26: 3.3 | E26: Source: SSSU, NBU staff estimates.
A27: 45992 | B27: 1.6 | C27: 2.2
A28: 46023 | B28: 8.4 | C28: 7.1 | D28: 01.26
A29: 46054 | B29: 15.8 | C29: 8.5
A30: 46082 | B30: 17.5 | C30: 11.6
A31: 46113 | B31: 20.8 | C31: 13
A32: 46143 | B32: 9.5 | C32: 11.4
A33: 46174 | B33: -2.5 | C33: 11.1 | D33: 06.26

Sheet 1.17
A1: << | B1: =IF(Content!$E$1=1,B2,B3) -> Річна зміна | C1: =IF(Content!$E$1=1,C2,C3) -> Річна зміна (попередній прогноз) | D1: =IF(Content!$E$1=1,D2,D3) -> Зміна за квартал | E1: =IF(Content!$E$1=1,E2,E3) -> Зміна за квартал, с/с | H1: =IF(Content!$E$1=1,H2,H3) -> Базовий ІСЦ на кінець періоду, %
B2: Річна зміна | C2: Річна зміна (попередній прогноз) | D2: Зміна за квартал | E2: Зміна за квартал, с/с | H2: Базовий ІСЦ на кінець періоду, %
B3: Annual change | C3: Annual change (previous forecast) | D3: Quarterly change | E3: Quarterly change, sa | H3: Core inflation at the end of period, %
A4: I.24 | B4: 4.2 | D4: 1.8 | E4: 1.3
B5: 5 | D5: 1.5 | E5: 2.2
B6: 7.3 | D6: 3.1 | E6: 2.8
B7: 10.7 | D7: 3.8 | E7: 3.9
A8: I.25 | B8: 12.4 | D8: 3.4 | E8: 2.9
B9: 12.1 | D9: 1.2 | E9: 2
B10: 11 | D10: 2.1 | E10: 1.8
B11: 8 | D11: 1 | E11: 1
A12: I.26 | B12: 7.1 | C12: 7.1 | D12: 2.7 | E12: 2.1
B13: 8.1 | C13: 7.2 | D13: 2.1 | E13: 2.9
B14: 8.3 | C14: 7 | D14: 2.3 | E14: 2
B15: 9.2 | C15: 7.2 | D15: 1.9 | E15: 1.9
A16: I.27 | B16: 8.7 | C16: 6.3 | D16: 2.2 | E16: 1.6
B17: 7.2 | C17: 5.3 | D17: 0.6 | E17: 1.4
B18: 6.1 | C18: 4.6 | D18: 1.3 | E18: 1
B19: 5.1 | C19: 4.3 | D19: 0.9 | E19: 1 | H19: =IF(Content!$E$1=1,H20,H21) -> Джерело: ДССУ, розрахунки НБУ.
A20: I.28 | B20: 4.3 | C20: 4 | D20: 1.4 | E20: 0.8 | H20: Джерело: ДССУ, розрахунки НБУ.
B21: 3.8 | C21: 3.7 | D21: 0 | E21: 0.8 | H21: Source: SSSU, NBU staff estimates.
B22: 3.4 | C22: 3.3 | D22: 1 | E22: 0.7
A23: IV.28 | B23: 3.3 | C23: 3.2 | D23: 0.7 | E23: 0.8

Sheet 1.18
A1: << | B1: =IF(Content!$E$1=1,B2,B3) -> Оброблені продукти | C1: =IF(Content!$E$1=1,C2,C3) -> Сирі продукти | F1: =IF(Content!$E$1=1,F2,F3) -> Компоненти продовольчої інфляції, зміна на кінець періоду, % р/р
B2: Оброблені продукти | C2: Сирі продукти | F2: Компоненти продовольчої інфляції, зміна на кінець періоду, % р/р
B3: Processed foods | C3: Raw foods | F3: Food inflation components at the end of period, % yoy
A4: I.23 | B4: 23.5 | C4: 31.6
B5: 14.7 | C5: 18.2
B6: 10.6 | C6: 0.3
B7: 5.9 | C7: 2.2
A8: I.24 | B8: 5.3 | C8: -4.9
B9: 5.9 | C9: -6.5
B10: 8.9 | C10: 7.1
B11: 14.7 | C11: 13.2
A12: I.25 | B12: 17.3 | C12: 17
B13: 18.2 | C13: 28.7
B14: 16.8 | C14: 18.1
B15: 12.1 | C15: 7.4
A16: I.26 | B16: 10 | C16: 8.4
B17: 10.4 | C17: -0.2
B18: 9.9 | C18: 4.6 | F18: =IF(Content!$E$1=1,F24,F25) -> Джерело: ДССУ, розрахунки НБУ.
B19: 9.8 | C19: 8.3
A20: I.27 | B20: 10 | C20: 7.4
B21: 7.9 | C21: 9.5
B22: 6.3 | C22: 6.7
B23: 4.9 | C23: 5.5
A24: I.28 | B24: 4 | C24: 4.6 | F24: Джерело: ДССУ, розрахунки НБУ.
B25: 3.5 | C25: 4.1 | F25: Source: SSSU, NBU staff estimates.
B26: 3.3 | C26: 3.7
A27: IV.28 | B27: 2.8 | C27: 3.4

Sheet 1.19
A1: << | B1: =IF(Content!$E$1=1,B2,B3) -> Річна зміна | C1: =IF(Content!$E$1=1,C2,C3) -> Річна зміна (попередній прогноз) | D1: =IF(Content!$E$1=1,D2,D3) -> Зміна за квартал | E1: =IF(Content!$E$1=1,E2,E3) -> Зміна за квартал, с/с | H1: =IF(Content!$E$1=1,H2,H3) -> Ціни на сирі продовольчі товари на кінець періоду, %
B2: Річна зміна | C2: Річна зміна (попередній прогноз) | D2: Зміна за квартал | E2: Зміна за квартал, с/с | H2: Ціни на сирі продовольчі товари на кінець періоду, %
B3: Annual change | C3: Annual change (previous forecast) | D3: Quarterly change | E3: Quarterly change, sa | H3: Raw food inflation at the end of period, %
A4: I.24 | B4: -4.9 | D4: 0.9 | E4: -2.3
B5: -6.5 | D5: 0.7 | E5: -1.4
B6: 7.1 | D6: -0.5 | E6: 7.3
B7: 13.2 | D7: 12.1 | E7: 9.2
A8: I.25 | B8: 17 | D8: 4.3 | E8: 1.5
B9: 28.7 | D9: 10.7 | E9: 8.1
B10: 18.1 | D10: -8.7 | E10: -1.2
B11: 7.4 | D11: 2 | E11: -1.2
A12: I.26 | B12: 8.4 | C12: 8.4 | D12: 5.2 | E12: 2.9
B13: -0.2 | C13: 1.3 | D13: 1.8 | E13: 1.5
B14: 4.6 | C14: 5.7 | D14: -4.2 | E14: 3.8
B15: 8.3 | C15: 9.2 | D15: 5.6 | E15: 4.6
A16: I.27 | B16: 7.4 | C16: 7.8 | D16: 4.3 | E16: 3.1
B17: 9.5 | C17: 7.8 | D17: 3.8 | E17: 2
B18: 6.7 | C18: 6 | D18: -6.7 | E18: 4.7 | H18: =IF(Content!$E$1=1,H19,H20) -> Джерело: ДССУ, розрахунки НБУ.
B19: 5.5 | C19: 5.2 | D19: 4.4 | E19: 3.7 | H19: Джерело: ДССУ, розрахунки НБУ.
A20: I.28 | B20: 4.6 | C20: 4.5 | D20: 3.4 | E20: 2.4 | H20: Source: SSSU, NBU staff estimates.
B21: 4.1 | C21: 4 | D21: 3.3 | E21: 1.2
B22: 3.7 | C22: 3.6 | D22: -7.1 | E22: 4
A23: IV.28 | B23: 3.4 | C23: 3.3 | D23: 4.2 | E23: 3.2

Sheet 1.20
A1: << | B1: =IF(Content!$E$1=1,B2,B3) -> Інфляція овочів | C1: =IF(Content!$E$1=1,C2,C3) -> Інфляція фруктів | D1: =IF(Content!$E$1=1,D2,D3) -> Зміна врожаю овочів (+ падіння) | G1: =IF(Content!$E$1=1,G2,G3) -> Окремі компоненти продовольчої інфляції та врожай, зміна на кінець періоду, % р/р
B2: Інфляція овочів | C2: Інфляція фруктів | D2: Зміна врожаю овочів (+ падіння) | G2: Окремі компоненти продовольчої інфляції та врожай, зміна на кінець періоду, % р/р
B3: Vegetables inflation | C3: Fruits inflation | D3: Vegetables crops change (+ indicates a decline) | G3: Individual components of food inflation and harvest, change at the end of period, % yoy
A4: 2021 | B4: 12.8 | C4: -10.2 | D4: -2.9
A5: 2022 | B5: 51.8 | C5: 73.8 | D5: 24.4
A6: 2023 | B6: 3 | C6: 2.2 | D6: -10.5
A7: 2024 | B7: 48.3 | C7: 16.4 | D7: 18.3
A8: 2025 | B8: -29.8 | C8: 15.2 | D8: -20.3
A9: 2026 | B9: 12.9 | C9: 10 | D9: 2
A10: 2027 | B10: 5.1 | C10: 5.4 | D10: -0.8
A11: 2028 | B11: 3.4 | C11: 3.4 | D11: -0.7
G17: =IF(Content!$E$1=1,G18,G19) -> Джерело: ДССУ, розрахунки НБУ.
G18: Джерело: ДССУ, розрахунки НБУ.
G19: Source: SSSU, NBU staff estimates.

Sheet 1.21
A1: << | B1: =IF(Content!$E$1=1,B2,B3) -> Річна зміна | C1: =IF(Content!$E$1=1,C2,C3) -> Річна зміна (попередній прогноз) | D1: =IF(Content!$E$1=1,D2,D3) -> Зміна за квартал | G1: =IF(Content!$E$1=1,G2,G3) -> Адміністративно регульовані ціни на кінець періоду, %
B2: Річна зміна | C2: Річна зміна (попередній прогноз) | D2: Зміна за квартал | G2: Адміністративно регульовані ціни на кінець періоду, %
B3: Annual change | C3: Annual change (previous forecast) | D3: Quarterly change | G3: Administered price inflation at the end of period, %
A4: I.24 | B4: 9.9 | D4: 0.9
B5: 13.3 | D5: 8.6
B6: 14 | D6: 2.1
B7: 16.3 | D7: 3.9
A8: I.25 | B8: 19 | D8: 3.3
B9: 10.9 | D9: 1.2
B10: 10.7 | D10: 1.9
B11: 9.7 | D11: 2.9
A12: I.26 | B12: 8.6 | C12: 8.6 | D12: 2.3
B13: 10.7 | C13: 10.9 | D13: 3.2
B14: 11.7 | C14: 12.7 | D14: 2.8
B15: 13.4 | C15: 14 | D15: 4.5
A16: I.27 | B16: 13.6 | C16: 14.1 | D16: 2.5
B17: 14.1 | C17: 14.3 | D17: 3.6
B18: 15.1 | C18: 14.4 | D18: 3.7
B19: 14 | C19: 14.4 | D19: 3.5 | G19: =IF(Content!$E$1=1,G20,G21) -> Джерело: ДССУ, розрахунки НБУ.
A20: I.28 | B20: 13.3 | C20: 13.6 | D20: 1.8 | G20: Джерело: ДССУ, розрахунки НБУ.
B21: 12.5 | C21: 12.8 | D21: 2.9 | G21: Source: SSSU, NBU staff estimates.
B22: 11.7 | C22: 12.1 | D22: 3
A23: IV.28 | B23: 11.3 | C23: 11.4 | D23: 3.1

Sheet 1.22
A1: << | B1: =IF(Content!$E$1=1,B2,B3) -> Річна зміна | C1: =IF(Content!$E$1=1,C2,C3) -> Річна зміна (попередній прогноз) | D1: =IF(Content!$E$1=1,D2,D3) -> Зміна за квартал | G1: =IF(Content!$E$1=1,G2,G3) -> Ціни на пальне на кінець періоду, %
B2: Річна зміна | C2: Річна зміна (попередній прогноз) | D2: Зміна за квартал | G2: Ціни на пальне на кінець періоду, %
B3: Annual change | C3: Annual change (previous forecast) | D3: Quarterly change | G3: Fuel price at the end of period, %
A4: I.24 | B4: 3.2 | D4: -2.5
B5: 25.5 | D5: 5.3
B6: 6 | D6: 2.2
B7: 4.8 | D7: -0.1
A8: I.25 | B8: 9.9 | D8: 2.3
B9: 3.1 | D9: -1.2
B10: 4.7 | D10: 3.6
B11: 6.4 | D11: 1.6
A12: I.26 | B12: 23.4 | C12: 23.4 | D12: 18.6
B13: 33.4 | C13: 31.8 | D13: 6.8
B14: 29.4 | C14: 26.2 | D14: 0.6
B15: 25.7 | C15: 24.3 | D15: -1.3
A16: I.27 | B16: 6.9 | C16: 5.9 | D16: 0.8
B17: 0.3 | C17: 0.7 | D17: 0.2
B18: -0.2 | C18: 1.5 | D18: 0.1
B19: 1.1 | C19: 1.7 | D19: 0 | G19: =IF(Content!$E$1=1,G20,G21) -> Джерело: ДССУ, розрахунки НБУ.
A20: I.28 | B20: 1.5 | C20: 1.5 | D20: 1.2 | G20: Джерело: ДССУ, розрахунки НБУ.
B21: 2.2 | C21: 1.4 | D21: 1 | G21: Source: SSSU, NBU staff estimates.
B22: 2.8 | C22: 1.2 | D22: 0.7
A23: IV.28 | B23: 3.6 | C23: 1.1 | D23: 0.8

Sheet 1.23
A1: << | C1: =IF(Content!$E$1=1,C2,C3) -> Річна зміна | D1: =IF(Content!$E$1=1,D2,D3) -> Зміна за квартал | E1: =IF(Content!$E$1=1,E2,E3) -> Річна зміна (попередній прогноз) | I1: =IF(Content!$E$1=1,I2,I3) -> Цільовий діапазон | J1: =IF(Content!$E$1=1,J2,J3) -> Ціль | M1: =IF(Content!$E$1=1,M2,M3) -> ІСЦ на кінець періоду, %
C2: Річна зміна | D2: Зміна за квартал | E2: Річна зміна (попередній прогноз) | I2: Цільовий діапазон | J2: Ціль | M2: ІСЦ на кінець періоду, %
C3: Annual change | D3: Quarterly change | E3: Annual change (previous forecast) | I3: Target range | J3: Inflation target | M3: CPI at the end of period, %
A4: I.24 | C4: 3.2 | D4: 1.2 | F4: 4 | G4: 5 | H4: 6 | I4: 2 | J4: 5
C5: 4.8 | D5: 3 | F5: 4 | G5: 5 | H5: 6 | I5: 2 | J5: 5
C6: 8.6 | D6: 2.1 | F6: 4 | G6: 5 | H6: 6 | I6: 2 | J6: 5
C7: 12 | D7: 5.2 | F7: 5 | G7: 5 | H7: 5 | J7: 5
A8: I.25 | C8: 14.6 | D8: 3.5 | F8: 5 | G8: 5 | J8: 5
C9: 14.3 | D9: 2.8 | F9: 5 | G9: 5 | J9: 5
C10: 11.9 | D10: -0.1 | F10: 5 | G10: 5 | J10: 5
C11: 8 | D11: 1.5 | F11: 5 | G11: 5 | J11: 5
A12: I.26 | C12: 7.9 | D12: 3.4 | E12: 7.9 | F12: 5 | G12: 5 | J12: 5
C13: 7.2 | D13: 2.2 | E13: 7.3 | F13: 5 | G13: 5 | J13: 5
C14: 8.4 | D14: 1 | E14: 8.3 | F14: 5 | G14: 5 | J14: 5
C15: 10 | D15: 3 | E15: 9.4 | F15: 5 | G15: 5 | J15: 5
A16: I.27 | C16: 9.1 | D16: 2.6 | E16: 8.2 | F16: 5 | G16: 5 | J16: 5 | M16: =IF(Content!$E$1=1,M17,M18) -> Джерело: ДССУ, розрахунки НБУ.
C17: 8.7 | D17: 1.8 | E17: 7.5 | F17: 5 | G17: 5 | J17: 5 | M17: Джерело: ДССУ, розрахунки НБУ.
C18: 7.8 | D18: 0.1 | E18: 6.9 | F18: 5 | G18: 5 | J18: 5 | M18: Source: SSSU, NBU staff estimates.
C19: 6.9 | D19: 2.1 | E19: 6.5 | F19: 5 | G19: 5 | J19: 5
A20: I.28 | C20: 6.1 | D20: 1.9 | E20: 6.1 | F20: 5 | G20: 5 | J20: 5
C21: 5.6 | D21: 1.4 | E21: 5.7 | F21: 5 | G21: 5 | J21: 5
C22: 5.2 | D22: -0.2 | E22: 5.3 | F22: 5 | G22: 5 | J22: 5
A23: IV.28 | C23: 5 | D23: 1.9 | E23: 5 | F23: 5 | G23: 5 | J23: 5

Sheet 1.24
A1: << | B1: =IF(Content!$E$1=1,B2,B3) -> ІСЦ, % | C1: =IF(Content!$E$1=1,C2,C3) -> Базова інфляція | D1: =IF(Content!$E$1=1,D2,D3) -> Сирі продукти | E1: =IF(Content!$E$1=1,E2,E3) -> Адміністративні тарифи | F1: =IF(Content!$E$1=1,F2,F3) -> Паливо | I1: =IF(Content!$E$1=1,I2,I3) -> Внески компонентів у річну зміну ІСЦ (в. п.)
B2: ІСЦ, % | C2: Базова інфляція | D2: Сирі продукти | E2: Адміністративні тарифи | F2: Паливо | I2: Внески компонентів у річну зміну ІСЦ (в. п.)
B3: CPI, % | C3: Core inflation | D3: Raw foods | E3: Administrative tariffs | F3: Fuel | I3: Contributions to annual CPI change by components, pp
A4: I.24 | B4: 3.2 | C4: 2.3 | D4: -0.9 | E4: 1.7 | F4: 0.1
B5: 4.8 | C5: 2.8 | D5: -1.3 | E5: 2.2 | F5: 1.1
B6: 8.6 | C6: 4 | D6: 1.4 | E6: 2.9 | F6: 0.3
B7: 12 | C7: 5.8 | D7: 2.6 | E7: 3.4 | F7: 0.2
A8: I.25 | B8: 14.6 | C8: 6.8 | D8: 3.4 | E8: 4 | F8: 0.5
B9: 14.3 | C9: 6.7 | D9: 5.6 | E9: 1.9 | F9: 0.1
B10: 11.9 | C10: 6.1 | D10: 3.6 | E10: 2.1 | F10: 0.2
B11: 8 | C11: 4.4 | D11: 1.4 | E11: 2 | F11: 0.2
A12: I.26 | B12: 7.9 | C12: 4 | D12: 1.6 | E12: 1.5 | F12: 0.8
B13: 7.2 | C13: 4.6 | D13: 0 | E13: 1.6 | F13: 1.1
B14: 8.4 | C14: 4.7 | D14: 0.9 | E14: 1.9 | F14: 1
B15: 10 | C15: 5.2 | D15: 1.6 | E15: 2.4 | F15: 0.9
A16: I.27 | B16: 9.1 | C16: 4.9 | D16: 1.4 | E16: 2.6 | F16: 0.2
B17: 8.7 | C17: 4 | D17: 1.8 | E17: 2.9 | F17: 0
B18: 7.8 | C18: 3.4 | D18: 1.2 | E18: 3.1 | F18: 0
B19: 6.9 | C19: 2.9 | D19: 1 | E19: 2.9 | F19: 0 | I19: =IF(Content!$E$1=1,I20,I21) -> Джерело: ДССУ, розрахунки НБУ.
A20: I.28 | B20: 6.1 | C20: 2.4 | D20: 0.8 | E20: 2.8 | F20: 0 | I20: Джерело: ДССУ, розрахунки НБУ.
B21: 5.6 | C21: 2.1 | D21: 0.8 | E21: 2.7 | F21: 0.1 | I21: Source: SSSU, NBU staff estimates.
B22: 5.2 | C22: 1.9 | D22: 0.7 | E22: 2.5 | F22: 0.1
A23: IV.28 | B23: 5 | C23: 1.8 | D23: 0.6 | E23: 2.5 | F23: 0.1

Sheet 2.1
A1: << | B1: =IF(Content!$E$1=1,B2,B3) -> Промисловість | C1: =IF(Content!$E$1=1,C2,C3) -> Добувна | D1: =IF(Content!$E$1=1,D2,D3) -> Переробна | E1: =IF(Content!$E$1=1,E2,E3) -> Енергетика | H1: =IF(Content!$E$1=1,H2,H3) -> Індекс промислової продукції за видами економічної діяльності*, % р/р | T1: 1
B2: Промисловість | C2: Добувна | D2: Переробна | E2: Енергетика | H2: Індекс промислової продукції за видами економічної діяльності*, % р/р
B3: Industry | C3: Mining | D3: Manufacturing | E3: Energy | H3: Production in main manufacturing sectors*, % yoy
A4: І.24 | B4: 13 | C4: 8.9 | D4: 15.8 | E4: 10.3 | F4: 01.24
A5: ІІ.24 | B5: 6.4 | C5: 3.3 | D5: 11 | E5: -6.6
A6: ІІІ.24 | B6: 0.5 | C6: -1 | D6: 3.4 | E6: -9.4
A7: ІV.24 | B7: 0.7 | C7: 3.5 | D7: 0.6 | E7: -3.6
A8: І.25 | B8: -5.3 | C8: -14.9 | D8: -0.9 | E8: -5.7
A9: ІІ.25 | B9: -0.3 | C9: -10.1 | D9: 2.5 | E9: 6.1
A10: ІІІ.25 | B10: 2.7 | C10: -1.7 | D10: 3.6 | E10: 8.4 | F10: 07.24
A11: ІV.25 | B11: -3.3 | C11: -14.7 | D11: 2.7 | E11: -10.2
A12: І.26 | B12: -2.1 | C12: 3.4 | D12: -0.3 | E12: -15.2
A13: ІІ.26 | B13: 0.9 | C13: 4.3 | D13: 2.1 | E13: -10.8
F16: 01.25
H17: =IF(Content!$E$1=1,H19,H21) -> * Квартальні значення індексу розраховані як середні значення за три місяці кварталу.
H18: =IF(Content!$E$1=1,H20,H22) -> Джерело: ДССУ.
H19: * Квартальні значення індексу розраховані як середні значення за три місяці кварталу.
H20: Джерело: ДССУ.
H21: * Quarterly index values ​​are calculated as average values ​​for the three months of the quarter.
F22: 07.25 | H22: Source: SSSU.
F27: 12.25

Sheet 2.2
A1: << | B1: =IF(Content!$E$1=1,B2,B3) -> Промисловість | C1: =IF(Content!$E$1=1,C2,C3) -> С/г | D1: =IF(Content!$E$1=1,D2,D3) -> Будівництво | E1: =IF(Content!$E$1=1,E2,E3) -> Торгівля | F1: =IF(Content!$E$1=1,F2,F3) -> Транспорт | G1: =IF(Content!$E$1=1,G2,G3) -> Сектори послуг | H1: =IF(Content!$E$1=1,H2,H3) -> ІДО | K1: =IF(Content!$E$1=1,K2,K3) -> Індекс ділових очікувань за видами діяльності, %
B2: Промисловість | C2: С/г | D2: Будівництво | E2: Торгівля | F2: Транспорт | G2: Сектори послуг | H2: ІДО | K2: Індекс ділових очікувань за видами діяльності, %
B3: Industry | C3: Agriculture | D3: Construction | E3: Trade | F3: Transportation | G3: Services | H3: BOI | K3: Business Outlook Index by type of activity, %
A4: І.22 | B4: 10.6 | C4: 5.1 | D4: -4.2 | E4: 8.2 | F4: 6.7 | G4: 9.8 | H4: 8.2
A5: ІІ.22 | B5: -31.5 | C5: -26.9 | D5: -23.3 | E5: -24 | F5: -22.6 | G5: -29.1 | H5: -27.4 | I5: ІІ.22
A6: ІІІ.22 | B6: -23 | C6: -20.4 | D6: -25 | E6: -21.9 | F6: -12.5 | G6: -19.6 | H6: -20.5
A7: IV.22 | B7: -22.1 | C7: -27.2 | D7: -9 | E7: -8.4 | F7: -8.5 | G7: -14.6 | H7: -16.5 | I7: IV.22
A8: І.23 | B8: -7 | C8: -10.3 | D8: -23.1 | E8: -11.2 | F8: -0.9 | G8: -11.3 | H8: -8.8
A9: ІІ.23 | B9: 4.2 | C9: -5.8 | D9: 26 | E9: 6.2 | F9: 5.3 | G9: 6.7 | H9: 4.5 | I9: ІІ.23
A10: ІІІ.23 | B10: 3.9 | C10: -1.4 | D10: 6.1 | E10: 9 | F10: 6.4 | G10: 3.3 | H10: 4.5
A11: IV.23 | B11: 3.7 | C11: -7.4 | D11: 3 | E11: 6.5 | F11: -0.8 | G11: 1.1 | H11: 1.6 | I11: IV.23
A12: I.24 | B12: 1.7 | C12: -0.2 | D12: -0.8 | E12: 5.1 | F12: 5.8 | G12: 3.4 | H12: 3
A13: II.24 | B13: 2.2 | C13: 1.4 | D13: -3.2 | E13: -3.3 | F13: 0 | G13: -2.9 | H13: -0.5 | I13: II.24
A14: IIІ.24 | B14: 1.1 | C14: 0.4 | D14: 2.1 | E14: 0.1 | F14: 5.2 | G14: -3.3 | H14: 0.6
A15: IV.24 | B15: 4.8 | C15: 2 | D15: -10.5 | E15: -1 | F15: 3.8 | G15: 0.2 | H15: 1.8 | I15: IV.24
A16: I.25 | B16: 12.6 | C16: 12.1 | D16: 6.9 | E16: 3 | F16: 1.8 | G16: 8.4 | H16: 8.2
A17: II.25 | B17: 6 | C17: 4.8 | D17: 13.3 | E17: -2 | F17: 0.8 | G17: 2.6 | H17: 3.1 | I17: II.25
A18: IІI.25 | B18: 6.5 | C18: 3.6 | D18: -5.7 | E18: -0.2 | F18: 1.2 | G18: -0.2 | H18: 2.5 | K18: =IF(Content!$E$1=1,K19,K20) -> Джерело: НБУ.
A19: IV.25 | B19: 5.1 | C19: -3.5 | D19: 1.9 | E19: 1.3 | F19: 0.9 | G19: 3.3 | H19: 2.1 | I19: IV.25 | K19: Джерело: НБУ.
A20: I.26 | B20: 8.9 | C20: 4.2 | D20: 1 | E20: 0.8 | F20: 9.2 | G20: 6 | H20: 5.8 | K20: Source: NBU.
A21: II.26 | B21: 6.3 | C21: 12.9 | D21: 8.9 | E21: 1 | F21: 6.1 | G21: 11.1 | H21: 7 | I21: II.26

Sheet 2.3
A1: << | B1: =IF(Content!$E$1=1,B2,B3) -> Вантажообіг | C1: =IF(Content!$E$1=1,C2,C3) -> Пасажирообіг | F1: =IF(Content!$E$1=1,F2,F3) -> Індекс вантажо- та пасажирообігу*, % р/р
B2: Вантажообіг | C2: Пасажирообіг | F2: Індекс вантажо- та пасажирообігу*, % р/р
B3: Freight turnover | C3: Passenger turnover | F3: Freight and passenger turnover index*, % yoy
A4: I.24 | B4: 22.2 | C4: 22.7
A5: II.24 | B5: 18.4 | C5: 12.3
A6: III.24 | B6: 9.7 | C6: 3.9
A7: IV.24 | B7: 4.8 | C7: 2.7
A8: I.25 | B8: -14.9 | C8: 5.3
A9: II.25 | B9: -9.7 | C9: 5
A10: IIІ.25 | B10: -16.6 | C10: 6.7
A11: IV.25 | B11: -17.8 | C11: -0.2
A12: I.26 | B12: -12.4 | C12: -8.3
A13: II.26 | B13: -7.4 | C13: -4
F16: =IF(Content!$E$1=1,F18,F20) -> * Квартальні значення індексу розраховані як середні значення за три місяці кварталу.
F17: =IF(Content!$E$1=1,F19,F21) -> Джерело: ДССУ.
F18: * Квартальні значення індексу розраховані як середні значення за три місяці кварталу.
F19: Джерело: ДССУ.
F20: * Quarterly index values ​​are calculated as average values ​​for the three months of the quarter.
F21: Source: SSSU.

Sheet 2.4
A1: << | B1: =IF(Content!$E$1=1,B2,B3) -> Будівництво | C1: =IF(Content!$E$1=1,C2,C3) -> Житлові будинки | D1: =IF(Content!$E$1=1,D2,D3) -> Нежитлові будівлі | E1: =IF(Content!$E$1=1,E2,E3) -> Інженерні споруди | H1: =IF(Content!$E$1=1,H2,H3) -> Індекс будівельної продукції*, % р/р
B2: Будівництво | C2: Житлові будинки | D2: Нежитлові будівлі | E2: Інженерні споруди | H2: Індекс будівельної продукції*, % р/р
B3: Construction | C3: Residential buildings | D3: Non-residential buildings | E3: Engineering structures | H3: Construction output index*, % yoy
A4: І.24 | B4: 39.3 | C4: 23.3 | D4: 41.4 | E4: 43.9
A5: ІІ.24 | B5: 42.3 | C5: 19.1 | D5: 36.2 | E5: 52.7
A6: ІІІ.24 | B6: 6.5 | C6: 3.7 | D6: 20 | E6: 0.7
A7: ІV.24 | B7: 9.1 | C7: -2.1 | D7: 26.9 | E7: 4.2
A8: І.25 | B8: 0.3 | C8: 0 | D8: 28.9 | E8: -12.2
A9: ІІ.25 | B9: 14.1 | C9: 12.3 | D9: 31.3 | E9: 7.5
A10: ІІІ.25 | B10: 30.2 | C10: 19.3 | D10: 32.2 | E10: 33
A11: ІV.25 | B11: 5 | C11: 21.6 | D11: 16.4 | E11: -4.5
A12: І.26 | B12: -4.8 | C12: -14.7 | D12: -11.8 | E12: 4.8
A13: ІІ.26 | B13: -7.5 | C13: -0.1 | D13: -12.8 | E13: -5.4
H17: =IF(Content!$E$1=1,H19,H21) -> * Квартальні значення індексу розраховані як середні значення за три місяці кварталу; значення індексу в ІІ кварталі 2026 – середнє за квітень–травень.
H18: =IF(Content!$E$1=1,H20,H22) -> Джерело: ДССУ.
H19: * Квартальні значення індексу розраховані як середні значення за три місяці кварталу; значення індексу в ІІ кварталі 2026 – середнє за квітень–травень.
H20: Джерело: ДССУ.
H21: * Quarterly index values ​​are calculated as average values ​​for the three months of the quarter; the index value in Q1 2026 is the average for April-May.
H22: Source: SSSU.
B32: 39.3 | C32: 42.3 | D32: 6.5 | E32: 9.1 | F32: 0.3 | G32: 14.1 | H32: 30.2 | I32: 5 | J32: -4.8 | K32: -7.5
B33: 34 | C33: 30 | D33: 14.4 | E33: 17.9 | F33: 18.1 | G33: 24.7 | H33: 27.9 | I33: 17.7 | J33: -12.7 | K33: -9
B34: 23.3 | C34: 19.1 | D34: 3.7 | E34: -2.1 | F34: 0 | G34: 12.3 | H34: 19.3 | I34: 21.6 | J34: -14.7 | K34: -0.1
B35: 41.4 | C35: 36.2 | D35: 20 | E35: 26.9 | F35: 28.9 | G35: 31.3 | H35: 32.2 | I35: 16.4 | J35: -11.8 | K35: -12.8
B36: 43.9 | C36: 52.7 | D36: 0.7 | E36: 4.2 | F36: -12.2 | G36: 7.5 | H36: 33 | I36: -4.5 | J36: 4.8 | K36: -5.4
B37: 39.3 | C37: 23.3 | D37: 41.4 | E37: 43.9
B38: 42.3 | C38: 19.1 | D38: 36.2 | E38: 52.7
B39: 6.5 | C39: 3.7 | D39: 20 | E39: 0.7
B40: 9.1 | C40: -2.1 | D40: 26.9 | E40: 4.2
B41: 0.3 | C41: 0 | D41: 28.9 | E41: -12.2
B42: 14.1 | C42: 12.3 | D42: 31.3 | E42: 7.5
B43: 30.2 | C43: 19.3 | D43: 32.2 | E43: 33
B44: 5 | C44: 21.6 | D44: 16.4 | E44: -4.5
B45: -4.8 | C45: -14.7 | D45: -11.8 | E45: 4.8
B46: -7.5 | C46: -0.1 | D46: -12.8 | E46: -5.4

Sheet 2.5
A1: << | B1: =IF(Content!$E$1=1,B2,B3) -> ІЕД | C1: =IF(Content!$E$1=1,C2,C3) -> НБУ | F1: =IF(Content!$E$1=1,F2,F3) -> Нестача працівників як проблема бізнесу, % відповідей
B2: ІЕД | C2: НБУ | F2: Нестача працівників як проблема бізнесу, % відповідей
B3: IER | C3: NBU | F3: Labor shortages as a business challenge, % of responses
A4: 44562
A5: 44593 | C5: 26.14
A6: 44621
A7: 44652
A8: 44682 | B8: 39 | C8: 14.02
A9: 44713 | B9: 34
A10: 44743 | B10: 34
A11: 44774 | B11: 13 | C11: 15.26
A12: 44805 | B12: 15
A13: 44835 | B13: 16
A14: 44866 | B14: 16 | C14: 13.81
A15: 44896 | B15: 19
A16: 44927 | B16: 22
A17: 44958 | B17: 26 | C17: 19.41 | F17: =IF(Content!$E$1=1,F18,F19) -> Джерело: опитування ІЕД, НБУ.
A18: 44986 | B18: 30 | F18: Джерело: опитування ІЕД, НБУ.
A19: 45017 | B19: 31 | F19: Source: IER, NBU surveys.
A20: 45047 | B20: 29 | C20: 24.55
A21: 45078 | B21: 37
A22: 45108 | B22: 38
A23: 45139 | B23: 35 | C23: 25.6
A24: 45170 | B24: 37
A25: 45200 | B25: 32
A26: 45231 | B26: 35 | C26: 34
A27: 45261 | B27: 46
A28: 45292 | B28: 41
A29: 45323 | B29: 46 | C29: 37.8
A30: 45352 | B30: 50
A31: 45383 | B31: 43
A32: 45413 | B32: 49 | C32: 39.8
A33: 45444 | B33: 42
A34: 45474 | B34: 47
A35: 45505 | B35: 63 | C35: 45.8
A36: 45536 | B36: 61
A37: 45566 | B37: 57
A38: 45597 | B38: 64 | C38: 47.3
A39: 45627 | B39: 61
A40: 45658 | B40: 65
A41: 45689 | B41: 64 | C41: 49.4
A42: 45717 | B42: 65
A43: 45748 | B43: 57
A44: 45778 | B44: 63 | C44: 49.2
A45: 45809 | B45: 58
A46: 45839 | B46: 57
A47: 45870 | B47: 62 | C47: 46
A48: 45901 | B48: 60
A49: 45931 | B49: 59
A50: 45962 | B50: 61 | C50: 47.2
A51: 45992 | B51: 62
A52: 46023 | B52: 60
A53: 46054 | B53: 64 | C53: 46.8
A54: 46082 | B54: 67
A55: 46113 | B55: 68
A56: 46143 | B56: 69 | C56: 51.9
A57: 46174 | B57: 71

Sheet 2.6
A1: << | B1: =IF(Content!$E$1=1,B2,B3) -> С/г | C1: =IF(Content!$E$1=1,C2,C3) -> Промисловість | D1: =IF(Content!$E$1=1,D2,D3) -> Будівництво | E1: =IF(Content!$E$1=1,E2,E3) -> Торгівля | F1: =IF(Content!$E$1=1,F2,F3) -> Транспорт | G1: =IF(Content!$E$1=1,G2,G3) -> Послуги | H1: =IF(Content!$E$1=1,H2,H3) -> Загалом | K1: =IF(Content!$E$1=1,K2,K3) -> Брак кваліфікованих працівників як чинник, що обмежує спроможності збільшувати виробництво, % відповідей
B2: С/г | C2: Промисловість | D2: Будівництво | E2: Торгівля | F2: Транспорт | G2: Послуги | H2: Загалом | K2: Брак кваліфікованих працівників як чинник, що обмежує спроможності збільшувати виробництво, % відповідей
B3: Agriculture | C3: Industry | D3: Construction | E3: Trade | F3: Transport | G3: Services | H3: Total | K3: Shortage of skilled workers as a factor limiting the ability to increase production, % of responses
A4: I.21 | B4: 17.5 | C4: 24.8 | D4: 38.1 | E4: 21.3 | F4: 24.2 | G4: 34.4 | H4: 25
A5: II.21 | B5: 19 | C5: 23.9 | D5: 55 | E5: 19.9 | F5: 30.1 | G5: 38.3 | H5: 26.8
A6: III.21 | B6: 20.4 | C6: 23.3 | D6: 36.4 | E6: 21.7 | F6: 30.4 | G6: 37.9 | H6: 26.5
A7: IV.21 | B7: 21.8 | C7: 25.1 | D7: 31.8 | E7: 21 | F7: 29.7 | G7: 43 | H7: 27.9
A8: I.22 | B8: 22 | C8: 22.5 | D8: 35 | E8: 22.2 | F8: 26.8 | G8: 37.3 | H8: 26.1
A9: II.22 | B9: 11.8 | C9: 13.2 | D9: 33.3 | E9: 9 | F9: 13.9 | G9: 21.3 | H9: 14
A10: III.22 | B10: 9.6 | C10: 15.7 | D10: 15.8 | E10: 11.8 | F10: 22.4 | G10: 17.9 | H10: 15.3
A11: IV.22 | B11: 8.9 | C11: 16.3 | D11: 10.5 | E11: 7.4 | F11: 16.9 | G11: 19.3 | H11: 13.8
A12: I.23 | B12: 10.8 | C12: 24.5 | D12: 28.6 | E12: 13.3 | F12: 20 | G12: 22.8 | H12: 19.4
A13: II.23 | B13: 16.3 | C13: 26.2 | D13: 40 | E13: 21 | F13: 23.1 | G13: 30.8 | H13: 24.5
A14: III.23 | B14: 14.9 | C14: 30.2 | D14: 55 | E14: 22.9 | F14: 23.8 | G14: 26.1 | H14: 25.6
A15: IV.23 | B15: 19.8 | C15: 37.4 | D15: 61.9 | E15: 34 | F15: 34.1 | G15: 34.8 | H15: 34
A16: I.24 | B16: 26.8 | C16: 45.4 | D16: 70 | E16: 32.6 | F16: 34.4 | G16: 37.9 | H16: 37.8 | K16: =IF(Content!$E$1=1,K17,K18) -> Джерело: НБУ.
A17: II.24 | B17: 28.7 | C17: 45.2 | D17: 70 | E17: 36.2 | F17: 43 | G17: 36.7 | H17: 39.8 | K17: Джерело: НБУ.
A18: III.24 | B18: 28.4 | C18: 52.8 | D18: 65 | E18: 40.6 | F18: 47.2 | G18: 50 | H18: 45.8 | K18: Source: NBU.
A19: IV.24 | B19: 39.8 | C19: 50.5 | D19: 73.7 | E19: 47.5 | F19: 51.7 | G19: 40 | H19: 47.3
A20: I.25 | B20: 42.1 | C20: 56.1 | D20: 57.1 | E20: 42.9 | F20: 56.5 | G20: 44.4 | H20: 49.4
A21: II.25 | B21: 44.2 | C21: 53.3 | D21: 81 | E21: 46.4 | F21: 48.4 | G21: 44.3 | H21: 49.2
A22: III.25 | B22: 41.1 | C22: 51.4 | D22: 66.7 | E22: 40.9 | F22: 49.5 | G22: 40.2 | H22: 46
A23: IV.25 | B23: 35.8 | C23: 52 | D23: 72.7 | E23: 42.1 | F23: 46.7 | G23: 50 | H23: 47.2
A24: I.26 | B24: 33.3 | C24: 51 | D24: 71.4 | E24: 45.7 | F24: 51.1 | G24: 44.4 | H24: 46.8
A25: II.26 | B25: 46.3 | C25: 59.6 | D25: 76.2 | E25: 42.4 | F25: 45.7 | G25: 54.8 | H25: 51.9

Sheet 2.7
A1: << | B1: =IF(Content!$E$1=1,B2,B3) -> Фіскальний імпульс | C1: =IF(Content!$E$1=1,C2,C3) -> Циклічне первинне сальдо, с/с, % потенційного ВВП | D1: =IF(Content!$E$1=1,D2,D3) -> Загальне сальдо без грантів, % ВВП | E1: =IF(Content!$E$1=1,E2,E3) -> Реальний ВВП, % | H1: =IF(Content!$E$1=1,H2,H3) -> Сальдо СЗДУ за різними вимірами* та реальний ВВП
B2: Фіскальний імпульс | C2: Циклічне первинне сальдо, с/с, % потенційного ВВП | D2: Загальне сальдо без грантів, % ВВП | E2: Реальний ВВП, % | H2: Сальдо СЗДУ за різними вимірами* та реальний ВВП
B3: Fiscal impulse | C3: Cyclically adjusted primary balance, SA, % of potential GDP | D3: Overall balance excl. grants, % of GDP | E3: Real GDP, % | H3: General government fiscal balance* and real GDP
A5: I.22 | B5: 4.33 | C5: -4.45 | D5: -5.1 | E5: -14.6 | F5: I.22
A6: ІI.22 | B6: 6.86 | C6: -7.57 | D6: -37.5 | E6: -36.6
A7: IІI.22 | B7: 25.75 | C7: -24.67 | D7: -21.2 | E7: -30.8 | F7: IІI.22
A8: IV.22 | B8: 21.78 | C8: -26.23 | D8: -33 | E8: -30.6 | P8: 4.5
A9: I.23 | B9: 23.06 | C9: -27.51 | D9: -22.65 | E9: -10.2 | F9: I.23 | O9: -50 | P9: 4.5
A10: ІI.23 | B10: 21.14 | C10: -28.71 | D10: -24.03 | E10: 19.3 | O10: 30 | P10: 8.5
A11: IІI.23 | B11: 6.36 | C11: -31.03 | D11: -21.3 | E11: 9.7 | F11: IІI.23 | P11: 8.5
A12: IV.23 | B12: -0.54 | C12: -25.7 | D12: -34.92 | E12: 5.2 | P12: 12.5
A13: I.24 | B13: -5.45 | C13: -22.07 | D13: -12.7 | E13: 7 | F13: I.24 | P13: 12.5
A14: II.24 | B14: -4.21 | C14: -24.51 | D14: -22.72 | E14: 4.4
A15: III.24 | B15: -3.71 | C15: -27.32 | D15: -19.07 | E15: 2.4 | F15: III.24
A16: IV.24 | B16: 0.55 | C16: -26.25 | D16: -37.53 | E16: 0.3
A17: I.25 | B17: 4.38 | C17: -26.45 | D17: -15.87 | E17: 0.8 | F17: I.25
A18: II.25 | B18: -3.63 | C18: -20.88 | D18: -20.42 | E18: 0.9 | H18: =IF(Content!$E$1=1,H22,H23) -> * Загальне сальдо – сальдо зведеного бюджету з урахуванням позичок ПФУ. Циклічне скориговане первинне сальдо – різниця між с/с доходами, у структурі яких податкові надходження скориговано на циклічні зміни ВВП, та с/с первинними видатками. Із доходів вирахувано одноразові надходження. Від’ємне значення означає м’яку політику. Для фіскального імпульсу додатне значення – стимулююча політика. ВВП 2026 року – оцінка НБУ.
A19: IIІ.25 | B19: 0.81 | C19: -28.13 | D19: -18.88 | E19: 2.4 | F19: IIІ.25 | H19: =IF(Content!$E$1=1,H20,H21) -> Джерело: ДКСУ, ДССУ, розрахунки НБУ.
A20: IV.25 | B20: 5.16 | C20: -31.41 | D20: -40.51 | E20: 2.8 | H20: Джерело: ДКСУ, ДССУ, розрахунки НБУ.
A21: I.26 | B21: -5.66 | C21: -20.79 | D21: -13.23 | E21: -0.6 | H21: Source: STSU, SSSU, NBU staff estimates.
A22: ІI.26 | B22: 7.28 | C22: -28.15 | D22: -24.16 | E22: 0.6 | F22: ІI.26 | H22: * Загальне сальдо – сальдо зведеного бюджету з урахуванням позичок ПФУ. Циклічне скориговане первинне сальдо – різниця між с/с доходами, у структурі яких податкові надходження скориговано на циклічні зміни ВВП, та с/с первинними видатками. Із доходів вирахувано одноразові надходження. Від’ємне значення означає м’яку політику. Для фіскального імпульсу додатне значення – стимулююча політика. ВВП 2026 року – оцінка НБУ.
H23: * The overall balance is the consolidated budget balance, taking into account loans to the PFU from the STA. The cyclically adjusted primary fiscal balance (CAPB) is the difference between seasonally adjusted revenues, in the structure of which tax revenues are adjusted for cyclical changes in GDP, and seasonally adjusted primary expenditures. Additionally, one-off proceeds are subtracted from revenues. A negative value indicates expansionary fiscal policy. For fiscal impulse, a positive value is stimulus policy. The 2026 GDP figure is the NBU's estimate.

Sheet 2.8
A1: << | D1: =IF(Content!$E$1=1,D2,D3) -> I.22 | E1: =IF(Content!$E$1=1,E2,E3) -> ІI.22 | F1: =IF(Content!$E$1=1,F2,F3) -> ІІI.22 | G1: =IF(Content!$E$1=1,G2,G3) -> ІV.22 | H1: =IF(Content!$E$1=1,H2,H3) -> I.23 | I1: =IF(Content!$E$1=1,I2,I3) -> II.23 | J1: =IF(Content!$E$1=1,J2,J3) -> III.23 | K1: =IF(Content!$E$1=1,K2,K3) -> IV.23 | ... U1: =IF(Content!$E$1=1,U2,U3) -> ІI.26 | W1: =IF(Content!$E$1=1,W2,W3) -> Видатки зведеного бюджету, млрд грн (економічна класифікація)
D2: I.22 | E2: ІI.22 | F2: ІІI.22 | G2: ІV.22 | H2: I.23 | I2: II.23 | J2: III.23 | K2: IV.23 | L2: I.24 | M2: II.24 | N2: III.24 | O2: IV.24 | P2: I.25 | Q2: II.25 | R2: III.25 | S2: IV.25 | T2: I.26 | U2: ІI.26 | W2: Видатки зведеного бюджету, млрд грн (економічна класифікація)
D3: I.22 | E3: ІI.22 | F3: ІІI.22 | G3: ІV.22 | H3: I.23 | I3: II.23 | J3: III.23 | K3: IV.23 | L3: I.24 | M3: II.24 | N3: III.24 | O3: IV.24 | P3: I.25 | Q3: II.25 | R3: III.25 | S3: IV.25 | T3: I.26 | U3: ІI.26 | W3: Consolidated budget expenditures, UAH billions (economic classification)
E4: ІI.22 | G4: ІV.22 | I4: II.23 | K4: IV.23 | M4: II.24 | O4: IV.24 | Q4: II.25
A5: =IF(Content!$E$1=1,B5,C5) -> Видатки | B5: Видатки | C5: Expenditures | D5: 447.34 | E5: 710.38 | F5: 786.72 | G5: 1099.43 | H5: 809.5 | I5: 1128.07 | J5: 1125.66 | K5: 1378.13 | L5: 916.39 | M5: 1179.69 | N5: 1140.38 | O5: 1709.22 | P5: 1251.82 | Q5: 1365.22 | R5: 1332.92 | S5: 2056.43 | T5: 1252.32 | U5: 1811.82 | AE5: 1.5
A6: =IF(Content!$E$1=1,B6,C6) -> Оплата праці з нарахуваннями | B6: Оплата праці з нарахуваннями | C6: Wages | D6: 149.44 | E6: 314.11 | F6: 355.59 | G6: 420.8 | H6: 332.12 | I6: 368.78 | J6: 362.94 | K6: 415.32 | L6: 347.96 | M6: 400.88 | N6: 387.16 | O6: 447.64 | P6: 421.89 | Q6: 481.84 | R6: 462.13 | S6: 514.47 | T6: 501.11 | U6: 566.39 | AD6: -50 | AE6: 1.5
A7: =IF(Content!$E$1=1,B7,C7) -> Використання товарів і послуг | B7: Використання товарів і послуг | C7: Goods and services | D7: 117.13 | E7: 173.95 | F7: 232.15 | G7: 322.22 | H7: 265.84 | I7: 441.51 | J7: 461.27 | K7: 496.02 | L7: 249.75 | M7: 371.34 | N7: 324.37 | O7: 539.92 | P7: 389.71 | Q7: 366.1 | R7: 385.41 | S7: 643.56 | T7: 319.13 | U7: 494.2 | AD7: 0 | AE7: 5.5
A8: =IF(Content!$E$1=1,B8,C8) -> Поточні трансферти | B8: Поточні трансферти | C8: Current transfers | D8: 24.87 | E8: 25.34 | F8: 22.27 | G8: 58.76 | H8: 23.24 | I8: 34.06 | J8: 33.39 | K8: 68.12 | L8: 92.27 | M8: 93.05 | N8: 101.56 | O8: 243.29 | P8: 152.14 | Q8: 146.76 | R8: 145.14 | S8: 363.46 | T8: 146.82 | U8: 335.65 | AE8: 5.5
A9: =IF(Content!$E$1=1,B9,C9) -> Соціальне забезпечення | B9: Соціальне забезпечення | C9: Social benefits | D9: 107.39 | E9: 125.89 | F9: 129.02 | G9: 158.1 | H9: 139.29 | I9: 136.76 | J9: 126.51 | K9: 148.53 | L9: 142.14 | M9: 149.31 | N9: 136.23 | O9: 173.71 | P9: 164.87 | Q9: 161.91 | R9: 169.2 | S9: 193.64 | T9: 175.99 | U9: 191.7 | AE9: 9.5
A10: =IF(Content!$E$1=1,B10,C10) -> Обслуговування боргу | B10: Обслуговування боргу | C10: Debt service | D10: 40.21 | E10: 49.49 | F10: 20.65 | G10: 51.77 | H10: 25.47 | I10: 94.57 | J10: 56.92 | K10: 76.98 | L10: 44.97 | M10: 90.4 | N10: 78.41 | O10: 91.24 | P10: 59.31 | Q10: 121.96 | R10: 67.15 | S10: 108.32 | T10: 65.32 | U10: 120.32 | AE10: 9.5
A11: =IF(Content!$E$1=1,B11,C11) -> Інші поточні видатки | B11: Інші поточні видатки | C11: Others current expenditures | D11: 2.61 | E11: 7.37 | F11: 1.49 | G11: 3.05 | H11: 1.54 | I11: 4.09 | J11: 5.43 | K11: 10.4 | L11: 3.18 | M11: 5.26 | N11: 14.83 | O11: 5.99 | P11: 3.78 | Q11: 5.63 | R11: 3.77 | S11: 16.03 | T11: 4.07 | U11: 4.72
A12: =IF(Content!$E$1=1,B12,C12) -> Капітальні видатки | B12: Капітальні видатки | C12: Capital expenditures | D12: 5.68 | E12: 14.23 | F12: 25.56 | G12: 84.74 | H12: 22.01 | I12: 48.3 | J12: 79.21 | K12: 162.76 | L12: 36.14 | M12: 69.46 | N12: 97.82 | O12: 207.42 | P12: 60.11 | Q12: 81.02 | R12: 100.1 | S12: 216.94 | T12: 39.89 | U12: 98.84
D14: I.22 | F14: ІІI.22 | H14: I.23 | J14: III.23 | L14: I.24 | N14: III.24 | P14: I.25 | R14: III.25 | U14: ІI.26
W18: =IF(Content!$E$1=1,W30,W31) -> Джерело: ДКСУ, розрахунки НБУ.
W30: Джерело: ДКСУ, розрахунки НБУ.
W31: Source: STSU, NBU staff estimates.

Sheet 2.9
A1: << | B1: =IF(Content!$E$1=1,B2,B3) -> Середня зарплата | C1: =IF(Content!$E$1=1,C2,C3) -> Освіта | D1: =IF(Content!$E$1=1,D2,D3) -> Виробництво транспортних засобів | G1: =IF(Content!$E$1=1,G2,G3) -> Реальна річна зміна зарплат окремих ВЕД, % р/р*
B2: Середня зарплата | C2: Освіта | D2: Виробництво транспортних засобів | G2: Реальна річна зміна зарплат окремих ВЕД, % р/р*
B3: Average wage | C3: Education | D3: Manufacturing of vehicles | G3: Real annual change in wages for selected economic activities, % yoy*
A4: 45292 | B4: 18.7 | C4: 10.2 | D4: 23.3
A5: 45323 | B5: 17.6 | C5: 10 | D5: 21.8
A6: 45352 | B6: 17.4 | C6: 10.6 | D6: 18.1
A7: 45383
A8: 45413 | O8: 4.5
A9: 45444 | N9: -50 | O9: 4.5
A10: 45474 | N10: 30 | O10: 8.5
A11: 45505 | O11: 8.5
A12: 45536 | O12: 12.5
A13: 45566 | O13: 12.5
A14: 45597
A15: 45627
A16: 45658 | B16: 11.2 | C16: 0.1 | D16: 25.9
A17: 45689 | B17: 8.7 | C17: -0.4 | D17: 23.1
A18: 45717 | B18: 9.5 | C18: -1.2 | D18: 22.4 | G18: =IF(Content!$E$1=1,G22,G23) -> * Пунктиром позначено місяці, для яких відсутні дані ДССУ.
A19: 45748 | B19: 5.5 | C19: -3.6 | D19: 18.1 | G19: =IF(Content!$E$1=1,G20,G21) -> Джерело: ДССУ, розрахунки НБУ
A20: 45778 | B20: 4.9 | C20: -5.2 | D20: 19 | G20: Джерело: ДССУ, розрахунки НБУ
A21: 45809 | B21: 6.2 | C21: -5.2 | D21: 19.2 | G21: Source: SSSU, NBU staff calculations.
A22: 45839 | B22: 6.4 | C22: -0.4 | D22: 17.9 | G22: * Пунктиром позначено місяці, для яких відсутні дані ДССУ.
A23: 45870 | B23: 6.9 | C23: -1.4 | D23: 13.5 | G23: * The dotted lines indicate months for which there is no data from the SSSU.
A24: 45901 | B24: 4.7 | C24: -3.2 | D24: 20.1
A25: 45931 | B25: 7.4 | C25: 3 | D25: 17.9
A26: 45962 | B26: 8.1 | C26: -0.9 | D26: 15.7
A27: 45992 | B27: 5.3 | C27: -3.5 | D27: 24.5
A28: 46023 | B28: 13.3 | C28: 20.8 | D28: 29
A29: 46054 | B29: 13.8 | C29: 21.8 | D29: 29.5
A30: 46082 | B30: 13.6 | C30: 21.8 | D30: 31
A31: 46142 | B31: 11.7 | C31: 23.3 | D31: 30.9
A32: 46173 | B32: 13.3 | C32: 25 | D32: 36.3
A33: 46203 | B33: 17 | C33: 25.5 | D33: 39

Sheet 2.10
A1: << | B1: =IF(Content!$E$1=1,B2,B3) -> Індекс обороту роздрібної торгівлі | C1: =IF(Content!$E$1=1,C2,C3) -> Індекс обороту оптової торгівлі | F1: =IF(Content!$E$1=1,F2,F3) -> Індекси обороту роздрібної та оптової торгівлі*, % р/р
B2: Індекс обороту роздрібної торгівлі | C2: Індекс обороту оптової торгівлі | F2: Індекси обороту роздрібної та оптової торгівлі*, % р/р
B3: Retail turnover index | C3: Wholesale turnover index | F3: Retail and wholesale trade turnover indices*, % yoy
A4: І.24 | B4: 18.6 | C4: -1
A5: ІІ.24 | B5: 14.3 | C5: -1.6
A6: ІІІ.24 | B6: 11.4 | C6: -5.3
A7: ІV.24 | B7: 4.7 | C7: -5.5
A8: І.25 | B8: 5.9 | C8: 5.4
A9: ІІ.25 | B9: 7.5 | C9: 0.3
A10: ІІІ.25 | B10: 5.1 | C10: 0.7
A11: ІV.25 | B11: 11 | C11: 5.3
A12: І.26 | B12: 11.2 | C12: 0.5
A13: ІІ.26 | B13: 9 | C13: 1.4
F16: =IF(Content!$E$1=1,F18,F20) -> * Квартальні значення індексу розраховані як середні значення за три місяці кварталу.
F17: =IF(Content!$E$1=1,F19,F21) -> Джерело: ДССУ.
F18: * Квартальні значення індексу розраховані як середні значення за три місяці кварталу.
F19: Джерело: ДССУ.
F20: * Quarterly index values ​​are calculated as average values ​​for the three months of the quarter.
F21: Source: SSSU.
C40: І.24 | E40: ІІІ.24 | F40: ІV.24 | G40: І.25 | H40: ІІ.25 | I40: ІІІ.25 | J40: ІV.25 | K40: І.26 | L40: ІІ.26
C41: 18.6 | E41: 11.4 | F41: 4.7 | G41: 5.9 | H41: 7.5 | I41: 5.1 | J41: 11 | K41: 11.2 | L41: 9
C42: -0.98403222 | E42: -5.3062258 | F42: -5.4936708 | G42: 5.3716851 | H42: 0.33903795 | I42: 0.72158754 | J42: 5.2681997 | K42: 0.46794129 | L42: 1.4
E45: І.24 | F45: 18.6 | G45: -0.98403222
E46: ІІ.24 | F46: 14.3 | G46: -1.6113798
E47: ІІІ.24 | F47: 11.4 | G47: -5.3062258
E48: ІV.24 | F48: 4.7 | G48: -5.4936708
E49: І.25 | F49: 5.9 | G49: 5.3716851
E50: ІІ.25 | F50: 7.5 | G50: 0.33903795
E51: ІІІ.25 | F51: 5.1 | G51: 0.72158754
E52: ІV.25 | F52: 11 | G52: 5.2681997
E53: І.26 | F53: 11.2 | G53: 0.46794129
E54: ІІ.26 | F54: 9 | G54: 1.4

Sheet 2.11
A1: << | B1: =IF(Content!$E$1=1,B2,B3) -> Поточний прогноз | C1: =IF(Content!$E$1=1,C2,C3) -> Попередній прогноз | F1: =IF(Content!$E$1=1,F2,F3) -> Дефіцит зведеного бюджету без грантів у доходах, % ВВП
B2: Поточний прогноз | C2: Попередній прогноз | F2: Дефіцит зведеного бюджету без грантів у доходах, % ВВП
B3: Current forecast | C3: Previous forecast | F3: Consolidated budget deficit excluding grants, % of GDP
A4: 2023 | B4: 26.6
A5: 2024 | B5: 23.8
A6: 2025 | B6: 24.7
A7: 2026 | B7: 35.2 | C7: 19.2
A8: 2027 | B8: 25.6 | C8: 17.7
A9: 2028 | B9: 14.6 | C9: 10.9
F17: =IF(Content!$E$1=1,F21,F22) -> Сірі стовпці – попередній прогноз.
F18: =IF(Content!$E$1=1,F19,F20) -> Джерело: ДКСУ, ДССУ, розрахунки НБУ.
F19: Джерело: ДКСУ, ДССУ, розрахунки НБУ.
F20: Source: STSU, SSSU, NBU staff estimates.
F21: Сірі стовпці – попередній прогноз.
F22: Gray bars are previous forecast.

Sheet 2.12
A1: << | B1: =IF(Content!$E$1=1,B2,B3) -> Реальна зарплата, рівень (логарифми) | C1: =IF(Content!$E$1=1,C2,C3) -> Тренд | E1: =IF(Content!$E$1=1,E2,E3) -> Реальна зарплата, рівень (логарифми)
B2: Реальна зарплата, рівень (логарифми) | C2: Тренд | E2: Реальна зарплата, рівень (логарифми)
B3: Real wages, level (logs) | C3: Trend | E3: Real wages, level (logs)
A4: I.20 | B4: 670.7 | C4: 670.4
A5: II.20 | B5: 667.1 | C5: 672.4
A6: III.20 | B6: 674 | C6: 674.4
A7: IV.20 | B7: 676.8 | C7: 676.3
A8: I.21 | B8: 678.9 | C8: 677.9
A9: II.21 | B9: 682.6 | C9: 679.4
A10: III.21 | B10: 683 | C10: 680.6
A11: IV.21 | B11: 684.1 | C11: 681.8
A12: I.22 | B12: 681.4 | C12: 682.9
A13: II.22 | B13: 665.1 | C13: 669
A14: III.22 | B14: 664.9 | C14: 670.3
A15: IV.22 | B15: 668.2 | C15: 671.6
A16: I.23 | B16: 665.5 | C16: 673.1 | E16: =IF(Content!$E$1=1,E17,E18) -> Джерело: ДССУ, розрахунки НБУ.
A17: II.23 | B17: 673.1 | C17: 674.8 | E17: Джерело: ДССУ, розрахунки НБУ.
A18: III.23 | B18: 676.8 | C18: 676.8 | E18: Source: SSSU, NBU staff estimates.
A19: IV.23 | B19: 678.6 | C19: 678.9
A20: I.24 | B20: 682.2 | C20: 681.3
A21: II.24 | B21: 689 | C21: 683.8
A22: III.24 | B22: 690 | C22: 686.2
A23: IV.24 | B23: 690.8 | C23: 688.7
A24: I.25 | B24: 692 | C24: 691
A25: II.25 | B25: 694.3 | C25: 693.4
A26: III.25 | B26: 695.9 | C26: 695.7 | N26: x | O26: x | P26: x
A27: IV.25 | B27: 698.3 | C27: 698
A28: I.26 | B28: 704.9 | C28: 700.4
A29: II.26 | B29: 705.9 | C29: 702.5
A30: III.26 | B30: 708.1 | C30: 704.5
A31: IV.26 | B31: 709.7 | C31: 706.4
A32: I.27 | B32: 711.8 | C32: 708.2
A33: II.27 | B33: 712.7 | C33: 709.8
A34: III.27 | B34: 713.2 | C34: 711.4
A35: IV.27 | B35: 713.9 | C35: 713
A36: I.28 | B36: 715.2 | C36: 714.5
A37: II.28 | B37: 716.5 | C37: 716
A38: III.28 | B38: 717.8 | C38: 717.5
A39: IV.28 | B39: 719.1 | C39: 719

Sheet 2.13
A1: << | B1: =IF(Content!$E$1=1,B2,B3) -> Зернові культури | C1: =IF(Content!$E$1=1,C2,C3) -> Олія | D1: =IF(Content!$E$1=1,D2,D3) -> Руди | E1: =IF(Content!$E$1=1,E2,E3) -> Чорні метали (4 групи) | H1: =IF(Content!$E$1=1,H2,H3) -> Внески в річну зміну фізичних обсягів експорту окремих товарів, в. п.
B2: Зернові культури | C2: Олія | D2: Руди | E2: Чорні метали (4 групи) | H2: Внески в річну зміну фізичних обсягів експорту окремих товарів, в. п.
B3: Grains | C3: Sunflower oil | D3: Ores | E3: Ferrous metals (4 groups) | H3: Contributions of selected commodities to the annual change in exports volumes, pp
A4: I.24 | B4: 5.5 | C4: 2.4 | D4: 26.2 | E4: 2.1 | F4: I.24
A5: II.24 | B5: 24.4 | C5: 1.7 | D5: 26.3 | E5: 0.5
A6: III.24 | B6: 26.4 | C6: -2 | D6: 21.3 | E6: 3.1 | F6: III.24
A7: IV.24 | B7: -0.7 | C7: -1.4 | D7: 18.2 | E7: 1.2
A8: I.25 | B8: -20.4 | C8: -2.4 | D8: -1.8 | E8: 0 | F8: I.25
A9: II.25 | B9: -28.6 | C9: -1.9 | D9: -6.4 | E9: 0.4
A10: III.25 | B10: -18.5 | C10: -1.3 | D10: 4.5 | E10: -0.2 | F10: III.25
A11: IV.25 | B11: -12.7 | C11: -0.7 | D11: -8.1 | E11: 1.9
A12: I.26 | B12: -0.2 | C12: 0.2 | D12: -13.9 | E12: -0.1 | F12: I.26
A13: II.26 | B13: 19.5 | C13: -1 | D13: -6.9 | E13: 0.9
A14: III.26 | B14: -6.1 | C14: 0.3 | D14: -19.1 | E14: -0.8 | F14: III.26
A15: IV.26 | B15: -1.5 | C15: 1.5 | D15: -4.7 | E15: -2.3
A16: I.27 | B16: 8.9 | C16: 0.7 | D16: 13.5 | E16: -0.5 | F16: I.27
A17: II.27 | B17: 20.8 | C17: 1.3 | D17: 10.1 | E17: -1 | H17: =IF(Content!$E$1=1,H18,H19) -> Джерело: ДМСУ, розрахунки НБУ.
A18: III.27 | B18: 58.8 | C18: 1.1 | D18: 29.5 | E18: -0.8 | F18: III.27 | H18: Джерело: ДМСУ, розрахунки НБУ.
A19: IV.27 | B19: 21.8 | C19: 0.8 | D19: 16 | E19: -0.1 | H19: Source: SCSU, NBU staff estimates.
A20: I.28 | B20: 2.7 | C20: 0.1 | D20: 4.4 | E20: 0.1 | F20: I.28
A21: II.28 | B21: -21.2 | C21: -0.2 | D21: 3.4 | E21: 0.1
A22: III.28 | B22: -15 | C22: -0.4 | D22: 3.8 | E22: 0.1
A23: IV.28 | B23: -3.4 | C23: -0.4 | D23: 3.3 | E23: 0 | F23: IV.28

Sheet 2.14
A1: << | B1: =IF(Content!$E$1=1,B2,B3) -> Продовольчі товари | C1: =IF(Content!$E$1=1,C2,C3) -> Енергоносії | D1: =IF(Content!$E$1=1,D2,D3) -> Хімія | E1: =IF(Content!$E$1=1,E2,E3) -> Промислові вироби | F1: =IF(Content!$E$1=1,F2,F3) -> Металургія | G1: =IF(Content!$E$1=1,G2,G3) -> Машинобудування | H1: =IF(Content!$E$1=1,H2,H3) -> Інші | K1: =IF(Content!$E$1=1,K2,K3) -> Внески в річну зміну імпорту товарів, в. п.
B2: Продовольчі товари | C2: Енергоносії | D2: Хімія | E2: Промислові вироби | F2: Металургія | G2: Машинобудування | H2: Інші | K2: Внески в річну зміну імпорту товарів, в. п.
B3: Foods | C3: Energy | D3: Chemicals | E3: Industrials | F3: Metallurgy | G3: Machinery | H3: Others | K3: Contributions to the annual change in imports, pp
A4: I.24 | B4: 1 | C4: -10.9 | D4: 1.3 | E4: 0.1 | F4: 1.2 | G4: 6 | H4: 1.8 | I4: I.24
A5: II.24 | B5: 0.8 | C5: 1.1 | D5: 1.7 | E5: 0.2 | F5: 1.6 | G5: 10.9 | H5: 0.8
A6: III.24 | B6: 0.7 | C6: 2.4 | D6: -0.1 | E6: -0.2 | F6: 0.4 | G6: 5.7 | H6: 1.3 | I6: III.24
A7: IV.24 | B7: 1.7 | C7: -1.5 | D7: 1.8 | E7: 0.2 | F7: 0.1 | G7: 8.1 | H7: 4.2
A8: I.25 | B8: 0.8 | C8: 3.3 | D8: 1.4 | E8: 0.2 | F8: 0.4 | G8: 9 | H8: 5.1 | I8: I.25
A9: II.25 | B9: 1.6 | C9: 2.6 | D9: 1 | E9: 0 | F9: 0.6 | G9: 11.5 | H9: 2.8
A10: III.25 | B10: 2.1 | C10: -0.1 | D10: 1.8 | E10: 0.4 | F10: 1.4 | G10: 14.9 | H10: 4 | I10: III.25
A11: IV.25 | B11: 1.3 | C11: 3.8 | D11: 0.9 | E11: 0.3 | F11: 0.9 | G11: 14.2 | H11: 8.2
A12: I.26 | B12: 1.1 | C12: 8.1 | D12: 0.6 | E12: 0.6 | F12: 0.3 | G12: 12.9 | H12: 4.8 | I12: I.26
A13: II.26 | B13: 0.5 | C13: 3 | D13: 1.5 | E13: 1 | F13: 0.7 | G13: 15.9 | H13: 0.7
A14: III.26 | B14: 1.5 | C14: 2.8 | D14: 2 | E14: 0.3 | F14: 2.1 | G14: 38.5 | H14: -0.8 | I14: III.26
A15: IV.26 | B15: 1.7 | C15: 1.7 | D15: 3.2 | E15: 0.3 | F15: 3.1 | G15: 32.2 | H15: -4.4
A16: I.27 | B16: 0.8 | C16: -1.1 | D16: 2.5 | E16: -0.1 | F16: 2.4 | G16: 16.2 | H16: -5.4 | I16: I.27
A17: II.27 | B17: 1.1 | C17: -1 | D17: 1.3 | E17: -0.2 | F17: 1.1 | G17: 3 | H17: -2.4
A18: III.27 | B18: 0.5 | C18: -1.1 | D18: 0.5 | E18: -0.1 | F18: -0.3 | G18: -15.4 | H18: -2.1 | I18: III.27
A19: IV.27 | B19: 0.1 | C19: -1.5 | D19: -0.4 | E19: 0.3 | F19: -1.2 | G19: -15.4 | H19: -1.7 | K19: =IF(Content!$E$1=1,K20,K21) -> Джерело: ДМСУ, розрахунки НБУ.
A20: I.28 | B20: 0.6 | C20: -4.6 | D20: 1 | E20: 0.4 | F20: -0.2 | G20: -10.7 | H20: -0.4 | I20: I.28 | K20: Джерело: ДМСУ, розрахунки НБУ.
A21: II.28 | B21: 0.7 | C21: -2.2 | D21: 1.2 | E21: 0.2 | F21: 0.3 | G21: -8.2 | H21: -0.4 | K21: Source: SCSU, NBU staff estimates.
A22: III.28 | B22: 1.1 | C22: -0.6 | D22: 1.4 | E22: 0.3 | F22: 0.2 | G22: -8.1 | H22: -0.5
A23: IV.28 | B23: 1.3 | C23: -0.7 | D23: 1.1 | E23: 0.4 | F23: 0.4 | G23: -8.9 | H23: -0.8 | I23: IV.28

Sheet 2.15
A1: << | B1: =IF(Content!$E$1=1,B2,B3) -> Базовий сценарій | C1: =IF(Content!$E$1=1,C2,C3) -> Попередній прогноз | F1: =IF(Content!$E$1=1,F2,F3) -> Дефіцит е/е, %
B2: Базовий сценарій | C2: Попередній прогноз | F2: Дефіцит е/е, %
B3: Baseline scenario | C3: Previous forecast | F3: Electricity deficit, %
A4: I.23 | B4: 5.4 | C4: 5.4 | D4: I.23
A5: II.23 | B5: 0 | C5: 0
A6: III.23 | B6: 1.6 | C6: 1.6 | D6: ІII.23
A7: IV.23 | B7: 3 | C7: 3 | L7: =IF(Content!$E$1=1,L8,L9) -> Попередня оцінка 5
A8: I.24 | B8: 2.1 | C8: 2.1 | D8: I.24 | L8: Попередня оцінка 5
A9: II.24 | B9: 5.2 | C9: 5.2 | L9: Previous estimate 5
A10: III.24 | B10: 6 | C10: 6 | D10: III.24
A11: IV.24 | B11: 3.1 | C11: 3.1
A12: I.25 | B12: 1 | C12: 1 | D12: I.25
A13: II.25 | B13: 0 | C13: 0
A14: III.25 | B14: 1 | C14: 1 | D14: III.25
A15: IV.25 | B15: 6.8 | C15: 6.8
A16: I.26 | B16: 10.868639 | C16: 10.9 | D16: I.26 | F16: =IF(Content!$E$1=1,F23,F24) -> Пунктирна лінія – попередній прогноз.
A17: II.26 | B17: 0.85807123 | C17: 5 | F17: =IF(Content!$E$1=1,F18,F19) -> Джерело: оцінки НБУ.
A18: III.26 | B18: 2.9756252 | C18: 3 | D18: III.26 | F18: Джерело: оцінки НБУ.
A19: IV.26 | B19: 7.0175439 | C19: 7 | F19: Source: NBU staff estimates.
A20: I.27 | B20: 8.1220657 | C20: 6 | D20: I.27
A21: II.27 | B21: 0.99009901 | C21: 0.8
A22: III.27 | B22: -3.3313704e-15 | C22: 0 | D22: III.27
A23: IV.27 | B23: 1.9674185 | C23: 2 | F23: Пунктирна лінія – попередній прогноз.
A24: I.28 | B24: 1.0359945 | C24: 1 | D24: I.28 | F24: Dotted line – previous forecast.
A25: II.28 | B25: 8.4655738e-15 | C25: 0
A26: III.28 | B26: 3.15782e-15 | C26: 0
A27: IV.28 | B27: -5.4656271e-15 | C27: 0 | D27: IV.28

Sheet 2.16
A1: << | C1: =IF(Content!$E$1=1,C2,C3) -> Олійні (п. ш.) | E1: =IF(Content!$E$1=1,E2,E3) -> Зернові | G1: =IF(Content!$E$1=1,G2,G3) -> Урожай зернових та олійних, млн т
C2: Олійні (п. ш.) | E2: Зернові | G2: Урожай зернових та олійних, млн т
C3: Oilseeds (RHS) | E3: Grains | G3: Harvest of grains and oilseeds, million tons
A4: 2023 | B4: 21.7 | C4: 21.7 | D4: 59.8 | E4: 59.8
A5: 24 | B5: 21.3 | C5: 21.3 | D5: 56.2 | E5: 56.2
A6: 25 | B6: 18.6 | C6: 18.5 | D6: 63.5 | E6: 61
A7: 26 | B7: 20.2 | C7: 20.7 | D7: 62.9 | E7: 62.2
A8: 27 | B8: 21.4 | C8: 21 | D8: 63.5 | E8: 63.1
A9: 2028 | B9: 22 | C9: 21.6 | D9: 65 | E9: 64.2
G17: =IF(Content!$E$1=1,G18,G19) -> Джерело: ДССУ, оцінки НБУ.
G18: Джерело: ДССУ, оцінки НБУ.
G19: Source: SSSU, NBU staff estimates.
A37: 2021 | C37: 86.01 | E37: 22.82455
A38: 2022 | C38: 53.86371 | E38: 18.09052
A39: 2023 | B39: 59.77222 | C39: 59.77222 | D39: 21.68589 | E39: 21.68589
A40: 2024 | B40: 56.246 | C40: 56.246 | D40: 21.28481 | E40: 21.28481
A41: 2025 | B41: 63.45034 | C41: 61.04469 | D41: 18.590302 | E41: 18.50933
A42: 2026 | B42: 62.9175 | C42: 62.187846 | D42: 20.21739 | E42: 20.659848
A43: 2027 | B43: 63.5395 | C43: 63.0955 | D43: 21.40029 | E43: 20.96489
A44: 2028 | B44: 65.0444 | C44: 64.2445 | D44: 22.02639 | E44: 21.63739
C46: =ROUND(C37,1) -> 86 | E46: =ROUND(E37,1) -> 22.8
C47: =ROUND(C38,1) -> 53.9 | E47: =ROUND(E38,1) -> 18.1
B48: =ROUND(B39,1) -> 59.8 | C48: =ROUND(C39,1) -> 59.8 | D48: =ROUND(D39,1) -> 21.7 | E48: =ROUND(E39,1) -> 21.7
B49: =ROUND(B40,1) -> 56.2 | C49: =ROUND(C40,1) -> 56.2 | D49: =ROUND(D40,1) -> 21.3 | E49: =ROUND(E40,1) -> 21.3
B50: =ROUND(B41,1) -> 63.5 | C50: =ROUND(C41,1) -> 61 | D50: =ROUND(D41,1) -> 18.6 | E50: =ROUND(E41,1) -> 18.5
B51: =ROUND(B42,1) -> 62.9 | C51: =ROUND(C42,1) -> 62.2 | D51: =ROUND(D42,1) -> 20.2 | E51: =ROUND(E42,1) -> 20.7
B52: =ROUND(B43,1) -> 63.5 | C52: =ROUND(C43,1) -> 63.1 | D52: =ROUND(D43,1) -> 21.4 | E52: =ROUND(E43,1) -> 21
B53: =ROUND(B44,1) -> 65 | C53: =ROUND(C44,1) -> 64.2 | D53: =ROUND(D44,1) -> 22 | E53: =ROUND(E44,1) -> 21.6

Sheet 2.17
A1: << | B1: =IF(Content!$E$1=1,B2,B3) -> Поточний прогноз | C1: =IF(Content!$E$1=1,C2,C3) -> Попередній прогноз | F1: =IF(Content!$E$1=1,F2,F3) -> Реальний ВВП, % р/р
B2: Поточний прогноз | C2: Попередній прогноз | F2: Реальний ВВП, % р/р
B3: Current forecast | C3: Previous forecast | F3: Real GDP, % yoy
A4: 2024 | B4: 3.2
A5: 2025 | B5: 1.8 | C5: 1.8
A6: 2026 | B6: 1.8 | C6: 1.3
A7: 2027 | B7: 2.8 | C7: 2.8
A8: 2028 | B8: 3 | C8: 3.7
F17: =IF(Content!$E$1=1,F22,F23) -> Сірі стовпці – попередній прогноз.
F19: =IF(Content!$E$1=1,F20,F21) -> Джерело: ДССУ, розрахунки НБУ.
F20: Джерело: ДССУ, розрахунки НБУ.
F21: Source: SSSU, NBU staff estimates.
F22: Сірі стовпці – попередній прогноз.
F23: Gray bars are the previous forecast.

Sheet 2.18
A1: << | B1: =IF(Content!$E$1=1,B2,B3) -> Розрив ВВП, % потенційного ВВП | C1: =IF(Content!$E$1=1,C2,C3) -> Розрив ВВП, % потенційного ВВП (попередній прогноз) | F1: =IF(Content!$E$1=1,F2,F3) -> Розрив ВВП, % потенційного ВВП
B2: Розрив ВВП, % потенційного ВВП | C2: Розрив ВВП, % потенційного ВВП (попередній прогноз) | F2: Розрив ВВП, % потенційного ВВП
B3: GDP gap, % of potential GDP | C3: GDP gap, % of potential GDP (previous forecast) | F3: Output gap, % of potential GDP
A4: 20 | B4: -2.8 | C4: -2.8
A5: 21 | B5: 1 | C5: 1.1
A6: 22 | B6: -6.3 | C6: -7.1
A7: 23 | B7: 1.2 | C7: -0.1
A8: 24 | B8: 1.7 | C8: 1.2
A9: 25 | B9: 1.2 | C9: 0.9
A10: 26 | B10: 0.9 | C10: 0.1
A11: 27 | B11: 1.4 | C11: 0.1
A12: 28 | B12: 0.2 | C12: -0.1
F16: =IF(Content!$E$1=1,F17,F18) -> Джерело: ДССУ, розрахунки НБУ.
F17: Джерело: ДССУ, розрахунки НБУ.
F18: Source: SSSU, NBU staff estimates.

Sheet В.1.1
A1: << | B1: =IF(Content!$E$1=1,B2,B3) -> Середня ціна на пальне | C1: =IF(Content!$E$1=1,C2,C3) -> Імпорт нафти і нафтопродуктів | F1: =IF(Content!$E$1=1,F2,F3) -> Імпорт нафтопродуктів і ціни на пальне в Україні, індекс 01.2021 = 100
B2: Середня ціна на пальне | C2: Імпорт нафти і нафтопродуктів | F2: Імпорт нафтопродуктів і ціни на пальне в Україні, індекс 01.2021 = 100
B3: Average fuel price | C3: Imports of oil and petroleum products | F3: Imports of petroleum products and fuel prices in Ukraine, index 01.2021 = 100
A4: 01.21 | B4: 100 | C4: 100
A5: 02.21 | B5: 106.6 | C5: 80.3
A6: 03.21 | B6: 113.1 | C6: 96.2
A7: 04.21 | B7: 113.8 | C7: 104.7
A8: 05.21 | B8: 114.2 | C8: 86.6
A9: 06.21 | B9: 114.5 | C9: 91.2
A10: 07.21 | B10: 117.9 | C10: 113.2
A11: 08.21 | B11: 117.8 | C11: 117.4
A12: 09.21 | B12: 117.3 | C12: 114.9
A13: 10.21 | B13: 121.1 | C13: 118.2
A14: 11.21 | B14: 125 | C14: 170.9
A15: 12.21 | B15: 120.3 | C15: 157.9
A16: 01.22 | B16: 124.8 | C16: 122.8 | F16: =IF(Content!$E$1=1,F20,F21) -> Зафарбована область – період порушення паливної логістики з 24 лютого 2022 року та початку її перебудови на імпорт з ЄС.
A17: 02.22 | B17: 136.6 | C17: 99.8 | F17: =IF(Content!$E$1=1,F18,F19) -> Джерело: ДМС, Консалтингова група А-95, розрахунки НБУ. | N17: 250
A18: 03.22 | B18: 151.3 | C18: 49.7 | F18: Джерело: ДМС, Консалтингова група А-95, розрахунки НБУ. | N18: 250
A19: 04.22 | B19: 141.7 | C19: 71.9 | F19: Source: State Customs Service, A-95 Consulting Group, NBU staff estimates. | N19: 250
A20: 05.22 | B20: 177.4 | C20: 59.1 | F20: Зафарбована область – період порушення паливної логістики з 24 лютого 2022 року та початку її перебудови на імпорт з ЄС. | N20: 250
A21: 06.22 | B21: 211 | C21: 84.7 | F21: Shaded area – the period of disruption to fuel logistics since 24 February 2022 and the start of its restructuring towards imports from the EU. | N21: 250
A22: 07.22 | B22: 209.9 | C22: 93.1
A23: 08.22 | B23: 204.1 | C23: 83.4
A24: 09.22 | B24: 202.6 | C24: 87.6
A25: 10.22 | B25: 202.4 | C25: 73.2
A26: 11.22 | B26: 204.9 | C26: 87.8
A27: 12.22 | B27: 212.1 | C27: 108.5
A28: 01.23 | B28: 207.3 | C28: 105.3
A29: 02.23 | B29: 196.4 | C29: 89.3
A30: 03.23 | B30: 191.1 | C30: 87.2
A31: 04.23 | B31: 185.8 | C31: 69
A32: 05.23 | B32: 180.1 | C32: 76
A33: 06.23 | B33: 175.2 | C33: 84.8
... A65: 02.26 | B65: 243.5 | C65: 98.8

Sheet В.1.2
A1: << | B1: =IF(Content!$E$1=1,B2,B3) -> Дунайські порти | C1: =IF(Content!$E$1=1,C2,C3) -> Чорноморські порти | D1: =IF(Content!$E$1=1,D2,D3) -> Всього | G1: =IF(Content!$E$1=1,G2,G3) -> Експорт вантажів через українські порти, млн т
B2: Дунайські порти | C2: Чорноморські порти | D2: Всього | G2: Експорт вантажів через українські порти, млн т
B3: Danube ports | C3: Black Sea ports | D3: Total | G3: Freight exports through Ukrainian ports, million tons
A4: 01.22 | B4: 0.3 | C4: 7.3 | D4: 7.6
A5: 02.22 | B5: 0.2 | C5: 7 | D5: 7.2
A6: 03.22 | B6: 0.2 | C6: 0 | D6: 0.2 | N6: 10
A7: 04.22 | B7: 0.7 | C7: 0 | D7: 0.7 | N7: 10
A8: 05.22 | B8: 1.2 | C8: 0 | D8: 1.2 | N8: 10
A9: 06.22 | B9: 1.3 | C9: 0 | D9: 1.3 | N9: 10
A10: 07.22 | B10: 1.5 | C10: 0 | D10: 1.5 | N10: 10
A11: 08.22 | B11: 1.7 | C11: 1.4 | D11: 3.1
A12: 09.22 | B12: 1.4 | C12: 3.9 | D12: 5.4
A13: 10.22 | B13: 1.6 | C13: 4.1 | D13: 5.8
A14: 11.22 | B14: 1.8 | C14: 2.9 | D14: 4.7
A15: 12.22 | B15: 1.6 | C15: 3.7 | D15: 5.2
A16: 01.23 | B16: 1.3 | C16: 3.2 | D16: 4.5 | G16: =IF(Content!$E$1=1,G21,G22) -> Зафарбовані області – періоди повного блокування українських чорноморських портів росією у 2022-23 роках.
A17: 02.23 | B17: 1.8 | C17: 3.4 | D17: 5.2 | G17: =IF(Content!$E$1=1,G19,G20) -> Джерело: ДМС, розрахунки НБУ.
A18: 03.23 | B18: 2.3 | C18: 3.7 | D18: 6.1
A19: 04.23 | B19: 2 | C19: 2.6 | D19: 4.6 | G19: Джерело: ДМС, розрахунки НБУ.
A20: 05.23 | B20: 2.7 | C20: 1.4 | D20: 4.1 | G20: Source: State Customs Service, NBU staff estimates.
A21: 06.23 | B21: 2.3 | C21: 1.8 | D21: 4.1 | G21: Зафарбовані області – періоди повного блокування українських чорноморських портів росією у 2022-23 роках.
A22: 07.23 | B22: 2.6 | C22: 0.2 | D22: 2.7 | G22: Shaded areas – periods of russia's complete blockade of Ukrainian Black Sea ports in 2022-23. | N22: 10
A23: 08.23 | B23: 2.9 | C23: 0 | D23: 2.9 | N23: 10
A24: 09.23 | B24: 2.8 | C24: 0.2 | D24: 3 | N24: 10
A25: 10.23 | B25: 2.4 | C25: 2.2 | D25: 4.6
A26: 11.23 | B26: 1.9 | C26: 4.4 | D26: 6.2
A27: 12.23 | B27: 1.6 | C27: 6.8 | D27: 8.4
A28: 01.24 | B28: 1.5 | C28: 6.3 | D28: 7.8
A29: 02.24 | B29: 1.5 | C29: 7.7 | D29: 9.3
A30: 03.24 | B30: 1.4 | C30: 7.6 | D30: 9
A31: 04.24 | B31: 1.2 | C31: 7.7 | D31: 8.9
A32: 05.24 | B32: 1.1 | C32: 6.6 | D32: 7.7
A33: 06.24 | B33: 0.9 | C33: 5.5 | D33: 6.4
A34: 07.24 | B34: 0.8 | C34: 5.3 | D34: 6.1
A35: 08.24 | B35: 0.8 | C35: 5.2 | D35: 5.9
A36: 09.24 | B36: 0.7 | C36: 5.6 | D36: 6.3
... A57: 06.26 | B57: 0.15562 | C57: 4.85418 | D57: 5.0098

Sheet В.1.3
A1: << | B1: =IF(Content!$E$1=1,B2,B3) -> Атаки рф на об'єкти генерації та передачі е/е | C1: =IF(Content!$E$1=1,C2,C3) -> Виробництво, передача та розподілення е/е, % р/р | F1: =IF(Content!$E$1=1,F2,F3) -> Атаки рф на об'єкти енергетики та динаміка виробництва, передачі та розподілу е/е
B2: Атаки рф на об'єкти генерації та передачі е/е | C2: Виробництво, передача та розподілення е/е, % р/р | F2: Атаки рф на об'єкти енергетики та динаміка виробництва, передачі та розподілу е/е
B3: russian attacks on electricity generation and transmission facilities | C3: Electricity production, transmission and distribution, % yoy | F3: russian attacks on energy facilities and the dynamics of electricity production, transmission and distribution
A4: 02.22 | B4: 2 | C4: -12 | D4: 44593
A5: 03.22 | B5: 7 | C5: -36.4
A6: 04.22 | B6: 0 | C6: -32.8
A7: 05.22 | B7: 0 | C7: -32.8
A8: 06.22 | B8: 1 | C8: -35.1
A9: 07.22 | B9: 4 | C9: -37.9
A10: 08.22 | B10: 5 | C10: -35.5
A11: 09.22 | B11: 8 | C11: -30.4
A12: 10.22 | B12: 31 | C12: -36.2 | N12: 60 | R12: -60
A13: 11.22 | B13: 24 | C13: -39.4 | N13: 60 | R13: -60
A14: 12.22 | B14: 3 | C14: -44.3 | N14: 60 | R14: -60
A15: 01.23 | B15: 1 | C15: -40 | D15: 44927 | N15: 60 | R15: -60
A16: 02.23 | B16: 3 | C16: -22.8 | N16: 60 | R16: -60
A17: 03.23 | B17: 5 | C17: 2.7 | F17: =IF(Content!$E$1=1,F22,F23) -> Зафарбовані області – ключові кампанії російських масованих обстрілів української енергетики. | N17: 60 | R17: -60
A18: 04.23 | B18: 1 | C18: 2.1 | F18: =IF(Content!$E$1=1,F19,F20) -> Джерело: ACLED, ДССУ, розрахунки НБУ.
A19: 05.23 | B19: 1 | C19: 12.8 | F19: Джерело: ACLED, ДССУ, розрахунки НБУ.
A20: 06.23 | B20: 2 | C20: 10.5 | F20: Source: ACLED, SSSU, NBU staff estimates.
A21: 07.23 | B21: 0 | C21: 6.7
A22: 08.23 | B22: 0 | C22: 12.2 | F22: Зафарбовані області – ключові кампанії російських масованих обстрілів української енергетики.
A23: 09.23 | B23: 0 | C23: 0.2 | F23: Shaded areas – key campaigns of massive russian strikes on Ukrainian energy infrastructure.
A24: 10.23 | B24: 0 | C24: 0.7
A25: 11.23 | B25: 0 | C25: 15.8
A26: 12.23 | B26: 1 | C26: 29.4
A27: 01.24 | B27: 3 | C27: 24 | D27: 45292
A28: 02.24 | B28: 2 | C28: 3.8
A29: 03.24 | B29: 10 | C29: 7.9 | O29: 60 | S29: -60
A30: 04.24 | B30: 19 | C30: -3.5 | O30: 60 | S30: -60
A31: 05.24 | B31: 18 | C31: -6.4 | O31: 60 | S31: -60
A32: 06.24 | B32: 8 | C32: -11.2 | O32: 60 | S32: -60
A33: 07.24 | B33: 12 | C33: -10.8 | O33: 60 | S33: -60
A34: 08.24 | B34: 7 | C34: -12.2 | O34: 60 | S34: -60
A35: 09.24 | B35: 12 | C35: -8.6
A36: 10.24 | B36: 7 | C36: -4.6
A37: 11.24 | B37: 26 | C37: -3 | P37: 60 | T37: -60
A38: 12.24 | B38: 11 | C38: -8.6 | P38: 60 | T38: -60
A39: 01.25 | B39: 7 | C39: -11 | D39: 45658 | P39: 60 | T39: -60
A40: 02.25 | B40: 15 | C40: -0.6 | P40: 60 | T40: -60
A41: 03.25 | B41: 15 | C41: -8.7 | P41: 60 | T41: -60
A42: 04.25 | B42: 3 | C42: 6.6
A43: 05.25 | B43: 4 | C43: 0.7
A44: 06.25 | B44: 4 | C44: 11.1
A45: 07.25 | B45: 6 | C45: 12.8
A46: 08.25 | B46: 11 | C46: 6.8
A47: 09.25 | B47: 11 | C47: 8.8
A48: 10.25 | B48: 52 | C48: 3 | Q48: 60 | U48: -60
A49: 11.25 | B49: 42 | C49: -18 | Q49: 60 | U49: -60
A50: 12.25 | B50: 37 | C50: -18.3 | Q50: 60 | U50: -60
A51: 01.26 | B51: 38 | C51: -17.9 | D51: 46023 | Q51: 60 | U51: -60
A52: 02.26 | B52: 25 | C52: -25.1 | Q52: 60 | U52: -60
A53: 03.26 | B53: 28 | C53: -13.7 | Q53: 60 | U53: -60
A54: 04.26 | B54: 30 | C54: -11 | Q54: 60 | U54: -60
A55: 05.26 | B55: 13 | C55: -11.8 | Q55: 60 | U55: -60
A56: 06.26 | B56: 19 | C56: -10.4 | Q56: 60 | U56: -60

Sheet В.1.4
A1: << | B1: =IF(Content!$E$1=1,B2,B3) -> Атаки рф на об'єкти газовидобутку | C1: =IF(Content!$E$1=1,C2,C3) -> Добування газу та нафти, % р/р | F1: =IF(Content!$E$1=1,F2,F3) -> Атаки рф на об'єкти газовидобутку та динаміка виробництва газу й нафти
B2: Атаки рф на об'єкти газовидобутку | C2: Добування газу та нафти, % р/р | F2: Атаки рф на об'єкти газовидобутку та динаміка виробництва газу й нафти
B3: russian attacks on gas production facilities | C3: Gas and oil production, % yoy | F3: russian attacks on gas production facilities and the dynamics of gas and oil production
A4: 02.22 | B4: 1 | C4: -0.7 | D4: 44593
A5: 03.22 | B5: 13 | C5: -11.2 | N5: 40 | Q5: -30
A6: 04.22 | B6: 12 | C6: -10 | N6: 40 | Q6: -30
A7: 05.22 | B7: 4 | C7: -7.2 | N7: 40 | Q7: -30
A8: 06.22 | B8: 3 | C8: -8.3
A9: 07.22 | B9: 3 | C9: -8.9
A10: 08.22 | B10: 2 | C10: -10.7
A11: 09.22 | B11: 1 | C11: -10.9
A12: 10.22 | B12: 2 | C12: -11.1
A13: 11.22 | B13: 2 | C13: -9.7
A14: 12.22 | B14: 2 | C14: -11.2
A15: 01.23 | B15: 2 | C15: -10.4 | D15: 44927
A16: 02.23 | B16: 5 | C16: -7.8 | F16: =IF(Content!$E$1=1,F20,F21) -> Зафарбовані області – ключові кампанії російських обстрілів українського газовидобутку.
A17: 03.23 | B17: 1 | C17: 3.4 | F17: =IF(Content!$E$1=1,F18,F19) -> Джерело: ACLED, ДССУ, розрахунки НБУ.
A18: 04.23 | B18: 4 | C18: 2.5 | F18: Джерело: ACLED, ДССУ, розрахунки НБУ.
A19: 05.23 | B19: 2 | C19: -0.5 | F19: Source: ACLED, SSSU, NBU staff estimates.
A20: 06.23 | B20: 3 | C20: -2.3 | F20: Зафарбовані області – ключові кампанії російських обстрілів українського газовидобутку.
A21: 07.23 | B21: 0 | C21: 0.3 | F21: Shaded areas – key campaigns of russian strikes on Ukrainian gas production.
A22: 08.23 | B22: 1 | C22: 2.1
A23: 09.23 | B23: 2 | C23: 3.8
A24: 10.23 | B24: 6 | C24: 4.6
A25: 11.23 | B25: 3 | C25: 3.8
A26: 12.23 | B26: 1 | C26: 1.9
A27: 01.24 | B27: 4 | C27: 1.1 | D27: 45292
A28: 02.24 | B28: 3 | C28: 5.7
A29: 03.24 | B29: 1 | C29: 2.2
A30: 04.24 | B30: 2 | C30: 0
A31: 05.24 | B31: 1 | C31: -1.2
A32: 06.24 | B32: 1 | C32: 1.2
A33: 07.24 | B33: 3 | C33: -1.4
A34: 08.24 | B34: 2 | C34: 1
A35: 09.24 | B35: 2 | C35: -0.6
A36: 10.24 | B36: 10 | C36: 0.5
A37: 11.24 | B37: 4 | C37: 0.1
A38: 12.24 | B38: 9 | C38: 2.7 | O38: 40 | R38: -30
A39: 01.25 | B39: 6 | C39: 3 | D39: 45658 | O39: 40 | R39: -30
A40: 02.25 | B40: 9 | C40: -26.3 | O40: 40 | R40: -30
A41: 03.25 | B41: 12 | C41: -21.2 | O41: 40 | R41: -30
A42: 04.25 | B42: 13 | C42: -16.6 | O42: 40 | R42: -30
A43: 05.25 | B43: 24 | C43: -5.8
A44: 06.25 | B44: 19 | C44: -0.3
A45: 07.25 | B45: 20 | C45: 0.6
A46: 08.25 | B46: 22 | C46: -0.6
A47: 09.25 | B47: 18 | C47: 1.8
A48: 10.25 | B48: 30 | C48: -20.6 | P48: 40 | S48: -30
A49: 11.25 | B49: 27 | C49: -10.9 | P49: 40 | S49: -30
A50: 12.25 | B50: 23 | C50: -4.4 | P50: 40 | S50: -30
A51: 01.26 | B51: 35 | C51: -4.7 | D51: 46023 | P51: 40 | S51: -30
A52: 02.26 | B52: 20 | C52: 27.4 | P52: 40 | S52: -30
A53: 03.26 | B53: 10 | C53: 24.2 | P53: 40 | S53: -30
A54: 04.26 | B54: 10 | C54: 22.3
A55: 05.26 | B55: 10 | C55: 10.3
A56: 06.26 | B56: 12 | C56: 6.3

Sheet В.1.5
A1: << | B1: =IF(Content!$E$1=1,B2,B3) -> Логістика, порти, залізниця | C1: =IF(Content!$E$1=1,C2,C3) -> Енергетика (передача) | D1: =IF(Content!$E$1=1,D2,D3) -> Енергетика (генерація е/е і ТКЕ) | E1: =IF(Content!$E$1=1,E2,E3) -> Газовидобуток, шахти, нафтобази | F1: =IF(Content!$E$1=1,F2,F3) -> Бізнес | I1: =IF(Content!$E$1=1,I2,I3) -> Частка нових пошкоджень об'єктів виробництва, логістики та бізнесу внаслідок обстрілів рф, %
B2: Логістика, порти, залізниця | C2: Енергетика (передача) | D2: Енергетика (генерація е/е і ТКЕ) | E2: Газовидобуток, шахти, нафтобази | F2: Бізнес | I2: Частка нових пошкоджень об'єктів виробництва, логістики та бізнесу внаслідок обстрілів рф, %
B3: Logistics, ports, railway | C3: Energy (transmission) | D3: Energy (electricity generation and district heating) | E3: Gas production, mines, oil depots | F3: Business | I3: Share of new damage to production, logistics, and business facilities caused by russian strikes, %
A4: 44593 | B4: 0 | C4: 1 | D4: 2 | E4: 5 | F4: 1 | G4: 44593
A5: 44621 | B5: 16 | C5: 8 | D5: 7 | E5: 24 | F5: 11
A6: 44652 | B6: 7 | C6: 6 | D6: 0 | E6: 23 | F6: 5
A7: 44682 | B7: 6 | C7: 11 | D7: 0 | E7: 6 | F7: 4
A8: 44713 | B8: 8 | C8: 10 | D8: 1 | E8: 6 | F8: 4
A9: 44743 | B9: 5 | C9: 8 | D9: 4 | E9: 4 | F9: 7
A10: 44774 | B10: 9 | C10: 8 | D10: 5 | E10: 2 | F10: 4
A11: 44805 | B11: 4 | C11: 6 | D11: 7 | E11: 4 | F11: 1
A12: 44835 | B12: 1 | C12: 35 | D12: 10 | E12: 5 | F12: 4
A13: 44866 | B13: 0 | C13: 26 | D13: 8 | E13: 3 | F13: 4
A14: 44896 | B14: 0 | C14: 9 | D14: 0 | E14: 2 | F14: 7
A15: 44927 | B15: 0 | C15: 4 | D15: 0 | E15: 2 | F15: 2 | G15: 44927
A16: 44958 | B16: 3 | C16: 13 | D16: 1 | E16: 6 | F16: 1
A17: 44986 | B17: 1 | C17: 12 | D17: 1 | E17: 2 | F17: 5 | I17: =IF(Content!$E$1=1,I18,I19) -> Джерело: ACLED, розрахунки НБУ.
A18: 45017 | B18: 1 | C18: 7 | D18: 0 | E18: 4 | F18: 3 | I18: Джерело: ACLED, розрахунки НБУ.
A19: 45047 | B19: 5 | C19: 6 | D19: 0 | E19: 3 | F19: 5 | I19: Source: ACLED, NBU staff estimates.
A20: 45078 | B20: 2 | C20: 5 | D20: 1 | E20: 3 | F20: 4
A21: 45108 | B21: 2 | C21: 3 | D21: 0 | E21: 2 | F21: 3
A22: 45139 | B22: 4 | C22: 2 | D22: 0 | E22: 2 | F22: 2
A23: 45170 | B23: 1 | C23: 7 | D23: 0 | E23: 4 | F23: 5
A24: 45200 | B24: 10 | C24: 3 | D24: 0 | E24: 8 | F24: 2
A25: 45231 | B25: 0 | C25: 8 | D25: 0 | E25: 6 | F25: 1
A26: 45261 | B26: 0 | C26: 5 | D26: 0 | E26: 4 | F26: 1
A27: 45292 | B27: 1 | C27: 5 | D27: 1 | E27: 5 | F27: 3 | G27: 45292
A28: 45323 | B28: 2 | C28: 3 | D28: 2 | E28: 3 | F28: 2
A29: 45352 | B29: 4 | C29: 8 | D29: 6 | E29: 1 | F29: 2
A30: 45383 | B30: 6 | C30: 20 | D30: 7 | E30: 3 | F30: 5
A31: 45413 | B31: 1 | C31: 24 | D31: 3 | E31: 1 | F31: 5
A32: 45444 | B32: 0 | C32: 9 | D32: 3 | E32: 3 | F32: 1
A33: 45474 | B33: 3 | C33: 25 | D33: 0 | E33: 5 | F33: 8
A34: 45505 | B34: 3 | C34: 14 | D34: 1 | E34: 3 | F34: 4
A35: 45536 | B35: 2 | C35: 23 | D35: 3 | E35: 3 | F35: 5
A36: 45566 | B36: 9 | C36: 17 | D36: 1 | E36: 10 | F36: 12
A37: 45597 | B37: 5 | C37: 28 | D37: 5 | E37: 5 | F37: 12
A38: 45627 | B38: 0 | C38: 19 | D38: 7 | E38: 9 | F38: #N/A
A39: 45658 | B39: 5 | C39: 20 | D39: 2 | E39: 6 | F39: 9 | G39: 45658
A40: 45689 | B40: 6 | C40: 36 | D40: 6 | E40: 10 | F40: 7
A41: 45717 | B41: 12 | C41: 35 | D41: 0 | E41: 13 | F41: 10
A42: 45748 | B42: 7 | C42: 18 | D42: 0 | E42: 13 | F42: 8
A43: 45778 | B43: 11 | C43: 26 | D43: 3 | E43: 24 | F43: 25
A44: 45809 | B44: 15 | C44: 37 | D44: 1 | E44: 19 | F44: 21
A45: 45839 | B45: 14 | C45: 35 | D45: 4 | E45: 21 | F45: 26
A46: 45870 | B46: 11 | C46: 37 | D46: 2 | E46: 25 | F46: 19
A47: 45901 | B47: 9 | C47: 72 | D47: 5 | E47: 20 | F47: 32
A48: 45931 | B48: 24 | C48: 98 | D48: 14 | E48: 37 | F48: 29
A49: 45962 | B49: 19 | C49: 89 | D49: 9 | E49: 29 | F49: 35
A50: 45992 | B50: 18 | C50: 76 | D50: 6 | E50: 24 | F50: 40
A51: 46023 | B51: 24 | C51: 82 | D51: 14 | E51: 36 | F51: 13 | G51: 46023
A52: 46054 | B52: 26 | C52: 51 | D52: 9 | E52: 23 | F52: 23
A53: 46082 | B53: 28 | C53: 104 | D53: 4 | E53: 10 | F53: 26
A54: 46113 | B54: 39 | C54: 89 | D54: 4 | E54: 11 | F54: 53
A55: 46143 | B55: 29 | C55: 61 | D55: 3 | E55: 11 | F55: 51
A56: 46174 | B56: 45 | C56: 63 | D56: 7 | E56: 12 | F56: 76

Sheet В.1.6
A1: << | B1: =IF(Content!$E$1=1,B2,B3) -> Підприємство | C1: =IF(Content!$E$1=1,C2,C3) -> Промислове підприємство | D1: =IF(Content!$E$1=1,D2,D3) -> Зв'язок | E1: =IF(Content!$E$1=1,E2,E3) -> АЗС | F1: =IF(Content!$E$1=1,F2,F3) -> АПК | I1: =IF(Content!$E$1=1,I2,I3) -> Кількість нових пошкоджень об'єктів бізнесу внаслідок обстрілів рф
B2: Підприємство | C2: Промислове підприємство | D2: Зв'язок | E2: АЗС | F2: АПК | I2: Кількість нових пошкоджень об'єктів бізнесу внаслідок обстрілів рф
B3: Enterprise | C3: Industrial enterprise | D3: Communications | E3: Gas station | F3: Agriculture | I3: Number of business facilities newly damaged by russian strikes
A4: 44593 | B4: #N/A | C4: #N/A | D4: #N/A | E4: 1 | F4: #N/A | G4: 44593
A5: 44621 | B5: 1 | C5: 5 | D5: 2 | E5: 3 | F5: #N/A
A6: 44652 | B6: #N/A | C6: 3 | D6: #N/A | E6: #N/A | F6: 2
A7: 44682 | B7: #N/A | C7: 2 | D7: #N/A | E7: #N/A | F7: 2
A8: 44713 | B8: #N/A | C8: 3 | D8: #N/A | E8: #N/A | F8: 1
A9: 44743 | B9: #N/A | C9: #N/A | D9: #N/A | E9: 2 | F9: 5
A10: 44774 | B10: #N/A | C10: 1 | D10: #N/A | E10: #N/A | F10: 3
A11: 44805 | B11: #N/A | C11: 1 | D11: #N/A | E11: #N/A | F11: #N/A
A12: 44835 | B12: #N/A | C12: 2 | D12: #N/A | E12: #N/A | F12: 2
A13: 44866 | B13: #N/A | C13: #N/A | D13: #N/A | E13: 2 | F13: 2
A14: 44896 | B14: #N/A | C14: 4 | D14: #N/A | E14: 1 | F14: 2
A15: 44927 | B15: #N/A | C15: #N/A | D15: #N/A | E15: 1 | F15: 1 | G15: 44927
A16: 44958 | B16: #N/A | C16: 1 | D16: #N/A | E16: #N/A | F16: #N/A
A17: 44986 | B17: 2 | C17: 2 | D17: #N/A | E17: #N/A | F17: 1 | I17: =IF(Content!$E$1=1,I18,I19) -> Джерело: ACLED, розрахунки НБУ.
A18: 45017 | B18: 2 | C18: 1 | D18: #N/A | E18: #N/A | F18: #N/A | I18: Джерело: ACLED, розрахунки НБУ.
A19: 45047 | B19: #N/A | C19: 3 | D19: #N/A | E19: 1 | F19: 1 | I19: Source: ACLED, NBU staff estimates.
A20: 45078 | B20: 1 | C20: 1 | D20: #N/A | E20: 2 | F20: #N/A
A21: 45108 | B21: #N/A | C21: #N/A | D21: #N/A | E21: #N/A | F21: 3
A22: 45139 | B22: #N/A | C22: 1 | D22: #N/A | E22: #N/A | F22: 1
A23: 45170 | B23: 1 | C23: 2 | D23: #N/A | E23: #N/A | F23: 2
A24: 45200 | B24: #N/A | C24: #N/A | D24: #N/A | E24: #N/A | F24: 2
A25: 45231 | B25: #N/A | C25: #N/A | D25: #N/A | E25: #N/A | F25: 1
A26: 45261 | B26: #N/A | C26: #N/A | D26: #N/A | E26: #N/A | F26: 1
A27: 45292 | B27: 1 | C27: 1 | D27: #N/A | E27: 1 | F27: #N/A | G27: 45292
A28: 45323 | B28: #N/A | C28: #N/A | D28: #N/A | E28: #N/A | F28: 2
A29: 45352 | B29: #N/A | C29: #N/A | D29: #N/A | E29: #N/A | F29: 2
A30: 45383 | B30: #N/A | C30: #N/A | D30: #N/A | E30: #N/A | F30: 5
A31: 45413 | B31: #N/A | C31: 1 | D31: #N/A | E31: 1 | F31: 3
A32: 45444 | B32: #N/A | C32: #N/A | D32: #N/A | E32: #N/A | F32: 1
A33: 45474 | B33: 1 | C33: 4 | D33: #N/A | E33: #N/A | F33: 3
A34: 45505 | B34: #N/A | C34: #N/A | D34: #N/A | E34: 1 | F34: 3
A35: 45536 | B35: 1 | C35: #N/A | D35: #N/A | E35: 2 | F35: 2
A36: 45566 | B36: #N/A | C36: #N/A | D36: 8 | E36: 2 | F36: 2
A37: 45597 | B37: 5 | C37: 1 | D37: #N/A | E37: 3 | F37: 3
A38: 45627 | B38: #N/A | C38: #N/A | D38: #N/A | E38: #N/A | F38: #N/A
A39: 45658 | B39: 1 | C39: 2 | D39: #N/A | E39: 1 | F39: 5 | G39: 45658
A40: 45689 | B40: 1 | C40: 3 | D40: #N/A | E40: 2 | F40: 1
A41: 45717 | B41: 1 | C41: 4 | D41: #N/A | E41: 1 | F41: 4
A42: 45748 | B42: #N/A | C42: 4 | D42: 1 | E42: 1 | F42: 2
A43: 45778 | B43: #N/A | C43: 7 | D43: 9 | E43: 2 | F43: 7
A44: 45809 | B44: 2 | C44: 5 | D44: 3 | E44: 6 | F44: 5
A45: 45839 | B45: 2 | C45: 8 | D45: 2 | E45: 6 | F45: 8
A46: 45870 | B46: #N/A | C46: 3 | D46: 2 | E46: 6 | F46: 8
A47: 45901 | B47: 1 | C47: 6 | D47: 4 | E47: 5 | F47: 16
A48: 45931 | B48: 2 | C48: 3 | D48: 2 | E48: 6 | F48: 16
A49: 45962 | B49: 1 | C49: 6 | D49: 6 | E49: 11 | F49: 11
A50: 45992 | B50: 3 | C50: 5 | D50: 8 | E50: 11 | F50: 13
A51: 46023 | B51: 2 | C51: 1 | D51: 3 | E51: 4 | F51: 3 | G51: 46023
A52: 46054 | B52: 2 | C52: 5 | D52: 5 | E52: 5 | F52: 6
A53: 46082 | B53: 3 | C53: 3 | D53: 2 | E53: 5 | F53: 13
A54: 46113 | B54: 9 | C54: 4 | D54: 4 | E54: 17 | F54: 19
A55: 46143 | B55: 7 | C55: 5 | D55: 4 | E55: 19 | F55: 16
A56: 46174 | B56: 4 | C56: 5 | D56: 11 | E56: 36 | F56: 20

Sheet В.1.7
A1: << | B1: =IF(Content!$E$1=1,B2,B3) -> Об'єкти логістики | C1: =IF(Content!$E$1=1,C2,C3) -> Портова інфраструктура | D1: =IF(Content!$E$1=1,D2,D3) -> Залізнична інфраструктура | G1: =IF(Content!$E$1=1,G2,G3) -> Кількість нових пошкоджень об'єктів логістики й транспортної інфраструктури внаслідок обстрілів рф
B2: Об'єкти логістики | C2: Портова інфраструктура | D2: Залізнична інфраструктура | G2: Кількість нових пошкоджень об'єктів логістики й транспортної інфраструктури внаслідок обстрілів рф
B3: Logistics facilities | C3: Port infrastructure | D3: Railway infrastructure | G3: Number of newly damaged logistics and transport infrastructure facilities caused by russian strikes
A4: 44593 | B4: 0 | E4: 44593
A5: 44621 | B5: 9 | D5: 7
A6: 44652 | B6: 6 | D6: 1
A7: 44682 | B7: 4 | C7: 1 | D7: 1
A8: 44713 | B8: 7 | C8: 1
A9: 44743 | B9: 3 | C9: 1 | D9: 1
A10: 44774 | B10: 7 | C10: 1 | D10: 1
A11: 44805 | B11: 2 | D11: 2
A12: 44835 | B12: 1
A13: 44866 | B13: 0
A14: 44896 | B14: 0
A15: 44927 | B15: 0 | E15: 44927
A16: 44958 | B16: 3
A17: 44986 | B17: 1 | G17: =IF(Content!$E$1=1,G18,G19) -> Джерело: ACLED, розрахунки НБУ.
A18: 45017 | B18: 0 | D18: 1 | G18: Джерело: ACLED, розрахунки НБУ.
A19: 45047 | B19: 3 | C19: 1 | D19: 1 | G19: Source: ACLED, NBU staff estimates.
A20: 45078 | B20: 2
A21: 45108 | B21: 2
A22: 45139 | B22: 3 | C22: 1
A23: 45170 | B23: 1
A24: 45200 | B24: 6 | C24: 4
A25: 45231 | B25: 0
A26: 45261 | B26: 0
A27: 45292 | B27: 1 | E27: 45292
A28: 45323 | B28: 1 | D28: 1
A29: 45352 | B29: 4
A30: 45383 | B30: 0 | C30: 3 | D30: 3
A31: 45413 | B31: 0 | D31: 1
A32: 45444 | B32: 0
A33: 45474 | B33: 1 | C33: 2
A34: 45505 | B34: 1 | C34: 1 | D34: 1
A35: 45536 | B35: 2
A36: 45566 | B36: 9
A37: 45597 | B37: 5
A38: 45627 | B38: 0
A39: 45658 | B39: 4 | D39: 1 | E39: 45658
A40: 45689 | B40: 4 | C40: 1 | D40: 1
A41: 45717 | B41: 7 | C41: 2 | D41: 3
A42: 45748 | B42: 6 | D42: 1
A43: 45778 | B43: 8 | D43: 3
A44: 45809 | B44: 10 | D44: 5
A45: 45839 | B45: 10 | C45: 1 | D45: 3
A46: 45870 | B46: 3 | C46: 2 | D46: 6
A47: 45901 | B47: 5 | D47: 4
A48: 45931 | B48: 6 | C48: 2 | D48: 16
A49: 45962 | B49: 12 | C49: 1 | D49: 6
A50: 45992 | B50: 12 | C50: 4 | D50: 2
A51: 46023 | B51: 16 | C51: 2 | D51: 6 | E51: 46023
A52: 46054 | B52: 13 | C52: 5 | D52: 8
A53: 46082 | B53: 14 | C53: 6 | D53: 8
A54: 46113 | B54: 16 | C54: 10 | D54: 13
A55: 46143 | B55: 15 | C55: 4 | D55: 10
A56: 46174 | B56: 31 | C56: 1 | D56: 13

Sheet В.1.8
A1: << | B1: =IF(Content!$E$1=1,B2,B3) -> Альтернативні маршрути* | C1: =IF(Content!$E$1=1,C2,C3) -> Чорноморські порти | F1: =IF(Content!$E$1=1,F2,F3) -> Експорт с/г вантажів чорноморськими портами та альтернативними маршрутами, млн т
B2: Альтернативні маршрути* | C2: Чорноморські порти | F2: Експорт с/г вантажів чорноморськими портами та альтернативними маршрутами, млн т
B3: Alternative routes* | C3: Black Sea ports | F3: Export of agricultural cargoes via Black Sea ports and alternative routes, million tons
A4: 03.22 | B4: 0.3 | C4: 0 | D4: 03.22
A5: 04.22 | B5: 1 | C5: 0
A6: 05.22 | B6: 1.7 | C6: 0
A7: 06.22 | B7: 2.2 | C7: 0
A8: 07.22 | B8: 2.8 | C8: 0
A9: 08.22 | B9: 3 | C9: 1.5
A10: 09.22 | B10: 2.7 | C10: 4.2
A11: 10.22 | B11: 2.7 | C11: 4.2
A12: 11.22 | B12: 2.8 | C12: 3.1
A13: 12.22 | B13: 2.7 | C13: 4.1
A14: 01.23 | B14: 2.6 | C14: 2.9 | D14: 01.23
A15: 02.23 | B15: 3 | C15: 3.3
A16: 03.23 | B16: 3.7 | C16: 3.7 | F16: =IF(Content!$E$1=1,F18,F20) -> * Альтернативні маршрути містять порти Дунаю, залізницю, автотранспорт, поромний транспорт.
A17: 04.23 | B17: 2.7 | C17: 2.9 | F17: =IF(Content!$E$1=1,F19,F21) -> Джерело: УЗА, ДМС, розрахунки НБУ.
A18: 05.23 | B18: 3.1 | C18: 1.3 | F18: * Альтернативні маршрути містять порти Дунаю, залізницю, автотранспорт, поромний транспорт.
A19: 06.23 | B19: 2.9 | C19: 2 | F19: Джерело: УЗА, ДМС, розрахунки НБУ.
A20: 07.23 | B20: 3.1 | C20: 0.3 | F20: * Alternative routes include Danube ports, rail, road, ferry transport.
A21: 08.23 | B21: 3.7 | C21: 0 | F21: Source: UGA, State Customs Service, NBU staff estimates.
A22: 09.23 | B22: 3.6 | C22: 0
A23: 10.23 | B23: 3 | C23: 1.3
A24: 11.23 | B24: 2.7 | C24: 2.7
A25: 12.23 | B25: 2.4 | C25: 4.8
A26: 01.24 | B26: 2.1 | C26: 4.3 | D26: 01.24
A27: 02.24 | B27: 2.2 | C27: 5.2
A28: 03.24 | B28: 2 | C28: 5
A29: 04.24 | B29: 1.8 | C29: 5.4
A30: 05.24 | B30: 1.6 | C30: 5.1
A31: 06.24 | B31: 1.4 | C31: 3.7
A32: 07.24 | B32: 1.3 | C32: 3.7
A33: 08.24 | B33: 1.1 | C33: 3.6
A34: 09.24 | B34: 1.1 | C34: 3.6
A35: 10.24 | B35: 1.2 | C35: 4.8
A36: 11.24 | B36: 1 | C36: 4.5
A37: 12.24 | B37: 0.8 | C37: 3.9
A38: 01.25 | B38: 0.6 | C38: 3.4 | D38: 01.25
A39: 02.25 | B39: 0.6 | C39: 3.8
A40: 03.25 | B40: 0.6 | C40: 4
A41: 04.25 | B41: 0.5 | C41: 3.2
A42: 05.25 | B42: 0.6 | C42: 3.5
A43: 06.25 | B43: 0.5 | C43: 2.6
A44: 07.25 | B44: 0.4 | C44: 2.5
A45: 08.25 | B45: 0.4 | C45: 3.3
A46: 09.25 | B46: 0.3 | C46: 2.5
A47: 10.25 | B47: 0.4 | C47: 3.5
A48: 11.25 | B48: 0.5 | C48: 3.9
A49: 12.25 | B49: 0.6 | C49: 3.6
A50: 01.26 | B50: 0.4 | C50: 3.7 | D50: 01.26
A51: 02.26 | B51: 0.6 | C51: 3.9
A52: 03.26 | B52: 0.6 | C52: 3.9
A53: 04.26 | B53: 0.5 | C53: 4.7
A54: 05.26 | B54: 0.5 | C54: 4.2
A55: 06.26 | B55: 0.5 | C55: 3.8
A56: 07.26 | B56: 0.5 | C56: 2.4 | D56: 07.26

Sheet B.2.T.1
A1: << | C1: =IF(Content!$E$1=1,C2,C3) -> Таблиця 1. Порівняння сценаріїв, закладених у Бюджетну декларацію, і прогнозу НБУ
C2: Таблиця 1. Порівняння сценаріїв, закладених у Бюджетну декларацію, і прогнозу НБУ
C3: Table 1. Comparison of scenarios embedded in the Budget Declaration, and the NBU forecast
C5: =IF(Content!$E$1=1,D5,E5) -> Показник | D5: Показник | E5: Indicator | F5: 2026 | G5: 2027 | H5: 2028 | I5: 2029 | J5: 2027 | K5: 2028 | L5: 2029 | M5: 2027 | N5: 2028 | O5: 2029
G6: =IF(Content!$E$1=1,G7,G8) -> Сценарій 1 | J6: =IF(Content!$E$1=1,J7,J8) -> НБУ, ІЗ липень | M6: =IF(Content!$E$1=1,M7,M8) -> Сценарій 2
G7: Сценарій 1 | J7: НБУ, ІЗ липень | M7: Сценарій 2
G8: Scenario 1 | J8: NBU, Inflation Report, July | M8: Scenario 2
C9: =IF(Content!$E$1=1,D9,E9) -> ВВП реальний, % р/р | D9: ВВП реальний, % р/р | E9: Real GDP, % yoy | F9: 1.6 | G9: 4.5 | H9: 5.3 | I9: 6.7 | J9: 1.8 | K9: 2.8 | L9: 3 | M9: 1.3 | N9: 4.1 | O9: 5
C10: =IF(Content!$E$1=1,D10,E10) -> Номінальний ВВП, млрд грн | D10: Номінальний ВВП, млрд грн | E10: Nominal GDP, UAH billions | F10: 10105 | G10: 11531 | H10: 13131 | I10: 14952 | J10: 10065 | K10: 11220 | L10: 12275 | M10: 11144 | N10: 12664 | O10: 14373
C11: =IF(Content!$E$1=1,D11,E11) -> Індекс споживчих цін, % (грудень до грудня) | D11: Індекс споживчих цін, % (грудень до грудня) | E11: Consumer price index, % (December-to-December) | F11: 9.2 | G11: 8.9 | H11: 6.9 | I11: 5.1 | J11: 10 | K11: 6.9 | L11: 5 | M11: 8 | N11: 8.2 | O11: 5.9
C12: =IF(Content!$E$1=1,D12,E12) -> Експорт товарів та послуг (млрд дол) | D12: Експорт товарів та послуг (млрд дол) | E12: Exports of goods and services (USD billions) | F12: 55.8 | G12: 60.4 | H12: 67.2 | I12: 77.5 | J12: 56.1 | K12: 67.9 | L12: 70.9 | M12: 57.9 | N12: 63.2 | O12: 72.2
C13: =IF(Content!$E$1=1,D13,E13) -> Імпорт товарів і послуг (млрд дол) | D13: Імпорт товарів і послуг (млрд дол) | E13: Imports of goods and services (USD billions) | F13: 125 | G13: 131.3 | H13: 141.5 | I13: 151.1 | J13: 145.1 | K13: 134.5 | L13: 125.1 | M13: 137.5 | N13: 143.3 | O13: 152.6
C14: =IF(Content!$E$1=1,D14,E14) -> Номінальна середня заробітна плата, грн | D14: Номінальна середня заробітна плата, грн | E14: Average nominal wage, UAH | F14: 30088 | G14: 35010 | H14: 39362 | I14: 44083 | J14: 31511 | K14: 36051 | L14: 39743 | M14: 34409 | N14: 38603 | O14: 43185
C16: =IF(Content!$E$1=1,C19,C20) -> Джерело: Сценарій 1 та сценарій 2 – прогноз Міністерства економіки, НБУ.
C19: Джерело: Сценарій 1 та сценарій 2 – прогноз Міністерства економіки, НБУ.
C20: Source: Scenario 1 and Scenario 2 – Ministry of Economy, NBU.

Sheet B.2.T.2
A1: << | C1: =IF(Content!$E$1=1,C2,C3) -> Таблиця 2. Параметри державного бюджету за Сценарієм 1 відповідно до Бюджетної декларації, млрд грн
C2: Таблиця 2. Параметри державного бюджету за Сценарієм 1 відповідно до Бюджетної декларації, млрд грн
C3: Table 2. State budget parameters under Scenario 1 according to the Budget Declaration, UAH billions
C5: =IF(Content!$E$1=1,D5,E5) -> Показник | D5: Показник | E5: Indicator | F5: 2027 | G5: 2028 | H5: 2029
C6: =IF(Content!$E$1=1,D6,E6) -> Доходи | D6: Доходи | E6: Revenues | F6: 3012 | G6: 3421 | H6: 3726
C7: =IF(Content!$E$1=1,D7,E7) -> Видатки | D7: Видатки | E7: Expenditures | F7: 5046 | G7: 4873 | H7: 4545
C8: =IF(Content!$E$1=1,D8,E8) -> Кредитування | D8: Кредитування | E8: Net lending | F8: 6 | G8: 5 | H8: 3
C9: =IF(Content!$E$1=1,D9,E9) -> Дефіцит | D9: Дефіцит | E9: Deficit | F9: 2041 | G9: 1458 | H9: 822
C10: =IF(Content!$E$1=1,D10,E10) -> Дефіцит, % ВВП | D10: Дефіцит, % ВВП | E10: Deficit, % of GDP | F10: 17.7 | G10: 11.1 | H10: 5.5
C12: =IF(Content!$E$1=1,C15,C16) -> Джерело:МФУ, розрахунки НБУ.
C15: Джерело:МФУ, розрахунки НБУ.
C16: Source: MoF, NBU staff estimates.

Sheet 3.1
A1: << | B1: =IF(Content!$E$1=1,B2,B3) -> Облікова ставка | C1: =IF(Content!$E$1=1,C2,C3) -> Середьозважена ФО | D1: =IF(Content!$E$1=1,D2,D3) -> Середньозважена НФК | E1: =IF(Content!$E$1=1,E2,E3) -> Медіана ФО | H1: =IF(Content!$E$1=1,H2,H3) -> Ставки за строковими гривневими депозитами та середньомісячна облікова ставка, %
B2: Облікова ставка | C2: Середьозважена ФО | D2: Середньозважена НФК | E2: Медіана ФО | H2: Ставки за строковими гривневими депозитами та середньомісячна облікова ставка, %
B3: Key policy rate | C3: Weighted average retail deposits | D3: Weighted average NFC deposits | E3: Median retail deposits rate | H3: Rates on term hryvnia deposits and average monthly key policy rate, %
A4: 44927 | B4: 25 | C4: 12.43 | D4: 11.1 | E4: 14.23
A5: 44958 | B5: 25 | C5: 12.63 | D5: 12.48 | E5: 14.31
A6: 44986 | B6: 25 | C6: 13.19 | D6: 13.71 | E6: 14.32
A7: 45017 | B7: 25 | C7: 13.27 | D7: 13.64 | E7: 14.77
A8: 45047 | B8: 25 | C8: 14.04 | D8: 13.94 | E8: 15.5
A9: 45078 | B9: 25 | C9: 14.44 | D9: 14.48 | E9: 15.67
A10: 45108 | B10: 24.61 | C10: 15.49 | D10: 14.67 | E10: 16.19
A11: 45139 | B11: 22 | C11: 14.76 | D11: 13.59 | E11: 15.71
A12: 45170 | B12: 20.93 | C12: 14.77 | D12: 12.68 | E12: 16.08
A13: 45200 | B13: 19.35 | C13: 14.55 | D13: 10.63 | E13: 15.31
A14: 45231 | B14: 16 | C14: 14.53 | D14: 10.35 | E14: 14.99
A15: 45261 | B15: 15.45 | C15: 14.43 | D15: 10.46 | E15: 15.15
A16: 45292 | B16: 15 | C16: 14.22 | D16: 10.1 | E16: 14.8
A17: 45323 | B17: 15 | C17: 14.08 | D17: 9.98 | E17: 14.95 | H17: =IF(Content!$E$1=1,H18,H19) -> Джерело: НБУ.
A18: 45352 | B18: 14.73 | C18: 13.96 | D18: 9.78 | E18: 14.64 | H18: Джерело: НБУ.
A19: 45383 | B19: 14.33 | C19: 13.66 | D19: 9.77 | E19: 14.56 | H19: Source: NBU.
A20: 45413 | B20: 13.5 | C20: 13.46 | D20: 9.06 | E20: 14.16
A21: 45444 | B21: 13.22 | C21: 13.13 | D21: 8.75 | E21: 14.28
A22: 45474 | B22: 13 | C22: 12.94 | D22: 8.57 | E22: 14.09
A23: 45505 | B23: 13 | C23: 12.72 | D23: 8.57 | E23: 13.85
A24: 45536 | B24: 13 | C24: 12.78 | D24: 8.69 | E24: 13.66
A25: 45566 | B25: 13 | C25: 12.87 | D25: 8.78 | E25: 13.43
A26: 45597 | B26: 13 | C26: 12.89 | D26: 8.54 | E26: 12.96
A27: 45627 | B27: 13.31 | C27: 12.98 | D27: 8.5 | E27: 13.42
A28: 45658 | B28: 13.73 | C28: 12.99 | D28: 8.73 | E28: 13.61
A29: 45689 | B29: 14.5 | C29: 13.13 | D29: 9.12 | E29: 13.87
A30: 45717 | B30: 15.27 | C30: 13.06 | D30: 9.54 | E30: 14.04
A31: 45748 | B31: 15.5 | C31: 13.32 | D31: 9.9 | E31: 14.48
... A45: 46174 | B45: 15 | C45: 13.62 | D45: 10.03 | E45: 14.67

Sheet 3.2
A1: << | B1: =IF(Content!$E$1=1,B2,B3) -> Всього | C1: =IF(Content!$E$1=1,C2,C3) -> Банки з державною часткою | D1: =IF(Content!$E$1=1,D2,D3) -> Банки іноземних банківських груп | E1: =IF(Content!$E$1=1,E2,E3) -> Банки з приватним капіталом | H1: =IF(Content!$E$1=1,H2,H3) -> Середньозважені ставки за гривневими депозитами ФО на строк від трьох місяців (за групами банків), %
B2: Всього | C2: Банки з державною часткою | D2: Банки іноземних банківських груп | E2: Банки з приватним капіталом | H2: Середньозважені ставки за гривневими депозитами ФО на строк від трьох місяців (за групами банків), %
B3: Total | C3: State-owned banks | D3: Banks of foreign banking groups | E3: Private banks | H3: Weighted average interest rates on hryvnia retail deposits with a term of over three months (by bank group), %
A4: 44927 | B4: 12.81 | C4: 12.26 | D4: 12.03 | E4: 13.9
A5: 44958 | B5: 13.06 | C5: 12.59 | D5: 11.84 | E5: 14.16
A6: 44986 | B6: 13.52 | C6: 12.97 | D6: 11.8 | E6: 14.96
A7: 45017 | B7: 13.78 | C7: 13.23 | D7: 12.27 | E7: 14.84
A8: 45047 | B8: 14.63 | C8: 14 | D8: 12.69 | E8: 16
A9: 45078 | B9: 14.92 | C9: 14.41 | D9: 12.91 | E9: 16.15
A10: 45108 | B10: 15.98 | C10: 15.38 | D10: 13.3 | E10: 17.16
A11: 45139 | B11: 15.43 | C11: 15.04 | D11: 13.48 | E11: 16.62
A12: 45170 | B12: 15.32 | C12: 14.77 | D12: 13.57 | E12: 16.46
A13: 45200 | B13: 15.07 | C13: 14.39 | D13: 13.62 | E13: 16.12
A14: 45231 | B14: 14.98 | C14: 14.23 | D14: 13.01 | E14: 16.07
A15: 45261 | B15: 14.91 | C15: 14.26 | D15: 13.07 | E15: 15.91
... A17: 45323 | B17: 14.47 | C17: 13.88 | D17: 12.72 | E17: 15.63
A18: 45352 | B18: 14.42 | C18: 13.75 | D18: 12.86 | E18: 15.52 | H18: =IF(Content!$E$1=1,H19,H20) -> Джерело: НБУ.
A19: 45383 | B19: 14.24 | C19: 13.48 | D19: 12.41 | E19: 15.34 | H19: Джерело: НБУ.
A20: 45413 | B20: 13.87 | C20: 12.86 | D20: 11.91 | E20: 15.2 | H20: Source: NBU.
A21: 45444 | B21: 13.53 | C21: 12.43 | D21: 11.86 | E21: 14.89
A22: 45474 | B22: 13.3 | C22: 12.2 | D22: 11.79 | E22: 14.75
A23: 45505 | B23: 13.2 | C23: 12.02 | D23: 11.51 | E23: 14.6
A24: 45536 | B24: 13.16 | C24: 11.98 | D24: 11.43 | E24: 14.72
A25: 45566 | B25: 13.23 | C25: 11.87 | D25: 11.57 | E25: 14.74
A26: 45597 | B26: 13.25 | C26: 11.87 | D26: 11.55 | E26: 14.74
A27: 45627 | B27: 13.33 | C27: 11.86 | D27: 11.61 | E27: 14.79
A28: 45658 | B28: 13.32 | C28: 11.77 | D28: 11.44 | E28: 14.78
A29: 45689 | B29: 13.44 | C29: 11.81 | D29: 11.99 | E29: 14.92
A30: 45717 | B30: 13.42 | C30: 11.84 | D30: 11.69 | E30: 14.99
A31: 45748 | B31: 13.65 | C31: 12.49 | D31: 12.12 | E31: 15.14
A32: 45778 | B32: 13.88 | C32: 12.53 | D32: 12.27 | E32: 15.33
... A45: 46174 | B45: 13.98 | C45: 12.91 | D45: 12.34 | E45: 15.45

Sheet 3.3
A1: << | B1: =IF(Content!$E$1=1,B2,B3) -> До 92 днів | C1: =IF(Content!$E$1=1,C2,C3) -> 93 дні та більше | D1: =IF(Content!$E$1=1,D2,D3) -> Поточні | E1: =IF(Content!$E$1=1,E2,E3) -> Частка строкових (п. ш.) | H1: =IF(Content!$E$1=1,H2,H3) -> Середньомісячні* залишки гривневих депозитів ФО, млрд грн, та частка строкових коштів у портфелі, %
B2: До 92 днів | C2: 93 дні та більше | D2: Поточні | E2: Частка строкових (п. ш.) | H2: Середньомісячні* залишки гривневих депозитів ФО, млрд грн, та частка строкових коштів у портфелі, %
B3: Up to 92 days | C3: 93 days and over | D3: On-demand | E3: Share of term deposits (RHS) | H3: Monthly average* stocks of hryvnia retail deposits, UAH billion, and share of term deposits in the portfolio, %
A4: 44927 | B4: 0 | C4: 180.73 | D4: 405.65 | E4: 30.82
A5: 44958 | B5: 0 | C5: 185 | D5: 404.3 | E5: 31.39
A6: 44986 | B6: 0 | C6: 190.76 | D6: 400.48 | E6: 32.26
A7: 45017 | B7: 37.53 | C7: 169.41 | D7: 398.44 | E7: 34.18
A8: 45047 | B8: 29.64 | C8: 177.29 | D8: 399.5 | E8: 34.12
A9: 45078 | B9: 22.12 | C9: 194.42 | D9: 406.42 | E9: 34.76
A10: 45108 | B10: 20.45 | C10: 190.75 | D10: 430.59 | E10: 32.91
A11: 45139 | B11: 22.3 | C11: 196.6 | D11: 429.66 | E11: 33.75
A12: 45170 | B12: 19.74 | C12: 205.65 | D12: 428.01 | E12: 34.5
A13: 45200 | B13: 17.75 | C13: 211.97 | D13: 424.39 | E13: 35.12
A14: 45231 | B14: 16.69 | C14: 217.53 | D14: 432.25 | E14: 35.14
A15: 45261 | B15: 15.61 | C15: 223.71 | D15: 457.57 | E15: 34.34
A16: 45292 | B16: 15.11 | C16: 229.39 | D16: 449.71 | E16: 35.22
A17: 45323 | B17: 10.79 | C17: 237.88 | D17: 449.48 | E17: 35.62 | H17: =IF(Content!$E$1=1,H19,H20) -> * Календарні дні.
A18: 45352 | B18: 10.14 | C18: 241.42 | D18: 459.97 | E18: 35.35 | H18: =IF(Content!$E$1=1,H21,H22) -> Джерело: НБУ.
A19: 45383 | B19: 9.69 | C19: 245.6 | D19: 462.47 | E19: 35.57 | H19: * Календарні дні.
A20: 45413 | B20: 9.27 | C20: 249.2 | D20: 473.85 | E20: 35.29 | H20: * Calendar days.
A21: 45444 | B21: 9.05 | C21: 250.71 | D21: 484.31 | E21: 34.91 | H21: Джерело: НБУ.
A22: 45474 | B22: 8.41 | C22: 250.98 | D22: 495.28 | E22: 34.37 | H22: Source: NBU.
A23: 45505 | B23: 7.91 | C23: 251.01 | D23: 491.86 | E23: 34.49
A24: 45536 | B24: 8.08 | C24: 251.26 | D24: 489.86 | E24: 34.62
A25: 45566 | B25: 7.94 | C25: 253.95 | D25: 504.89 | E25: 34.15
A26: 45597 | B26: 7.94 | C26: 254.88 | D26: 503.92 | E26: 34.28
A27: 45627 | B27: 7.54 | C27: 255.51 | D27: 523.49 | E27: 33.44
A28: 45658 | B28: 7.47 | C28: 257.23 | D28: 517.14 | E28: 33.86
A29: 45689 | B29: 7.51 | C29: 259.9 | D29: 526.09 | E29: 33.7
A30: 45717 | B30: 7.65 | C30: 262.37 | D30: 536.48 | E30: 33.48
A31: 45748 | B31: 7.37 | C31: 268.8 | D31: 535.17 | E31: 34.04
A32: 45778 | B32: 7.19 | C32: 273.49 | D32: 546.45 | E32: 33.93
A33: 45809 | B33: 6.97 | C33: 278.64 | D33: 562.32 | E33: 33.68
A34: 45839 | B34: 6.57 | C34: 282.75 | D34: 568.5 | E34: 33.73
... A45: 46174 | B45: 6.98 | C45: 333.39 | D45: 668.5 | E45: 33.74

Sheet 3.4
A1: << | B1: =IF(Content!$E$1=1,B2,B3) -> Строкові депозити | C1: =IF(Content!$E$1=1,C2,C3) -> ОВДП* | F1: =IF(Content!$E$1=1,F2,F3) -> Зміна залишків гривневих ОВДП у портфелі ФО та строкових депозитів ФО, млрд грн
B2: Строкові депозити | C2: ОВДП* | F2: Зміна залишків гривневих ОВДП у портфелі ФО та строкових депозитів ФО, млрд грн
B3: Retail term deposits | C3: Domestic debt securities* | F3: Changes in the stock of hryvnia domestic debt securities held by individuals and hryvnia retail term deposits, UAH billions
A4: 44927 | B4: 3.51 | C4: 0.83
A5: 44958 | B5: 4.18 | C5: 0.69
A6: 44986 | B6: 7.93 | C6: 1.11
A7: 45017 | B7: 7.19 | C7: 1
A8: 45047 | B8: 10.35 | C8: 1.27
A9: 45078 | B9: 9.69 | C9: 0.66
A10: 45108 | B10: -7.12 | C10: 1.72
A11: 45139 | B11: 7.82 | C11: 0.88
A12: 45170 | B12: 5.58 | C12: 0.18 | M12: =IF(Content!$E$1=1,M13,M14) -> перекласифікація
A13: 45200 | B13: 3.46 | C13: 1.13 | M13: перекласифікація
A14: 45231 | B14: 4.93 | C14: 0.02 | M14: reclassification
A15: 45261 | B15: 6.23 | C15: 1.41
A16: 45292 | B16: 4.11 | C16: 1.74 | F16: =IF(Content!$E$1=1,F18,F19) -> * За номінально-амортизаційною вартістю.
A17: 45323 | B17: 3.54 | C17: 1.32 | F17: =IF(Content!$E$1=1,F20,F21) -> Джерело: НБУ.
A18: 45352 | B18: 2.66 | C18: 1.01 | F18: * За номінально-амортизаційною вартістю.
A19: 45383 | B19: 4.02 | C19: 0.12 | F19: * At outstanding nominal value.
A20: 45413 | B20: 3.38 | C20: 2.3 | F20: Джерело: НБУ.
A21: 45444 | B21: -0.85 | C21: -3.38 | F21: Source: NBU.
A22: 45474 | B22: -0.48 | C22: 2.57
A23: 45505 | B23: -0.37 | C23: 1.95
A24: 45536 | B24: 2.04 | C24: 1.81
A25: 45566 | B25: 1.9 | C25: 0.33
A26: 45597 | B26: 0.43 | C26: 0.79
A27: 45627 | B27: 1.33 | C27: 3.06
A28: 45658 | B28: 1.67 | C28: 0.33
A29: 45689 | B29: 3.01 | C29: 0.89
A30: 45717 | B30: 2.44 | C30: 2.82
A31: 45748 | B31: 6.68 | C31: 0.12
A32: 45778 | B32: 4.59 | C32: 6.96
A33: 45809 | B33: 5.84 | C33: -0.35
... A45: 46174 | B45: 6.04 | C45: -1.32

Sheet 3.5
A1: << | B1: =IF(Content!$E$1=1,B2,B3) -> Всього | C1: =IF(Content!$E$1=1,C2,C3) -> Великі | D1: =IF(Content!$E$1=1,D2,D3) -> Середні | E1: =IF(Content!$E$1=1,E2,E3) -> Малі та мікро | H1: =IF(Content!$E$1=1,H2,H3) -> Середньозважені процентні ставки за новими* гривневими кредитами НФК (за розміром підприємств), %
B2: Всього | C2: Великі | D2: Середні | E2: Малі та мікро | H2: Середньозважені процентні ставки за новими* гривневими кредитами НФК (за розміром підприємств), %
B3: Total | C3: Large | D3: Medium | E3: Small and micro | H3: Weighted average interest rates on new* hryvnia loans of NFCs (by size of enterprises), %
A4: 43466 | B4: 19.87 | C4: 19.92 | D4: 19.69 | E4: 19.92
A5: 43497 | B5: 18.12 | C5: 17.59 | D5: 18.62 | E5: 18.9
A6: 43525 | B6: 18.23 | C6: 17.57 | D6: 18.61 | E6: 19.79
A7: 43556 | B7: 18.3 | C7: 17.67 | D7: 18.81 | E7: 19.52
A8: 43586 | B8: 18.33 | C8: 17.79 | D8: 18.66 | E8: 19.48
A9: 43617 | B9: 18.53 | C9: 17.85 | D9: 19.16 | E9: 19.68
A10: 43647 | B10: 18.39 | C10: 17.68 | D10: 19.09 | E10: 20.08
A11: 43678 | B11: 18.33 | C11: 17.65 | D11: 19.37 | E11: 19.66
A12: 43709 | B12: 17.95 | C12: 17.42 | D12: 19.53 | E12: 18.21
A13: 43739 | B13: 17.29 | C13: 16.3 | D13: 19.08 | E13: 19.2
A14: 43770 | B14: 16.29 | C14: 15.08 | D14: 18.73 | E14: 18.66
A15: 43800 | B15: 15.53 | C15: 14.26 | D15: 18.13 | E15: 18.22
A16: 43831 | B16: 13.83 | C16: 12.31 | D16: 17.41 | E16: 18.36 | H16: =IF(Content!$E$1=1,H19,H20) -> * Без урахування угод за додатковими договорами, за якими відбулася зміна суми та/або процентної ставки, а також пролонгації.
A17: 43862 | B17: 12.44 | C17: 10.18 | D17: 16.54 | E17: 18.31 | H17: =IF(Content!$E$1=1,H21,H22) -> Джерело: НБУ.
A18: 43891 | B18: 13.77 | C18: 12.22 | D18: 16.67 | E18: 18.24
A19: 43922 | B19: 13.38 | C19: 12.18 | D19: 16.27 | E19: 17.6 | H19: * Без урахування угод за додатковими договорами, за якими відбулася зміна суми та/або процентної ставки, а також пролонгації.
A20: 43952 | B20: 11.42 | C20: 9.74 | D20: 15.2 | E20: 16.58 | H20: * Excluding transactions under additional agreements where there was a change in the loan principal and/or interest rate, as well as prolongation.
A21: 43983 | B21: 10.49 | C21: 8.63 | D21: 13.9 | E21: 15.66 | H21: Джерело: НБУ.
A22: 44013 | B22: 9.69 | C22: 7.71 | D22: 13.16 | E22: 15.17 | H22: Source: NBU.
A23: 44044 | B23: 9.33 | C23: 7.42 | D23: 12.63 | E23: 13.36
A24: 44075 | B24: 9.31 | C24: 7.33 | D24: 12.56 | E24: 12.29
A25: 44105 | B25: 9.04 | C25: 7.21 | D25: 12.47 | E25: 11.96
A26: 44136 | B26: 9.06 | C26: 7.12 | D26: 10.99 | E26: 13.9
A27: 44166 | B27: 8.98 | C27: 7.06 | D27: 10.36 | E27: 13.63
A28: 44197 | B28: 8.95 | C28: 7.36 | D28: 10.07 | E28: 12.93
A29: 44228 | B29: 8.59 | C29: 6.93 | D29: 10.24 | E29: 12.23
A30: 44256 | B30: 8.63 | C30: 6.72 | D30: 10.44 | E30: 11.96
A31: 44287 | B31: 8.87 | C31: 7.01 | D31: 10.84 | E31: 11.27
A32: 44317 | B32: 9.32 | C32: 7.78 | D32: 10.83 | E32: 10.87
A33: 44348 | B33: 9.34 | C33: 7.71 | D33: 11.21 | E33: 10.78
A34: 44378 | B34: 9.39 | C34: 7.85 | D34: 11.2 | E34: 10.53
... A93: 46174 | B93: 15.09 | C93: 13.65 | D93: 16.08 | E93: 17.99

Sheet 3.6
A1: << | B1: =IF(Content!$E$1=1,B2,B3) -> Корпоративний сектор | C1: =IF(Content!$E$1=1,C2,C3) -> Фізичні особи | F1: =IF(Content!$E$1=1,F2,F3) -> Чисті гривневі кредити, 12.2018 = 100
B2: Корпоративний сектор | C2: Фізичні особи | F2: Чисті гривневі кредити, 12.2018 = 100
B3: Corporate sector | C3: Retail loans | F3: Net hryvnia loans, 12.2018 = 100
A4: 43466 | B4: 93.6 | C4: 101.82
A5: 43497 | B5: 94.2 | C5: 103.37
A6: 43525 | B6: 95.25 | C6: 106.18
A7: 43556 | B7: 97.09 | C7: 107.75
A8: 43586 | B8: 96.39 | C8: 111.45
A9: 43617 | B9: 98.43 | C9: 113.15
A10: 43647 | B10: 99.06 | C10: 116.37
A11: 43678 | B11: 100.98 | C11: 119.63
A12: 43709 | B12: 99.77 | C12: 122.21
A13: 43739 | B13: 99.98 | C13: 124.95
A14: 43770 | B14: 99.75 | C14: 126.87
A15: 43800 | B15: 93.32 | C15: 130.61
A16: 43831 | B16: 87.52 | C16: 132.49 | F16: =IF(Content!$E$1=1,F17,F18) -> Джерело: НБУ.
A17: 43862 | B17: 89.01 | C17: 133.95 | F17: Джерело: НБУ.
A18: 43891 | B18: 97.34 | C18: 134.9 | F18: Source: NBU.
A19: 43922 | B19: 93.99 | C19: 128.86
A20: 43952 | B20: 91.33 | C20: 128.2
A21: 43983 | B21: 91.09 | C21: 128.16
A22: 44013 | B22: 91.89 | C22: 129.69
A23: 44044 | B23: 91.26 | C23: 132.04
A24: 44075 | B24: 93.79 | C24: 133.26
A25: 44105 | B25: 96.7 | C25: 134.18
A26: 44136 | B26: 98.86 | C26: 136.72
A27: 44166 | B27: 98.02 | C27: 137.87
A28: 44197 | B28: 99.87 | C28: 138.84
A29: 44228 | B29: 100.96 | C29: 141.59
A30: 44256 | B30: 103.19 | C30: 146.12
... A93: 46174 | B93: 261.73 | C93: 334.36

Sheet 3.7
A1: << | B1: =IF(Content!$E$1=1,B2,B3) -> Офіційний курс гривні до долара | C1: =IF(Content!$E$1=1,C2,C3) -> Курс продажу долара на готівковому ринку | D1: =IF(Content!$E$1=1,D2,D3) -> Офіційний курс гривні до євро | E1: =IF(Content!$E$1=1,E2,E3) -> Курс євро до долара (п. ш.) | H1: =IF(Content!$E$1=1,H2,H3) -> Курси гривні до долара та євро до долара
B2: Офіційний курс гривні до долара | C2: Курс продажу долара на готівковому ринку | D2: Офіційний курс гривні до євро | E2: Курс євро до долара (п. ш.) | H2: Курси гривні до долара та євро до долара
B3: Official UAH/USD exchange rate | C3: USD cash market selling exchange rate | D3: Official UAH/EUR exchange rate | E3: EUR/USD exchange rate (RHS) | H3: Hryvnia to USD and EUR exchange rates, and EUR to USD
A4: 45658 | B4: 42.0295 | C4: 42.4365 | D4: 43.6855 | E4: 1.0389
A5: 45659 | B5: 41.9725 | C5: 42.4595 | D5: 43.6052 | E5: 1.0321
A6: 45660 | B6: 42.0385 | C6: 42.5143 | D6: 43.3753 | E6: 1.0299
A7: 45661 | B7: 42.0385 | C7: 42.5143 | D7: 43.3753 | E7: 1.0299
A8: 45662 | B8: 42.0385 | C8: 42.5143 | D8: 43.3753 | E8: 1.0299
A9: 45663 | B9: 42.0889 | C9: 42.6891 | D9: 43.3347 | E9: 1.0426
A10: 45664 | B10: 42.1959 | C10: 42.745 | D10: 43.9091 | E10: 1.0393
A11: 45665 | B11: 42.2297 | C11: 42.7669 | D11: 43.8767 | E11: 1.0286
A12: 45666 | B12: 42.2361 | C12: 42.8597 | D12: 43.4272 | E12: 1.0305
A13: 45667 | B13: 42.2825 | C13: 42.9692 | D13: 43.5594 | E13: 1.0304
A14: 45668 | B14: 42.2825 | C14: 42.9692 | D14: 43.5594 | E14: 1.0304
A15: 45669 | B15: 42.2825 | C15: 42.9692 | D15: 43.5594 | E15: 1.0304
... A17: 45671 | B17: 42.2692 | C17: 42.9324 | D17: 43.1273 | E17: 1.0245
A18: 45672 | B18: 42.2734 | C18: 42.887 | D18: 43.3218 | E18: 1.03 | H18: =IF(Content!$E$1=1,H20,H21) -> Джерело: НБУ, ЄЦБ.
A19: 45673 | B19: 42.2659 | C19: 42.7506 | D19: 43.5297 | E19: 1.0272
A20: 45674 | B20: 42.1729 | C20: 42.6348 | D20: 43.32 | E20: 1.0298 | H20: Джерело: НБУ, ЄЦБ.
A21: 45675 | B21: 42.1729 | C21: 42.6348 | D21: 43.32 | E21: 1.0298 | H21: Source: NBU, ECB.
A22: 45676 | B22: 42.1729 | C22: 42.6348 | D22: 43.32 | E22: 1.0298
A23: 45677 | B23: 42.1257 | C23: 42.6159 | D23: 43.3684 | E23: 1.0316
A24: 45678 | B24: 42.1551 | C24: 42.5699 | D24: 43.4998 | E24: 1.0357
A25: 45679 | B25: 42.1661 | C25: 42.4242 | D25: 43.6419 | E25: 1.0443
A26: 45680 | B26: 42.0325 | C26: 42.3146 | D26: 43.8735 | E26: 1.0404
A27: 45681 | B27: 41.9751 | C27: 42.1414 | D27: 43.6709 | E27: 1.0472
A28: 45682 | B28: 41.9751 | C28: 42.1414 | D28: 43.6709 | E28: 1.0472
A29: 45683 | B29: 41.9751 | C29: 42.1414 | D29: 43.6709 | E29: 1.0472
A30: 45684 | B30: 41.9253 | C30: 42.227 | D30: 43.9168 | E30: 1.053
A31: 45685 | B31: 41.9479 | C31: 42.2667 | D31: 44.146 | E31: 1.0421
A32: 45686 | B32: 42.0195 | C32: 42.1943 | D32: 43.7843 | E32: 1.0396
A33: 45687 | B33: 41.9294 | C33: 42.0816 | D33: 43.6192 | E33: 1.0403
... A580: 46234 | B580: 44.6916 | C580: 44.9047 | D580: 51.2747 | E580: 1.1485

Sheet 3.8
A1: << | B1: =IF(Content!$E$1=1,B2,B3) -> РЕОК | C1: =IF(Content!$E$1=1,C2,C3) -> НЕОК | D1: =IF(Content!$E$1=1,D2,D3) -> Інфляційний диференціал | G1: =IF(Content!$E$1=1,G2,G3) -> Внески в зміну індексу РЕОК, % р/р
B2: РЕОК | C2: НЕОК | D2: Інфляційний диференціал | G2: Внески в зміну індексу РЕОК, % р/р
B3: REER | C3: NEER | D3: Inflationary differential | G3: Contributions to the change in the REER index, % yoy | R3: =IF(Content!$E$1=1,R4,R5) -> зміцнення
A4: 43466 | B4: -18.4 | C4: -12.2 | D4: -5.5 | R4: зміцнення
A5: 43497 | B5: -16.3 | C5: -10.8 | D5: -4.9 | R5: appreciation
A6: 43525 | B6: -12.9 | C6: -8 | D6: -4.6
A7: 43556 | B7: -11.4 | C7: -6.5 | D7: -4.6
A8: 43586 | B8: -11.3 | C8: -5.6 | D8: -5.5
A9: 43617 | B9: -8.8 | C9: -3.3 | D9: -5.3
A10: 43647 | B10: -12.1 | C10: -6.4 | D10: -5.4
A11: 43678 | B11: -17.3 | C11: -11.4 | D11: -5.3
A12: 43709 | B12: -21.6 | C12: -16.3 | D12: -4.5
A13: 43739 | B13: -18.8 | C13: -14.7 | D13: -3.6
A14: 43770 | B14: -18.3 | C14: -15.9 | D14: -2
A15: 43800 | B15: -19.2 | C15: -18.3 | D15: -0.7
A16: 43831 | B16: -14.9 | C16: -15.2 | D16: 0.3
A17: 43862 | B17: -11.7 | C17: -12.8 | D17: 0.9
... A19: 43922 | B19: -5.4 | C19: -5.9 | D19: 0.5
A20: 43952 | B20: -3.4 | C20: -4.1 | D20: 0.6 | G20: =IF(Content!$E$1=1,G21,G22) -> Джерело: МВФ, національні статистичні агенції, розрахунки НБУ.
A21: 43983 | B21: -2.7 | C21: -2.8 | D21: 0.1 | G21: Джерело: МВФ, національні статистичні агенції, розрахунки НБУ.
A22: 44013 | B22: 2.9 | C22: 2.8 | D22: 0.1 | G22: Source: IMF, national statistical offices, NBU staff estimates.
A23: 44044 | B23: 7.1 | C23: 7.2 | D23: -0.1
A24: 44075 | B24: 10.6 | C24: 10.5 | D24: 0.1
A25: 44105 | B25: 9.8 | C25: 10 | D25: -0.2
A26: 44136 | B26: 10.8 | C26: 12.1 | D26: -1.4
A27: 44166 | B27: 13.8 | C27: 15.9 | D27: -2.5
A28: 44197 | B28: 10.5 | C28: 13.4 | D28: -3.3
A29: 44228 | B29: 9.1 | C29: 12.9 | D29: -4.4
A30: 44256 | B30: 1.9 | C30: 6.5 | D30: -4.9
A31: 44287 | B31: 2.8 | C31: 6.9 | D31: -4.4
A32: 44317 | B32: 3.1 | C32: 7.7 | D32: -5
A33: 44348 | B33: -0.6 | C33: 4.1 | D33: -4.9
A34: 44378 | B34: -5.6 | C34: -0.3 | D34: -5.3
... A93: 46174 | B93: 4.7 | C93: 6.8 | D93: -2.2

Sheet 3.9
A1: << | B1: =IF(Content!$E$1=1,B2,B3) -> Експорт продтоварів | C1: =IF(Content!$E$1=1,C2,C3) -> Експорт продукції ГМК | D1: =IF(Content!$E$1=1,D2,D3) -> Експорт інших товарів та послуг | E1: =IF(Content!$E$1=1,E2,E3) -> Грошові перекази | F1: =IF(Content!$E$1=1,F2,F3) -> Торгові кредити | G1: =IF(Content!$E$1=1,G2,G3) -> Гранти | H1: =IF(Content!$E$1=1,H2,H3) -> Борг. залучення держ. сектору | K1: =IF(Content!$E$1=1,K2,K3) -> Основні компоненти валютних надходжень у країну, млрд дол.
B2: Експорт продтоварів | C2: Експорт продукції ГМК | D2: Експорт інших товарів та послуг | E2: Грошові перекази | F2: Торгові кредити | G2: Гранти | H2: Борг. залучення держ. сектору | K2: Основні компоненти валютних надходжень у країну, млрд дол.
B3: Exports of foods | C3: Exports of ores and metal. products | D3: Exports of other goods and services | E3: Remittances | F3: Trade credits | G3: Grants | H3: Public sector debt inflows | K3: Key components of FX inflows to Ukraine, USD billions
A4: I.20 | B4: 5.6 | C4: 3.2 | D4: 6.5 | E4: 2.9 | F4: 0.9 | G4: 0 | H4: 2.3 | P4: I.20
A5: II.20 | B5: 4.6 | C5: 3.1 | D5: 5.6 | E5: 2.7 | F5: 0.4 | G5: 0 | H5: 3
A6: III.20 | B6: 5.2 | C6: 3.2 | D6: 6.6 | E6: 3.1 | F6: 0.9 | G6: 0 | H6: 2.5 | P6: III.20
A7: IV.20 | B7: 6.7 | C7: 3.6 | D7: 7.1 | E7: 3.3 | F7: 0.9 | G7: 0 | H7: 2.8
A8: I.21 | B8: 5.2 | C8: 4.8 | D8: 6.5 | E8: 3.4 | F8: 0.9 | G8: 0 | H8: 1.1 | P8: I.21
A9: II.21 | B9: 5.6 | C9: 6.2 | D9: 7.6 | E9: 3.5 | F9: 0.1 | G9: 0 | H9: 2.5
A10: III.21 | B10: 7 | C10: 6.7 | D10: 8.4 | E10: 3.5 | F10: 0.2 | G10: 0 | H10: 3.7 | P10: III.21
A11: IV.21 | B11: 9.8 | C11: 5.2 | D11: 9 | E11: 3.7 | F11: 0.5 | G11: 0 | H11: 3.1
A12: I.22 | B12: 6.4 | C12: 4 | D12: 7 | E12: 3.3 | F12: 0.8 | G12: 0.1 | H12: 3.5 | P12: I.22
A13: II.22 | B13: 3.6 | C13: 2.2 | D13: 5.9 | E13: 3.1 | F13: 0 | G13: 2.6 | H13: 4.1
A14: III.22 | B14: 5.9 | C14: 1.6 | D14: 6.1 | E14: 3.1 | F14: 0 | G14: 7.8 | H14: 2.3 | P14: III.22
A15: IV.22 | B15: 7.4 | C15: 1.2 | D15: 6.3 | E15: 3.1 | F15: 0.1 | G15: 4.1 | H15: 8.9
A16: I.23 | B16: 6.8 | C16: 1.3 | D16: 5.8 | E16: 2.9 | F16: 2.3 | G16: 3.7 | H16: 8.1 | P16: I.23
A17: II.23 | B17: 5.1 | C17: 1.7 | D17: 6.2 | E17: 2.8 | F17: 0.2 | G17: 3.7 | H17: 9.9 | K17: =IF(Content!$E$1=1,K21,K22) -> Джерело: НБУ.
A18: III.23 | B18: 4.3 | C18: 1.4 | D18: 5.8 | E18: 2.8 | F18: 0.5 | G18: 2.6 | H18: 7 | P18: III.23
A19: IV.23 | B19: 5.8 | C19: 1.3 | D19: 6.1 | E19: 2.8 | F19: 0.2 | G19: 1.9 | H19: 8.7
A20: I.24 | B20: 6.5 | C20: 2 | D20: 5.9 | E20: 2.5 | F20: 1.5 | G20: 1.1 | H20: 9.7 | P20: I.24
A21: II.24 | B21: 5.9 | C21: 1.8 | D21: 6.2 | E21: 2.4 | F21: 1.1 | G21: 0 | H21: 4 | K21: Джерело: НБУ.
A22: III.24 | B22: 5.5 | C22: 1.9 | D22: 6.1 | E22: 2.3 | F22: 1.9 | G22: 5.6 | H22: 5.5 | K22: Source: NBU. | P22: III.24
A23: IV.24 | B23: 6.7 | C23: 1.7 | D23: 6.4 | E23: 2.2 | F23: 1 | G23: 4.6 | H23: 13.4
A24: I.25 | B24: 5.8 | C24: 1.8 | D24: 5.6 | E24: 1.9 | F24: 2 | G24: 2.4 | H24: 7.6 | P24: I.25
A25: II.25 | B25: 5.5 | C25: 1.8 | D25: 6.1 | E25: 2 | F25: 2 | G25: 2.7 | H25: 10.1
A26: III.25 | B26: 5 | C26: 1.7 | D26: 6.3 | E26: 2 | F26: 1.7 | G26: 2.4 | H26: 8.9 | P26: III.25
A27: IV.25 | B27: 6.3 | C27: 1.8 | D27: 6.5 | E27: 1.9 | F27: 1.2 | G27: 5.2 | H27: 19
A28: I.26 | B28: 6.3 | C28: 1.4 | D28: 5.8 | E28: 1.8 | F28: 3.8 | G28: 5.3 | H28: 1.9
A29: II.26 | B29: 6.2 | C29: 1.7 | D29: 6.5 | E29: 1.9 | F29: 2.7 | G29: 7.6 | H29: 5.7 | P29: II.26

Sheet 3.10
A1: << | B1: =IF(Content!$E$1=1,B2,B3) -> Енергетичний імпорт | C1: =IF(Content!$E$1=1,C2,C3) -> Імпорт машинобудування | D1: =IF(Content!$E$1=1,D2,D3) -> Витрати мігрантів за кордоном | E1: =IF(Content!$E$1=1,E2,E3) -> Імпорт інших товарів та послуг* | F1: =IF(Content!$E$1=1,F2,F3) -> Готівка поза банками | G1: =IF(Content!$E$1=1,G2,G3) -> Торгові кредити | H1: =IF(Content!$E$1=1,H2,H3) -> Виплати держ. сектору | K1: =IF(Content!$E$1=1,K2,K3) -> Основні компоненти відпливу валюти, млрд дол.
B2: Енергетичний імпорт | C2: Імпорт машинобудування | D2: Витрати мігрантів за кордоном | E2: Імпорт інших товарів та послуг* | F2: Готівка поза банками | G2: Торгові кредити | H2: Виплати держ. сектору | K2: Основні компоненти відпливу валюти, млрд дол.
B3: Energy imports | C3: Machinery imports | D3: Migrants expenses abroad | E3: Imports of other goods and services* | F3: FX cash outside banks | G3: Trade credits | H3: Public sector repayments | K3: Key components of FX outflows, USD billions
A4: I.20 | B4: 2.4 | C4: 3.9 | D4: 1.7 | E4: 8.7 | F4: 0.8 | G4: 0.2 | H4: 3.4 | P4: I.20
A5: II.20 | B5: 1.6 | C5: 3.5 | D5: 0.7 | E5: 7 | F5: 1.4 | G5: 0.1 | H5: 3.1
A6: III.20 | B6: 1.7 | C6: 4.7 | D6: 1.2 | E6: 8.7 | F6: 0.9 | G6: 0 | H6: 5.7 | P6: III.20
A7: IV.20 | B7: 2.2 | C7: 5.4 | D7: 1 | E7: 10.1 | F7: 1.5 | G7: 0.2 | H7: 1.7
A8: I.21 | B8: 2.5 | C8: 4.4 | D8: 1.2 | E8: 9.4 | F8: 1.3 | G8: 0.6 | H8: 2.9 | P8: I.21
A9: II.21 | B9: 2.3 | C9: 5.3 | D9: 1.5 | E9: 9.9 | F9: 0.6 | G9: 1.5 | H9: 1.6 | R9: Туча
A10: III.21 | B10: 4.1 | C10: 5.6 | D10: 1.9 | E10: 11.5 | F10: 1.2 | G10: 0.2 | H10: 5 | P10: III.21
A11: IV.21 | B11: 5 | C11: 6.5 | D11: 1.6 | E11: 13.3 | F11: 1.6 | G11: 0.4 | H11: 2.6
A12: I.22 | B12: 3.8 | C12: 3.4 | D12: 3.1 | E12: 8.3 | F12: 2.6 | G12: 4.3 | H12: 3.2 | P12: I.22
A13: II.22 | B13: 2.4 | C13: 3 | D13: 5.5 | E13: 6.7 | F13: 2.5 | G13: 4.8 | H13: 1.4
A14: III.22 | B14: 3.2 | C14: 3.6 | D14: 5.4 | E14: 8.7 | F14: 2.4 | G14: 2.7 | H14: 1.8 | P14: III.22
A15: IV.22 | B15: 3.3 | C15: 4.8 | D15: 5.7 | E15: 10.6 | F15: 2.1 | G15: 1.5 | H15: 1.9
A16: I.23 | B16: 3.8 | C16: 4.3 | D16: 5.3 | E16: 9.7 | F16: 3 | G16: 0.3 | H16: 2.4 | K16: =IF(Content!$E$1=1,K26,K27) -> * Без урахування гуманітарної допомоги. | P16: I.23
A17: II.23 | B17: 2.1 | C17: 4.4 | D17: 3.5 | E17: 10.2 | F17: 2.7 | G17: 0.3 | H17: 2.3 | K17: =IF(Content!$E$1=1,K28,K29) -> Джерело: НБУ.
A18: III.23 | B18: 2.1 | C18: 5.2 | D18: 3.5 | E18: 10.7 | F18: 1.8 | G18: 0.7 | H18: 2.5 | P18: III.23
A19: IV.23 | B19: 2.4 | C19: 5.8 | D19: 3.4 | E19: 11.2 | F19: 3.4 | G19: 1 | H19: 2
A20: I.24 | B20: 2 | C20: 5.2 | D20: 3.3 | E20: 11.3 | F20: 3.8 | G20: 0.4 | H20: 2.4 | P20: I.24
A21: II.24 | B21: 2.2 | C21: 6 | D21: 3.3 | E21: 11.7 | F21: 3.6 | G21: 0.5 | H21: 2.6
A22: III.24 | B22: 2.5 | C22: 6.1 | D22: 3.4 | E22: 11.8 | F22: 3.6 | G22: 0 | H22: 7.8 | P22: III.24
A23: IV.24 | B23: 2.1 | C23: 7.2 | D23: 3.1 | E23: 13.1 | F23: 4.5 | G23: 0.8 | H23: 2.3
A24: I.25 | B24: 2.6 | C24: 6.7 | D24: 2.8 | E24: 12.5 | F24: 3.4 | G24: 0.2 | H24: 2.8 | P24: I.25
A25: II.25 | B25: 2.6 | C25: 8.1 | D25: 2.9 | E25: 13.1 | F25: 1.1 | G25: 0.3 | H25: 2.1
A26: III.25 | B26: 2.5 | C26: 8.8 | D26: 3 | E26: 14 | F26: 1.1 | G26: 0.4 | H26: 2.3 | K26: * Без урахування гуманітарної допомоги. | P26: III.25
A27: IV.25 | B27: 2.9 | C27: 10.1 | D27: 3 | E27: 16 | F27: 2.3 | G27: 0 | H27: 5.7 | K27: * Excluding humanitarian aid.
A28: I.26 | B28: 4.1 | C28: 9.2 | D28: 2.8 | E28: 14.5 | F28: 2.6 | G28: 0 | H28: 2.1 | K28: Джерело: НБУ.
A29: II.26 | B29: 3.3 | C29: 11.4 | D29: 2.7 | E29: 13.9 | F29: 1.3 | G29: 0 | H29: 2.1 | K29: Source: NBU. | P29: II.26

Sheet 3.11
A1: << | B1: =IF(Content!$E$1=1,B2,B3) -> Інтервенції НБУ (на дату валютування) | C1: =IF(Content!$E$1=1,C2,C3) -> Сальдо операцій клієнтів | D1: =IF(Content!$E$1=1,D2,D3) -> Частка операцій без НБУ (п. ш.), % | G1: =IF(Content!$E$1=1,G2,G3) -> Чиста купівля клієнтами банків та сальдо продажу іноземної валюти НБУ, млрд дол.
B2: Інтервенції НБУ (на дату валютування) | C2: Сальдо операцій клієнтів | D2: Частка операцій без НБУ (п. ш.), % | G2: Чиста купівля клієнтами банків та сальдо продажу іноземної валюти НБУ, млрд дол.
B3: NBU interventions (value date) | C3: Net customer transactions | D3: Share of transactions without the NBU (RHS), % | G3: Net FX purchases by banks' clients and net FX sales by the NBU, USD bn
A4: 45658 | B4: 3.7 | C4: 3.1 | D4: 38.5 | F4: 45658
A5: 45689 | B5: 3 | C5: 2.5 | D5: 47.5
A6: 45717 | B6: 2.6 | C6: 2 | D6: 53.7
A7: 45748 | B7: 2.2 | C7: 1.8 | D7: 57.9
A8: 45778 | B8: 3 | C8: 2.2 | D8: 51.5
A9: 45809 | B9: 3 | C9: 2.3 | D9: 52.7
A10: 45839 | B10: 3.5 | C10: 2.7 | D10: 52.2 | F10: 45839
A11: 45870 | B11: 2.7 | C11: 2 | D11: 55.1
A12: 45901 | B12: 2.3 | C12: 1.6 | D12: 65.5
A13: 45931 | B13: 2.8 | C13: 2.2 | D13: 57.8
A14: 45962 | B14: 2.7 | C14: 2.1 | D14: 54.8
A15: 45992 | B15: 4.7 | C15: 3.7 | D15: 49
A16: 46023 | B16: 3.7 | C16: 3.1 | D16: 47.7 | F16: 46023
A17: 46054 | B17: 3 | C17: 2.4 | D17: 51.4
A18: 46082 | B18: 4.8 | C18: 3.9 | D18: 42.5 | G18: =IF(Content!$E$1=1,G22,G23) -> Джерело: НБУ.
A19: 46113 | B19: 3.6 | C19: 2.9 | D19: 50.8
A20: 46143 | B20: 3.1 | C20: 2.5 | D20: 55.2
A21: 46174 | B21: 5.1 | C21: 4.3 | D21: 41
A22: 46204 | B22: 4.8 | C22: 4 | D22: 43.1 | F22: 46204 | G22: Джерело: НБУ.
G23: Source: NBU.
F34: =A34 -> 0
F40: =A40 -> 0

Sheet 3.12
A1: << | B1: =IF(Content!$E$1=1,B2,B3) -> Банки | C1: =IF(Content!$E$1=1,C2,C3) -> Підприємства | D1: =IF(Content!$E$1=1,D2,D3) -> Домогосподарства | E1: =IF(Content!$E$1=1,E2,E3) -> Фінансові аналітики | H1: =IF(Content!$E$1=1,H2,H3) -> Курсові очікування на наступні 12 місяців, грн/дол.
B2: Банки | C2: Підприємства | D2: Домогосподарства | E2: Фінансові аналітики | H2: Курсові очікування на наступні 12 місяців, грн/дол.
B3: Banks | C3: Corporates | D3: Households | E3: Financial analysts | H3: 12-month-ahead exchange rate expectations, UAH per USD
A4: 45292 | B4: 41.31 | C4: #N/A | D4: 40.13 | E4: 40.29 | G4: 01.24
A5: 45323 | B5: #N/A | C5: 40.44 | D5: 39.84 | E5: #N/A
A6: 45352 | B6: #N/A | C6: #N/A | D6: 39.8 | E6: 41.13
A7: 45383 | B7: 41.69 | C7: #N/A | D7: 40.73 | E7: 41.81
A8: 45413 | B8: #N/A | C8: 41.61 | D8: 41.03 | E8: #N/A
A9: 45444 | B9: #N/A | C9: #N/A | D9: 42.51 | E9: 42.8
A10: 45474 | B10: 43.15 | C10: #N/A | D10: 43.5 | E10: 43.36 | G10: 07.24
A11: 45505 | B11: #N/A | C11: 43.72 | D11: 43.25 | E11: #N/A
A12: 45536 | B12: #N/A | C12: #N/A | D12: 44.03 | E12: 43.98
A13: 45566 | B13: 44.92 | C13: #N/A | D13: 44.54 | E13: 44.08
A14: 45597 | B14: #N/A | C14: 44.42 | D14: 44.1 | E14: #N/A
A15: 45627 | B15: #N/A | C15: #N/A | D15: 44.11 | E15: 44.83
A16: 45658 | B16: 45.31 | C16: #N/A | D16: 44.53 | E16: 45.19 | G16: 01.25
A17: 45689 | B17: #N/A | C17: 44.23 | D17: 44.01 | E17: 45.27
A18: 45717 | B18: #N/A | C18: #N/A | D18: 43.36 | E18: #N/A | H18: =IF(Content!$E$1=1,I20,I21) -> Джерело: НБУ, Info Sapiens.
A19: 45748 | B19: 45.29 | C19: #N/A | D19: 42.5 | E19: 44.75
A20: 45778 | B20: #N/A | C20: 43.84 | D20: 43.1 | E20: 44.47 | I20: Джерело: НБУ, Info Sapiens.
A21: 45809 | B21: #N/A | C21: #N/A | D21: 43.69 | E21: #N/A | I21: Source: NBU, Info Sapiens.
A22: 45839 | B22: 45.29 | C22: #N/A | D22: 43.75 | E22: 44.74 | G22: 07.25
A23: 45870 | B23: #N/A | C23: 44.11 | D23: 43.73 | E23: #N/A
A24: 45901 | B24: #N/A | C24: #N/A | D24: 43.75 | E24: 44.45
A25: 45931 | B25: 44.94 | C25: #N/A | D25: 43.83 | E25: 44.05
A26: 45962 | B26: #N/A | C26: 44.27 | D26: 43.91 | E26: #N/A
A27: 45992 | B27: #N/A | C27: #N/A | D27: 44.35 | E27: 45.02
A28: 46023 | B28: 45.12 | C28: #N/A | D28: 44.86 | E28: 45.23 | G28: 01.26
A29: 46054 | B29: #N/A | C29: 45 | D29: 45.17 | E29: #N/A
A30: 46082 | B30: #N/A | C30: #N/A | D30: 45.68 | E30: 45.8
A31: 46113 | B31: 45.69 | C31: #N/A | D31: 46.22 | E31: 45.84
A32: 46143 | B32: #N/A | C32: 46.12 | D32: 46.58 | E32: #N/A
A33: 46174 | B33: #N/A | C33: #N/A | D33: 47.14 | E33: 46.24
A34: 46204 | B34: 46.52 | C34: #N/A | D34: 46.39 | E34: 47.1 | G34: 07.26
G46: 07.25

Sheet 3.13
A1: << | B1: =IF(Content!$E$1=1,B2,B3) -> Поточний рахунок | C1: =IF(Content!$E$1=1,C2,C3) -> ПІІ | D1: =IF(Content!$E$1=1,D2,D3) -> ERA (кредити) | E1: =IF(Content!$E$1=1,E2,E3) -> Ukraine Facility | F1: =IF(Content!$E$1=1,F2,F3) -> MFA | G1: =IF(Content!$E$1=1,G2,G3) -> Очікувані позики | H1: =IF(Content!$E$1=1,H2,H3) -> Широкий базовий баланс | I1: =IF(Content!$E$1=1,I2,I3) -> Широкий базовий баланс, попередній прогноз | L1: =IF(Content!$E$1=1,L2,L3) -> Широкий базовий баланс, млрд дол.
B2: Поточний рахунок | C2: ПІІ | D2: ERA (кредити) | E2: Ukraine Facility | F2: MFA | G2: Очікувані позики | H2: Широкий базовий баланс | I2: Широкий базовий баланс, попередній прогноз | L2: Широкий базовий баланс, млрд дол.
B3: Current account | C3: FDI | D3: ERA (loans) | E3: Ukraine Facility | F3: MFA | G3: Expected loans | H3: Broad basic balance | I3: Broad basic balance, previous forecast | L3: Broad basic balance, USD billions
A4: 2022 | B4: 6.2 | C4: 0.1 | D4: 0 | E4: 0 | F4: 7.3 | G4: 0 | H4: 13.6 | I4: 13.6 | K4: 2022
A5: 2023 | B5: -10.8 | C5: 4.5 | D5: 0 | E5: 0 | F5: 19.5 | G5: 0 | H5: 13.2 | I5: 13.2 | K5: 2023
A6: 2024 | B6: -16.9 | C6: 4 | D6: 0 | E6: 14.1 | F6: 0 | G6: 0 | H6: 1.2 | I6: 1.2 | K6: 2024 | T6: =IF(Content!$E$1=1,T7,T8) -> Широкий базовий баланс
A7: 2025 | B7: -33.4 | C7: 1.6 | D7: 25.9 | E7: 11.4 | F7: 0 | G7: 0 | H7: 5.5 | I7: 5.6 | K7: 2025 | T7: Широкий базовий баланс
A8: 2026 | B8: -16.1 | C8: 2.8 | D8: 0 | E8: 0 | F8: 0 | G8: 9.8 | H8: -3.5 | I8: -7.7 | K8: 2026
A9: 2027 | B9: -11.9 | C9: 6.5 | D9: 0 | E9: 0 | F9: 0 | G9: 2.3 | H9: -3.1 | I9: -4.3 | K9: 2027
A10: 2028 | B10: -44.9 | C10: 8.8 | D10: 0 | E10: 0 | F10: 0 | G10: 11.9 | H10: -24.2 | I10: -15 | K10: 2028 | S10: Покидько
K11: I.25
K13: III.25
K15: I.26
L16: =IF(Content!$E$1=1,L18,L19) -> Джерело: розрахунки НБУ.
K17: III.26
L18: Джерело: розрахунки НБУ.
K19: I.27 | L19: Source: NBU staff estimates.
K22: IV.27

Sheet 3.14
A1: << | B1: =IF(Content!$E$1=1,B2,B3) -> Міжнародні резерви, млрд дол. | C1: =IF(Content!$E$1=1,C2,C3) -> У % до композитного критерію МВФ (п. ш.) | F1: =IF(Content!$E$1=1,F2,F3) -> Валові міжнародні резерви | O1: =IF(Content!$E$1=1,O2,O3) -> Адекватний рівень 100-150%
B2: Міжнародні резерви, млрд дол. | C2: У % до композитного критерію МВФ (п. ш.) | F2: Валові міжнародні резерви | O2: Адекватний рівень 100-150%
B3: International reserves, USD billions | C3: As a percentage of the IMF composite criterion (RHS) | F3: Gross international reserves | O3: Adequate level 100%-150%
A4: I.24 | B4: 43.8 | C4: 129.4 | E4: I.24
A5: II.24 | B5: 37.9 | C5: 111.4
A6: III.24 | B6: 38.9 | C6: 112.4 | E6: III.24
A7: IV.24 | B7: 43.8 | C7: 121.1
A8: I.25 | B8: 42.4 | C8: 112.4 | E8: I.25
A9: II.25 | B9: 45.1 | C9: 110.7
A10: III.25 | B10: 46.6 | C10: 109.9 | E10: III.25
A11: IV.25 | B11: 57.3 | C11: 126.8
A12: I.26 | B12: 52 | C12: 114.5 | E12: I.26
A13: II.26 | B13: 51.3 | C13: 110.6
A14: III.26 | B14: 53.8 | C14: 114.8 | E14: III.26
A15: IV.26 | B15: 69.7 | C15: 141.7
A16: I.27 | B16: 68.9 | C16: 138.9 | E16: I.27
A17: II.27 | B17: 71.7 | C17: 142.7 | F17: =IF(Content!$E$1=1,F18,F19) -> Джерело: розрахунки НБУ.
A18: III.27 | B18: 72.5 | C18: 142.7 | E18: III.27 | F18: Джерело: розрахунки НБУ.
A19: IV.27 | B19: 73.7 | C19: 142.7 | F19: Source: NBU staff estimates.
A20: I.28 | B20: 71.6 | C20: 135.7 | E20: I.28
A21: II.28 | B21: 72.6 | C21: 133.8
A22: III.28 | B22: 71.9 | C22: 129.2
A23: IV.28 | B23: 70 | C23: 122.8 | E23: IV.28

Sheet 3.15
A1: <<
D2: =IF(Content!$E$1=1,D3,D4) -> 2022 | E2: =IF(Content!$E$1=1,E3,E4) -> 23 | F2: =IF(Content!$E$1=1,F3,F4) -> 24 | G2: =IF(Content!$E$1=1,G3,G4) -> 25 | H2: =IF(Content!$E$1=1,H3,H4) -> 26 | I2: =IF(Content!$E$1=1,I3,I4) -> 27 | J2: =IF(Content!$E$1=1,J3,J4) -> 28 | K2: =IF(Content!$E$1=1,K3,K4) -> 25.I П | L2: =IF(Content!$E$1=1,L3,L4) -> 26.I П | O2: =IF(Content!$E$1=1,O3,O4) -> Фінансування* дефіциту державного бюджету (без урахування грантів у доходах), млрд грн
D3: 2022 | E3: 23 | F3: 24 | G3: 25 | H3: 26 | I3: 27 | J3: 28 | K3: 25.I П | L3: 26.I П | O3: Фінансування* дефіциту державного бюджету (без урахування грантів у доходах), млрд грн
D4: 2022 | E4: 23 | F4: 24 | G4: 25 | H4: 26 | I4: 27 | J4: 28 | K4: 25.Н І | L4: 26.H I | O4: Financing* of the state budget deficit (excluding grants in revenues), UAH billions
A5: =IF(Content!$E$1=1,B5,C5) -> Дефіцит | B5: Дефіцит | C5: Deficit | D5: 1395.53 | E5: 1770.73 | F5: 1833.26 | G5: 2190.5 | H5: 3544.72 | I5: 2866.53 | J5: 1793.51 | K5: 760.91 | L5: 875.08
A6: =IF(Content!$E$1=1,B6,C6) -> Зовнішні залучення | B6: Зовнішні залучення | C6: External borrowings | D6: 565.57 | E6: 1084.88 | F6: 1173.87 | G6: 1745.92 | H6: 3526.55 | I6: 2862.73 | J6: 1788.82 | K6: 584.91 | L6: 206.84
A7: =IF(Content!$E$1=1,B7,C7) -> Грантові кошти | B7: Грантові кошти | C7: Grants | D7: 480.66 | E7: 433.86 | F7: 473.91 | G7: 554.71 | K7: 214.91 | L7: 572
A8: =IF(Content!$E$1=1,B8,C8) -> Інше фінансування | B8: Інше фінансування | C8: Other financing | D8: 54.33 | E8: 69.19 | F8: -70.11 | G8: -202.82 | K8: -13.98 | L8: 92.81
A9: =IF(Content!$E$1=1,B9,C9) -> Внутрішні залучення | B9: Внутрішні залучення | C9: Domestic debt securities | D9: -93.53 | E9: 197.38 | F9: 267.98 | G9: 105.77 | H9: 30.34 | I9: 15.64 | J9: 15.68 | K9: -19.85 | L9: 12.2
A10: =IF(Content!$E$1=1,B10,C10) -> НБУ купівля ОВДП | B10: НБУ купівля ОВДП | C10: Domestic debt securities purchased by the NBU | D10: 388.5 | E10: -14.58 | F10: -12.38 | G10: -13.08 | H10: -12.16 | I10: -11.84 | J10: -11 | K10: -5.08 | L10: -8.76
O19: =IF(Content!$E$1=1,O25,O26) -> * Чисті залучення. Запозичення в гривні містять випуск ОВДП для збільшення статутного капіталу банків, ФГВФО та інших державних підприємств. Дефіцит у 2026‒2028 роках – прогноз НБУ. Сіра заливка охоплює зовнішні залучення, грантові кошти та інше фінансування, зокрема використання залишків коштів на кінець попереднього періоду.
O20: =IF(Content!$E$1=1,O23,O24) -> Джерело: ДКСУ, розрахунки НБУ.
O23: Джерело: ДКСУ, розрахунки НБУ.
O24: Source: STSU, NBU staff estimates.
O25: * Чисті залучення. Запозичення в гривні містять випуск ОВДП для збільшення статутного капіталу банків, ФГВФО та інших державних підприємств. Дефіцит у 2026‒2028 роках – прогноз НБУ. Сіра заливка охоплює зовнішні залучення, грантові кошти та інше фінансування, зокрема використання залишків коштів на кінець попереднього періоду.
O26: * Net borrowing. Hryvnia-denominated borrowings include domestic debt securieties issued to increase the authorized capital of banks, the Deposit Guarantee Fund (DGF), and other state-owned enterprises. Deficit in 2026–2028 reflects the NBU's forecast. The grey color denotes external borrowings, grant funds, and other financing, in particular, the use of relatively large cash balances on gov`t accounts at the end of the previous period.

Sheet 3.16
A1: << | B1: =IF(Content!$E$1=1,B2,B3) -> Погашення (номінальна вартість, без НБУ) | C1: =IF(Content!$E$1=1,C2,C3) -> Залучення (за датою оплати) | D1: =IF(Content!$E$1=1,D2,D3) -> Бенчмарк-ОВДП | E1: =IF(Content!$E$1=1,E2,E3) -> Дохідність, % (п. ш.) | H1: =IF(Content!$E$1=1,H2,H3) -> Первинне розміщення* та погашення гривневих ОВДП, млрд грн
B2: Погашення (номінальна вартість, без НБУ) | C2: Залучення (за датою оплати) | D2: Бенчмарк-ОВДП | E2: Дохідність, % (п. ш.) | H2: Первинне розміщення* та погашення гривневих ОВДП, млрд грн
B3: Redemption (nominal value, excl. NBU) | C3: Placement (payment date) | D3: Benchmark securities | E3: YTM, % (RHS) | H3: Primary placement* and redemption of hryvnia domestic government debt securities, UAH bn
A4: 44562 | B4: 11 | G4: 44562
C5: 6.8 | E5: 12.1
A6: 44593 | B6: 29.5
C7: 5.2 | E7: 11.6
A8: 44621 | B8: 17.8 | G8: 44621
C9: 29.3 | E9: 10.9
A10: 44652 | B10: 19.3
C11: 20.3 | E11: 10.7
A12: 44682 | B12: 32.3 | G12: 44682
C13: 27.2 | E13: 10.3
A14: 44713 | B14: 20.9
C15: 8.8 | E15: 9.3
A16: 44743 | B16: 21.9 | G16: 44743
C17: 6.5 | E17: 14.5
A18: 44774 | B18: 35.3
C19: 7.2 | E19: 13.8
A20: 44805 | B20: 1.7 | G20: 44805 | H20: =IF(Content!$E$1=1,H22,H23) -> * За результатами проведення аукціонів з розміщення ОВДП до відображення цінових ефектів унаслідок дорозміщення цінних паперів. Не містять ОВДП, випущені у 2022, 2024 та 2025 роках для докапіталізації ПрАТ "Укрфінжитло", та викуп НБУ військових ОВДП.
C21: 0.9 | E21: 14.2 | H21: =IF(Content!$E$1=1,H24,H25) -> Джерело: розрахунки НБУ.
A22: 44835 | B22: 15.8 | H22: * За результатами проведення аукціонів з розміщення ОВДП до відображення цінових ефектів унаслідок дорозміщення цінних паперів. Не містять ОВДП, випущені у 2022, 2024 та 2025 роках для докапіталізації ПрАТ "Укрфінжитло", та викуп НБУ військових ОВДП.
C23: 6.9 | E23: 15.9 | H23: * According to the results of auctions for the placement of domestic debt securities before reflecting the price effects due to the additional placement of securities. Excluding hryvnia domestic debt securities issued in 2022, 2024 and 2025 for recapitalization of PJSC "Ukrfinzhytlo" and purchase of war bonds by the NBU.
A24: 44866 | B24: 34 | G24: 44866 | H24: Джерело: розрахунки НБУ.
C25: 21.7 | E25: 14.8 | H25: Source: NBU staff estimates.
A26: 44896 | B26: 14.4
C27: 23.6 | E27: 17.3
A28: 44927 | B28: 9.1 | G28: 44927
C29: 7.9 | D29: 32.8 | E29: 18.8
A30: 44958 | B30: 12.1
C31: 1.1 | D31: 30.8 | E31: 19
A32: 44986 | B32: 27.1 | G32: 44986
C33: 4.3 | D33: 33.8 | E33: 19.6
A34: 45017 | B34: 30.4
C35: 12.1 | D35: 13.1 | E35: 19.3
A36: 45047 | B36: 26.1 | G36: 45047
C37: 10.9 | D37: 19.3 | E37: 19.3
A38: 45078 | B38: 22
C39: 22 | D39: 7.4 | E39: 18.9
A40: 45108 | B40: 14.9 | G40: 45108
C41: 17.8 | D41: 14 | E41: 19
A42: 45139 | B42: 21.3
C43: 5.9 | D43: 20.5 | E43: 19.122062
A44: 45170 | B44: 16.1 | G44: 45170
C45: 13.8 | D45: 10.1 | E45: 18.622314
A46: 45200 | B46: 4.3
C47: 23.9 | D47: 20.2 | E47: 18.421117
A48: 45231 | B48: 32.8 | G48: 45231
C49: 31.1 | D49: 15.8 | E49: 17.783241
A50: 45261 | B50: 0
C51: 26.9 | D51: 6.1 | E51: 17.164466
A52: 45292 | B52: 0 | G52: 45292
C53: 9.8 | D53: 3.5 | E53: 17.748304
A54: 45323 | B54: 10.2
C55: 21.4 | D55: 0.1 | E55: 17.325154
A56: 45352 | B56: 15.9 | G56: 45352
C57: 34.2 | D57: 0 | E57: 17.193379
A58: 45383 | B58: 0
C59: 26.6 | D59: 0 | E59: 16.855912
A60: 45413 | B60: 44 | G60: 45413
C61: 43.4 | D61: 0 | E61: 16.121955
A62: 45444 | B62: 33.6
C63: 38.4 | D63: 0 | E63: 15.584122
A64: 45474 | B64: 10.2 | G64: 45474
C65: 26.4 | D65: 0 | E65: 15.084883
A66: 45505 | B66: 20
C67: 6 | D67: 23.1 | E67: 16.149575
A68: 45536 | B68: 9.3 | G68: 45536
C69: 6.5 | D69: 41.1 | E69: 16.01897
A70: 45566 | B70: 44.8
C71: 62.7 | D71: 20.8 | E71: 15.595461
A72: 45597 | B72: 32.2 | G72: 45597
C73: 46.8 | D73: 26 | E73: 15.357335
A74: 45627 | B74: 25.2
C75: 45.4 | D75: 15.6 | E75: 15.648848
A76: 45658 | B76: 19.4 | G76: 45658
C77: 7.2 | D77: 22.3 | E77: 14.893172
A78: 45689 | B78: 40.1
C79: 6.1 | D79: 10.1 | E79: 16.029838
A80: 45717 | B80: 23.8 | G80: 45717
C81: 20.2 | D81: 10.2 | E81: 16.388919
A82: 45748 | B82: 48.6
C83: 26.3 | D83: 21.3 | E83: 16.23405
A84: 45778 | B84: 10.5 | G84: 45778
C85: 24 | D85: 10.1 | E85: 16.226038
A86: 45809 | B86: 48.5
C87: 28.6 | D87: 8.5 | E87: 16.371477
A88: 45839 | B88: 18.9 | G88: 45839
C89: 34.7 | D89: 20.3 | E89: 16.176982
A90: 45870 | B90: 12.1
C91: 12.1 | D91: 15.2 | E91: 15.757193
A92: 45901 | B92: 18.8 | G92: 45901
C93: 20.8 | D93: 5.1 | E93: 16.776596
A94: 45931 | B94: 58.8
C95: 53 | D95: 20.7 | E95: 16.409083
A96: 45962 | B96: 15.6 | G96: =A96 -> 45962
C97: 26.3 | D97: 0 | E97: 17.155362
A98: 45992 | B98: 5.4
C99: 27.1 | D99: 0 | E99: 17.153756
A100: 46023 | B100: 40.9 | G100: =A100 -> 46023
...

Sheet 3.17
A1: << | B1: =IF(Content!$E$1=1,B2,B3) -> Державний та гарантований державою борг (п. ш.) | C1: =IF(Content!$E$1=1,C2,C3) -> Дефіцит СЗДУ | D1: =IF(Content!$E$1=1,D2,D3) -> Фінансування НАК "Нафтогаз" | E1: =IF(Content!$E$1=1,E2,E3) -> Рекапіталізація банків та інше | H1: =IF(Content!$E$1=1,H2,H3) -> Широкий дефіцит СЗДУ й державний та гарантований державою борг, % ВВП
B2: Державний та гарантований державою борг (п. ш.) | C2: Дефіцит СЗДУ | D2: Фінансування НАК "Нафтогаз" | E2: Рекапіталізація банків та інше | H2: Широкий дефіцит СЗДУ й державний та гарантований державою борг, % ВВП
B3: Public and publicly guaranteed debt (RHS) | C3: General government deficit | D3: Naftogaz financing | E3: Bank recapitalization & other | H3: Broad public sector deficit, public and publicly guaranteed debt, % of GDP
A4: 14 | B4: 69.4 | C4: 4.4 | D4: 5.5 | E4: 3.4
A5: 15 | B5: 79 | C5: 0.9 | D5: 1 | E5: 2.3
A6: 16 | B6: 80.9 | C6: 2.1 | D6: 0 | E6: 5.4
A7: 17 | B7: 71.8 | C7: 1.2 | D7: 0 | E7: 2.4
A8: 18 | B8: 60.9 | C8: 2.1 | D8: 0 | E8: 0
A9: 19 | B9: 50.2 | C9: 2.2 | D9: 0 | E9: 0
A10: 20 | B10: 60.4 | C10: 5.8 | D10: 0 | E10: 0.2
A11: 21 | B11: 49 | C11: 3.8 | D11: 0 | E11: 0.4
A12: 22 | B12: 77.7 | C12: 15.6 | D12: 0 | E12: 0.6
A13: 23 | B13: 83.3 | C13: 20.1 | D13: 0 | E13: 0
A14: 24 | B14: 91.1 | C14: 17.6 | D14: 0 | E14: 0.3
A15: 25 | B15: 101.3 | C15: 19 | D15: 0 | E15: 0
... A18: 28 | B18: 87.4 | C18: 11.1 | D18: 0 | E18: 0
H19: =IF(Content!$E$1=1,H20,H21) -> Джерело: МВФ, ДКСУ, МФУ, ДССУ, розрахунки НБУ.
H20: Джерело: МВФ, ДКСУ, МФУ, ДССУ, розрахунки НБУ.
H21: Source: IMF, STSU, MFU, SSSU, NBU staff estimates.

Sheet 3.18
A1: << | B1: =IF(Content!$E$1=1,B2,B3) -> Номінальна ставка | C1: =IF(Content!$E$1=1,C2,C3) -> Попередній прогноз (Квітень 2026) | D1: =IF(Content!$E$1=1,D2,D3) -> Реальна ставка* | E1: =IF(Content!$E$1=1,E2,E3) -> Попередній прогноз (Квітень 2026) | F1: =IF(Content!$E$1=1,F2,F3) -> Реальна ставка** | I1: =IF(Content!$E$1=1,I2,I3) -> Облікова ставка, у середньому за квартал %
B2: Номінальна ставка | C2: Попередній прогноз (Квітень 2026) | D2: Реальна ставка* | E2: Попередній прогноз (Квітень 2026) | F2: Реальна ставка** | I2: Облікова ставка, у середньому за квартал %
B3: Nominal rate | C3: Previous forecast (April 2026) | D3: Real rate* | E3: Previous forecast (April 2026) | F3: Real rate** | I3: Key policy rate, quaterly average %
A4: I.18 | B4: 15.9 | D4: 5 | F4: 6.8
B5: 17 | D5: 10.7 | F5: 8.6
B6: 17.6 | D6: 11.7 | F6: 9.1
B7: 18 | D7: 9.4 | F7: 10
A8: I.19 | B8: 18 | D8: 9.5 | F8: 10.7
B9: 17.6 | D9: 11.7 | F9: 10.5
B10: 17 | D10: 12.8 | F10: 9.9
B11: 15.3 | D11: 12.2 | F11: 9.1
A12: I.20 | B12: 11.6 | D12: 9.5 | F12: 6.1
B13: 8.1 | D13: 6.8 | F13: 1.8
B14: 6 | D14: 0.6 | F14: 0.1
B15: 6 | D15: -1.1 | F15: -0.4
A16: I.21 | B16: 6.1 | D16: -3.6 | F16: -0.1
B17: 7.3 | D17: -1.9 | F17: 0.9 | I17: =IF(Content!$E$1=1,I21,I22) -> * Дефльована на модельні очікування (КПМ+).
B18: 8 | D18: 0.5 | F18: 1.8 | I18: =IF(Content!$E$1=1,I23,I24) -> ** Дефльована на очікування фінансових аналітиків.
B19: 8.6 | D19: 1.7 | F19: 1.9 | I19: =IF(Content!$E$1=1,I25,I26) -> Джерело: розрахунки НБУ.
A20: I.22 | B20: 9.8 | C20: 9.8 | D20: 0.4 | E20: 0.4 | F20: -2.1
B21: 14.7 | C21: 14.7 | D21: -1.2 | E21: -1.1 | F21: -2.8 | I21: * Дефльована на модельні очікування (КПМ+).
B22: 25 | C22: 25 | D22: 3.7 | E22: 3.7 | F22: 5.6 | I22: * Deflated by model expectations (QPM+).
B23: 25 | C23: 25 | D23: 9.9 | E23: 10.1 | F23: 5.9 | I23: ** Дефльована на очікування фінансових аналітиків.
A24: I.23 | B24: 25 | C24: 25 | D24: 15.3 | E24: 15.5 | F24: 7.6 | I24: ** Deflated by the expectations of financial analysts.
B25: 25 | C25: 25 | D25: 19.1 | E25: 19 | F25: 10.2 | I25: Джерело: розрахунки НБУ.
B26: 22.5 | C26: 22.5 | D26: 18.9 | E26: 18.8 | F26: 11.3 | I26: Source: NBU staff estimates.
B27: 16.9 | C27: 16.9 | D27: 13.5 | E27: 13.5 | F27: 8.3
A28: I.24 | B28: 14.9 | C28: 14.9 | D28: 10 | E28: 9.8 | F28: 6.8
B29: 13.7 | C29: 13.7 | D29: 7.8 | E29: 7.3 | F29: 6.5
B30: 13 | C30: 13 | D30: 3.5 | E30: 3 | F30: 5.7
B31: 13.1 | C31: 13.1 | D31: 1 | E31: 0.5 | F31: 5.7
A32: I.25 | B32: 14.5 | C32: 14.5 | D32: 3.5 | E32: 3.1 | F32: 6.7
B33: 15.5 | C33: 15.5 | D33: 6.9 | E33: 5.9 | F33: 7.7
B34: 15.5 | C34: 15.5 | D34: 8.5 | E34: 7.7 | F34: 8.2
B35: 15.5 | C35: 15.5 | D35: 10.3 | E35: 9.4 | F35: 8
A36: I.26 | B36: 15.2 | C36: 15.2 | D36: 8.6 | E36: 8.9 | F36: 7.6
B37: 15 | C37: 15 | D37: 6.1 | E37: 6.8 | F37: 7.5
B38: 15.4 | C38: 15 | D38: 7.1 | E38: 6.6
B39: 16 | C39: 15 | D39: 8.2 | E39: 7
A40: I.27 | B40: 16 | C40: 15 | D40: 8.2 | E40: 8.4
B41: 15.3 | C41: 14.3 | D41: 8.5 | E41: 8.4
B42: 14.6 | C42: 13.6 | D42: 8.5 | E42: 7.8
B43: 14 | C43: 13 | D43: 8.2 | E43: 7.1
A44: I.28 | B44: 13.2 | C44: 12.3 | D44: 8.4 | E44: 7.3
B45: 12.4 | C45: 11.7 | D45: 8 | E45: 7.3
B46: 11.7 | C46: 11.2 | D46: 7 | E46: 6.6
B47: 11.2 | C47: 10.7 | D47: 6.2 | E47: 5.7

Sheet В.3.1
A1: << | J1: =IF(Content!$E$1=1,J2,J3) -> Частка політичної комунікації у звітах за різні періоди
A2: Період | D2: Політична комунікація | E2: Середня кількість символів комунікації (тис, п. ш.) | F2: =IF(Content!$E$1=1,E2,E3) -> Середня кількість символів комунікації (тис, п. ш.) | J2: Частка політичної комунікації у звітах за різні періоди
A3: Period | D3: Policy communication | E3: Average number of communication characters (thousands, RHS) | J3: Share of policy communication in reports for different periods
A4: =IF(Content!$E$1=1,A2,A3) -> Період | D4: =IF(Content!$E$1=1,D2,D3) -> Політична комунікація | E4: =IF(Content!$E$1=1,E2,E3) -> Середня кількість символів комунікації (тис, п. ш.)
A5: =IF(Content!$E$1=1,B5,C5) -> Становлення ІТ (I'15 – II'17) | B5: Становлення ІТ (I'15 – II'17) | C5: The emergence of IT (I'15 – II'17) | D5: 10 | E5: 123.6
A6: =IF(Content!$E$1=1,B6,C6) -> Стабілізація інфляції (III'17 – I'20) | B6: Стабілізація інфляції (III'17 – I'20) | C6: Inflation stabilization (III'17 – I'20) | D6: 14.6 | E6: 124.6 | P6: =IF(Content!$E$1=1,P7,P8) -> Середній обсяг комунікації та частка політичної комунікації (%) | Q6: =IF(Content!$E$1=1,Q7,Q8) -> Повномасштабне вторгнення
A7: =IF(Content!$E$1=1,B7,C7) -> COVID-19 (II'20 – I'21) | B7: COVID-19 (II'20 – I'21) | C7: COVID-19 (II'20 – I'21) | D7: 17.2 | E7: 98.2 | P7: Середній обсяг комунікації та частка політичної комунікації (%) | Q7: Повномасштабне вторгнення
A8: =IF(Content!$E$1=1,B8,C8) -> Post-COVID (II'21 – I'22) | B8: Post-COVID (II'21 – I'22) | C8: Post-COVID (II'21 – I'22) | D8: 17.8 | E8: 103.7 | P8: Average volume of communication and share of policy communication (%) | Q8: Full-scale invasion
A9: =IF(Content!$E$1=1,B9,C9) -> Фіксація обмінного курсу (III'22 – III'23) | B9: Фіксація обмінного курсу (III'22 – III'23) | C9: FX peg (III'22 – III'23) | D9: 18.9 | E9: 107.9
A10: =IF(Content!$E$1=1,B10,C10) -> Керована гнучкість курсу (IV'23 – III'24) | B10: Керована гнучкість курсу (IV'23 – III'24) | C10: FX managed flexibility (IV'23 – III'24) | D10: 26.5 | E10: 99.6
A11: =IF(Content!$E$1=1,B11,C11) -> Гнучке ІТ (IV'24 – I'26) | B11: Гнучке ІТ (IV'24 – I'26) | C11: Flexible ІТ (IV'24 – I'26) | D11: 18.6 | E11: 104.7
J19: =IF(Content!$E$1=1,J20,J21) -> Джерело: розрахунки НБУ.
J20: Джерело: розрахунки НБУ.
J21: Source: NBU staff estimates.

Sheet В.3.2
A1: << | M1: =IF(Content!$E$1=1,M2,M3) -> Структура основних цілей та додаткових завдань політичної комунікації за різних періодів
A2: Період | D2: Цінова стабільність | E2: Фінансова стабільність | F2: Економічна активність | M2: Структура основних цілей та додаткових завдань політичної комунікації за різних періодів
A3: Period | D3: Price stability | E3: Financial stability | F3: Economic activity | M3: Structure of the main goals and additional tasks of policy communication in different periods
A4: =IF(Content!$E$1=1,A2,A3) -> Період | D4: =IF(Content!$E$1=1,$D$2,$D$3) -> Цінова стабільність | E4: =IF(Content!$E$1=1,$E$2,$E$3) -> Фінансова стабільність | F4: =IF(Content!$E$1=1,$F$2,$F$3) -> Економічна активність | J4: 1 | K4: =SUM(F4:I4) -> 0
A5: =IF(Content!$E$1=1,B5,C5) -> Становлення ІТ (I'15 – II'17) | B5: Становлення ІТ (I'15 – II'17) | C5: The emergence of IT (I'15 – II'17) | D5: 52.4 | E5: 36.3 | F5: 11.2 | J5: 1 | Y5: =IF(Content!$E$1=1,Y6,Y7) -> Структура основних цілей політичної комунікації (%)
A6: =IF(Content!$E$1=1,B6,C6) -> Стабілізація інфляції (III'17 – I'20) | B6: Стабілізація інфляції (III'17 – I'20) | C6: Inflation stabilization (III'17 – I'20) | D6: 61.3 | E6: 26 | F6: 12.7 | J6: 1 | Y6: Структура основних цілей політичної комунікації (%)
A7: =IF(Content!$E$1=1,B7,C7) -> COVID-19 (II'20 – I'21) | B7: COVID-19 (II'20 – I'21) | C7: COVID-19 (II'20 – I'21) | D7: 27 | E7: 27.9 | F7: 45.1 | J7: 1 | Y7: Structure of the main goals of policy communication (%)
A8: =IF(Content!$E$1=1,B8,C8) -> Post-COVID (II'21 – I'22) | B8: Post-COVID (II'21 – I'22) | C8: Post-COVID (II'21 – I'22) | D8: 65.5 | E8: 14.7 | F8: 19.7 | J8: 1
A9: =IF(Content!$E$1=1,B9,C9) -> Фіксація обмінного курсу (III'22 – III'23) | B9: Фіксація обмінного курсу (III'22 – III'23) | C9: FX peg (III'22 – III'23) | D9: 46.9 | E9: 42 | F9: 11.1 | J9: 1 | Y9: =IF(Content!$E$1=1,Y10,Y11) -> Структура додаткових завдань політичної комунікації (%)
A10: =IF(Content!$E$1=1,B10,C10) -> Керована гнучкість курсу (IV'23 – III'24) | B10: Керована гнучкість курсу (IV'23 – III'24) | C10: FX managed flexibility (IV'23 – III'24) | D10: 39 | E10: 47.6 | F10: 13.4 | J10: 1 | Y10: Структура додаткових завдань політичної комунікації (%)
A11: =IF(Content!$E$1=1,B11,C11) -> Гнучке ІТ (IV'24 – I'26) | B11: Гнучке ІТ (IV'24 – I'26) | C11: Flexible ІТ (IV'24 – I'26) | D11: 53.8 | E11: 34.6 | F11: 11.7 | J11: 1 | Y11: Structure of additional tasks of policy communication (%)
J12: 1
J13: 1 | Y13: =IF(Content!$E$1=1,Y14,Y15) -> Структура додаткових завдань політичної комунікації (продовження, %)
A14: =IF(Content!$E$1=1,A2,A3) -> Період | D14: =IF(Content!$E$1=1,$G$14,$G$15) -> Заякорення очікувань | E14: =IF(Content!$E$1=1,$H$14,$H$15) -> Довіра до гривні | F14: =IF(Content!$E$1=1,$I$14,$I$15) -> Курсова стійкість | G14: Заякорення очікувань | H14: Довіра до гривні | I14: Курсова стійкість | J14: 1 | Y14: Структура додаткових завдань політичної комунікації (продовження, %)
A15: =IF(Content!$E$1=1,B15,C15) -> Становлення ІТ (I'15 – II'17) | B15: Становлення ІТ (I'15 – II'17) | C15: The emergence of IT (I'15 – II'17) | D15: 10.1 | E15: 4.6 | F15: 16.9 | G15: Anchoring expectations | H15: Confidence in the hryvnya | I15: Exchange rate resilience | J15: 1 | Y15: Structure of additional tasks of policy communication (continued, %)
A16: =IF(Content!$E$1=1,B16,C16) -> Стабілізація інфляції (III'17 – I'20) | B16: Стабілізація інфляції (III'17 – I'20) | C16: Inflation stabilization (III'17 – I'20) | D16: 25 | E16: 3.5 | F16: 9.6 | J16: 1
A17: =IF(Content!$E$1=1,B17,C17) -> COVID-19 (II'20 – I'21) | B17: COVID-19 (II'20 – I'21) | C17: COVID-19 (II'20 – I'21) | D17: 17.1 | E17: 1.1 | F17: 11.3 | J17: 1
A18: =IF(Content!$E$1=1,B18,C18) -> Post-COVID (II'21 – I'22) | B18: Post-COVID (II'21 – I'22) | C18: Post-COVID (II'21 – I'22) | D18: 31.9 | E18: 4.5 | F18: 9 | J18: 1
A19: =IF(Content!$E$1=1,B19,C19) -> Фіксація обмінного курсу (III'22 – III'23) | B19: Фіксація обмінного курсу (III'22 – III'23) | C19: FX peg (III'22 – III'23) | D19: 11.4 | E19: 17.6 | F19: 26.9 | J19: 1
A20: =IF(Content!$E$1=1,B20,C20) -> Керована гнучкість курсу (IV'23 – III'24) | B20: Керована гнучкість курсу (IV'23 – III'24) | C20: FX managed flexibility (IV'23 – III'24) | D20: 14.4 | E20: 14 | F20: 27.8 | J20: 1
A21: =IF(Content!$E$1=1,B21,C21) -> Гнучке ІТ (IV'24 – I'26) | B21: Гнучке ІТ (IV'24 – I'26) | C21: Flexible IT (IV'24 – I'26) | D21: 24.4 | E21: 10.8 | F21: 25.9 | J21: 1
J22: 1
J23: 1
A24: =IF(Content!$E$1=1,A2,A3) -> Період | D24: =IF(Content!$E$1=1,$G$24,$G$25) -> Розвиток кредитування | E24: =IF(Content!$E$1=1,$H$24,$H$25) -> Міжнародні резерви | F24: =IF(Content!$E$1=1,$I$24,$I$25) -> Валютна лібералізація | G24: Розвиток кредитування | H24: Міжнародні резерви | I24: Валютна лібералізація | J24: 1
A25: =IF(Content!$E$1=1,B25,C25) -> Становлення ІТ (I'15 – II'17) | B25: Становлення ІТ (I'15 – II'17) | C25: The emergence of IT (I'15 – II'17) | D25: 2.7 | E25: 9.7 | F25: 11.5 | G25: Lending development | H25: International reserves | I25: Currency liberalization | J25: 1
A26: =IF(Content!$E$1=1,B26,C26) -> Стабілізація інфляції (III'17 – I'20) | B26: Стабілізація інфляції (III'17 – I'20) | C26: Inflation stabilization (III'17 – I'20) | D26: 5.3 | E26: 9.8 | F26: 6.1 | J26: 1
A27: =IF(Content!$E$1=1,B27,C27) -> COVID-19 (II'20 – I'21) | B27: COVID-19 (II'20 – I'21) | C27: COVID-19 (II'20 – I'21) | D27: 21.4 | E27: 9.1 | F27: 0 | J27: 1
A28: =IF(Content!$E$1=1,B28,C28) -> Post-COVID (II'21 – I'22) | B28: Post-COVID (II'21 – I'22) | C28: Post-COVID (II'21 – I'22) | D28: 2.8 | E28: 10.4 | F28: 3.9
A29: =IF(Content!$E$1=1,B29,C29) -> Фіксація обмінного курсу (III'22 – III'23) | B29: Фіксація обмінного курсу (III'22 – III'23) | C29: FX peg (III'22 – III'23) | D29: 0 | E29: 6.5 | F29: 9.5
A30: =IF(Content!$E$1=1,B30,C30) -> Керована гнучкість курсу (IV'23 – III'24) | B30: Керована гнучкість курсу (IV'23 – III'24) | C30: FX managed flexibility (IV'23 – III'24) | D30: 4 | E30: 7.8 | F30: 10
A31: =IF(Content!$E$1=1,B31,C31) -> Гнучке ІТ (IV'24 – I'26) | B31: Гнучке ІТ (IV'24 – I'26) | C31: Flexible ІТ (IV'24 – I'26) | D31: 4.2 | E31: 5.7 | F31: 6.7
